Workbook
Name Strength: 'Main Sheet'!$G$9
Name BaseAttack: 'Main Sheet'!$AM$6
Name tSizeChange: 'Main Sheet'!$AK$74
Name Charisma: 'Main Sheet'!$G$14
Name tSkill: 'Main Sheet'!$AQ$74
Name Level: 'Main Sheet'!$AQ$6
Name Intelligence: 'Main Sheet'!$G$12
Name Size: 'Main Sheet'!$D$5
Name tRangedDamage: 'Main Sheet'!$AE$74
Name tOHDamage: 'Main Sheet'!$AA$74
Name tRangedAttack: 'Main Sheet'!$AD$74
Name tMeleeDamage: 'Main Sheet'!$Z$74
Name t2HDamage: 'Main Sheet'!$AB$74
Name Tier: 'Main Sheet'!$AQ$5
Name SizeTable: 'Formula References'!$A$138:$G$146
Name Wisdom: 'Main Sheet'!$G$13
Name tMeleeAttack: 'Main Sheet'!$Y$74
Name Dexterity: 'Main Sheet'!$G$10
Name Constitution: 'Main Sheet'!$G$11

Sheet Welcome Page
M1: This sheet is free to use, but a Paypal link is listed below. Maintaining this old gal is a labor of love that requires many sleepless hours, so if you feel that this project is worthy, please consider donating a small amount. :) I want to thank Paizo for creating an awesome game, my friends and fellow gamers for playing it with me, and /r/pathfinder_rpg for being an awesome community.
B2: Welcome to the Pathfinder AutoSheet v6!
B3: To use this character sheet, you must first copy it to your own Google Drive. You will then have full Edit access to that version. | M3: Email: | N3: autopathfindersheet@gmail.com | P3: Reddit: | Q3: /u/darthmarth28
M4: Paypal Link: | N4: https://www.paypal.com/cgi-bin/webscr?cmd=_donations&business=SQ5H3R27U4L68&lc=US&item_name=Automated%20Pathfinder%20Character%20Sheet&currency_code=USD&bn=PP%2dDonationsBF%3abtn_donate_SM%2egif%3aNonHosted
B5: The most up to date Version is: | D5: White cells are not referenced by anything - write notes here! | H5: =HYPERLINK("https://docs.google.com/spreadsheets/d/1ZCnFreS_IkbePoHv80NFlIB8QQgTygF6BXTC43NI7s8/copy","CLICK HERE TO MAKE A COPY") -> CLICK HERE TO MAKE A COPY | N5: Alt. Rules:
C6: =IFERROR(__xludf.DUMMYFUNCTION("IMPORTRANGE(""1ZCnFreS_IkbePoHv80NFlIB8QQgTygF6BXTC43NI7s8"",""Welcome Page!C7"")"),"v6.2.1") -> v6.2.1 | D6: Yellow cells are referenced by formulas and refer to pluses | N6: Unchained Skills | P6: Background Skills
B7: This sheet is: | C7: v6.2.1 | D7: Red cells are referenced by formulas and refer to minuses | N7: Wound Thresholds | P7: INACTIVE
B8: =IF(C7=C6,"This Sheet is up to Date!",hyperlink("https://docs.google.com/spreadsheets/d/1ZCnFreS_IkbePoHv80NFlIB8QQgTygF6BXTC43NI7s8/edit#gid=1828856411","Click here for the Changelog!")) -> This Sheet is up to Date! | D8: Grey cells contain formulas, and should not be edited! | N8: Minimum 4+INT skill ranks | P8: INACTIVE
K9: Don't worry, its safe. Click "Advanced" to proceed. Ctrl+z works to undo the effects of the script
B10: Mini-FAQ (Permissions and Compatibility): | H10: Other Pathfinder Resources by me: | L10: "File" -> "Make a Copy" | N10: Protips:
B11: > No, I will not grant you access to this sheet. This is the Master. You may not build your PC on it. My Gmail automatically filters requests. | J11: Massive, comprehensive, and automatically updating. Copy/Paste the address of your copied sheet to link this seperate GooglyDoc to your PC. (See ImportRange permissions protip to the right if you're having difficulties - sharing permissions are important!) | N11: This sheet is meant to be viewed without gridlines. It will look super ugly if you have them enabled. To toggle gridlines, go to "View", then uncheck "Gridlines"
H12: =hyperlink("https://docs.google.com/spreadsheets/d/10b3sYEcrGAybAWJEVJzm7jdDWlaxRXnkDF1IRDOVYis/edit#gid=1919188920","AutoSpellcasting Sheet") -> AutoSpellcasting Sheet
B13: I followed the link to make a copy, but it still isn't letting me Edit. > If the provided link doesn't work, try making a manual copy to your personal Drive by going to "File" -> "Make a Copy". If that's still giving you grief, double check that it is "Copy of Pathfinder Autosheet" and that it is from your Google Drive - the most common error I've seen is being signed into alternate work or school Google accounts. | N13: Hover over this cell to learn how to Insert Notes Notes are a HUGE asset to minutia tracking - very important for when the GM asks how in the hell you have a +59 to Stealth checks without Invisibility.
J14: Are you a pack rat? an OCD neat-freak? Does your GM force your party to actually track encumbrance? This Equipment page has you covered. Features multiple sections to sort your gear and automatically calculates carry capacity for you, your magical bags, AND a pack animal!
H15: =hyperlink("https://docs.google.com/spreadsheets/d/1rWBgTIy3lCH1-l5D29KfuyMGgP0MWEyleF5Fxeiddyg/edit#gid=641126097","Equipment Tracker") -> Equipment Tracker
N16: Named Ranges: many important values can now be used by directly typing their names into formulas. For a complete list, see "Data" --> "Named Ranges".
B17: I can't find feature X that was in Autosheet v5, what gives? > Some of v6's functionality has been split over multiple spreadsheets. Cohorts and Animal Companions should get their own sheet, the old-school Spell Sheet is a standalone now (see right), and Encumbrance-tracking madmen can find that feature in the Equipment Tracker (ditto). While it IS possible to reintigrate these support sheets, doing so is difficult and may make the sheet laggy and less responsive. I suggest pasting a hyperlink to your support sheets into the Main Sheet's note section. | H17: =Hyperlink("https://docs.google.com/spreadsheets/d/1jRs4ilch6pSaXnAAnap_8lSWxMsKiPKuh864yXR6e1Y/edit?usp=sharing","Party Treasure, XP, and GM Reference") -> Party Treasure, XP, and GM Reference | J17: Input Treasure and XP into this chart to track your progress as you adventure. Easily divide your rewards fairly. Also has calculations for debts, loans, and of course XP tracking. Every party should have 1 shared copy of this sheet. Also contains an automated GM Reference Screen
N18: Printing this character sheet: I recommend 69% zoom, Narrow Margins, and Portrait orientation. This cuts the less-important right-hand edge of the sheet off while retaining all of the critical information. I also recommend: 1. Replacing the Quick Toggle section with large resource-tracking boxes 2. Add 13 rows above Spellcasting to place that section entirely on the second page instead of being cut in half by the page break (or delete/hide rows 59-68 if you're a tertiary caster). Maybe move the Resources, Magic Items, and Notes sections that would otherwise be deleted over to this new space. 3. Edit the HP box to =" / " & $AK$6 4. Print in Black and White, obviously
J20: You probably don't need this, but my players do. Have a look if you'd like, though! -- Feat Tax reduction -- Class Balancing (buffs/bans) -- New/Modified Feats (more buffs/bans) -- Marksman Weapons (new firearm/crossbow rules)
H21: =Hyperlink("https://drive.google.com/open?id=1vhwAw2KgXBohwIwTGGuga5SaddjMf4ul0P5CXWag6HU","My Personal Houserule Doc") -> My Personal Houserule Doc
B23: Can I do a thing with this sheet? | J23: Like Pathfinder? Like Sci-Fi? You're probably already a fan of Starfinder. The Starfinder Autosheet contains all the goodies and tricks of the Pathfinder Autosheet, combined with a sweet sci-fi color scheme.
B24: > You may use or modify this sheet for any non-commercial purpose. You may link to this sheet from other websites, but you may not rehost this sheet as your own work. | H24: =Hyperlink("https://drive.google.com/open?id=1Fv86mdaBe2QPKiUMUWea1Mhnv9PRIX4tWIYz6cgQkzI","Starfinder Autosheet") -> Starfinder Autosheet
H25: (still incomplete / in Beta)
B26: My internet is terrible. Can I use this offline? | J26: The previous-gen Autosheet, if for some reason you decide this one is ugly and everything is terrible about it... or if it breaks for some strange reason and I can't figure out why for a while. | N26: ImportRange updates only when something else on the sheet is changed, NOT a timer, so if you're trying to keep something like the "Party Treasure, XP, and GM Reference" sheet synced, all you need to do is type a quick string of gibberish in the margins, hit Enter, and re-delete it.
B27: > To use the autosheet offline, try downloading the offline Googlesheets app. The AutoSpellcasting Sheet ABSOLUTELY will not work, but everything else should. Unfortunately, this sheet isn't compatible with Microsoft Excel. Many of its important formulas rely on GoogleSheet-only commands. | H27: =HYPERLINK("https://drive.google.com/open?id=1V6l7A0kaPkPUjNlwFEqziMnE5NWnCELZ42yW4ePbexE","Pathfinder Autosheet v5") -> Pathfinder Autosheet v5
N29: ImportRange permissions may cause an error for the AutoSpellcasting, Equipment , or Party Treasure support sheets. In order to work, these sheets need permission to access the main sheet they pull values from just like a human would. You can solve this problem by setting everything's Sharing Settings to "Viewable by Everyone with the Hyperlink".
N33: Building an Undead Character? You'll want to set your Constitution score equal to your Charisma score (overwrite F11 with "=F14"), with that done, you can hide the Constitution row either by filling it Black or changing the text color to the same parchment-esque yellow as the background.
B34: DO NOT DELETE THIS TAB! When those grey cells in the top-right go missing, lots of things break. | K34: (actually just Skills, but you get the picture)
B35: Feel free to right click the red "Welcome Page" tab below and select "Hide Sheet" though. You can find it again by going to the top bar menu, View->Hidden Sheets
N37: Massive Errors in the Skills Section probably originate from either trying to customize the skill list or messing up the formatting. The cell which is causing you grief is AE9 "Acrobatics", which is importing the entire 34-row list of skills from the bottom of the Formula References tab. You can either Copy AE9:AE45 and Right-Click -> "Paste Special" -> "Paste Values Only..." to break the OFFSET formula, or you can edit the Formula References tab to change things around.

Sheet Main Sheet
AD1: Category Filter | AG1: Class | AK1: HD | AL1: Skills | AM1: BAB | AN1: Fort | AO1: Reflex | AP1: Will | AQ1: Level
B2: Charlie | J2: Neutral | N2: Runecarved Human | V2: Medium | AA2: Favored Class Bonuses | AD2: Akashic Classes | AE2: Rajah | AK2: =if($AQ2>0, int(vlookup($AE2, 'Class Charts'!$B:$N,2,False)),) -> 6 | AL2: =if('Welcome Page'!$P$6="Consolidated", if($AQ2>0, MAX(1,int((vlookup($AE2, 'Class Charts'!$B:$N,7,False)+Intelligence)/2)), ), if($AQ2>0, MAX(1,if('Welcome Page'!$P$8="ACTIVE", Max(4,vlookup($AE2, 'Class Charts'!$B:$N,7,False))+Intelligence, vlookup($AE2, 'Class Charts'!$B:$N,7,False)+Intelligence)), ) ) -> 14 | AM2: =if($AQ2>0, int(vlookup($AE2, 'Class Charts'!$B:$N,3,False)*$AQ2),) -> 1 | AN2: =if($AQ2>0, if(vlookup($AE2,'Class Charts'!$B:$N,4,false)="Good",2+INT($AQ2/2), if(vlookup($AE2,'Class Charts'!$B:$N,4,false)="Poor", int($AQ2/3), if(vlookup($AE2,'Class Charts'!$B:$N,4,false)="Prestige Good",INT(($AQ2+1)/2), if(vlookup($AE2,'Class Charts'!$B:$N,4,false)="Prestige Poor",INT(($AQ2+1)/3),)))),) -> 3 | AO2: =if($AQ2>0, if(vlookup($AE2,'Class Charts'!$B:$N,5,false)="Good",2+INT($AQ2/2), if(vlookup($AE2,'Class Charts'!$B:$N,5,false)="Poor", int($AQ2/3), if(vlookup($AE2,'Class Charts'!$B:$N,5,false)="Prestige Good",INT(($AQ2+1)/2), if(vlookup($AE2,'Class Charts'!$B:$N,5,false)="Prestige Poor",INT(($AQ2+1)/3),)))),) -> 1 | AP2: =if($AQ2>0, if(vlookup($AE2,'Class Charts'!$B:$N,6,false)="Good",2+INT($AQ2/2), if(vlookup($AE2,'Class Charts'!$B:$N,6,false)="Poor", int($AQ2/3), if(vlookup($AE2,'Class Charts'!$B:$N,6,false)="Prestige Good",INT(($AQ2+1)/2), if(vlookup($AE2,'Class Charts'!$B:$N,6,false)="Prestige Poor",INT(($AQ2+1)/3),)))),) -> 3 | AQ2: 3
B3: Character Name | J3: Alignment | N3: Race | R3: Deity | V3: XP Growth Rate | AA3: Bonus HP | AD3: 3PP-Martial | AE3: Stalker | AK3: =if($AQ3>0, int(vlookup($AE3, 'Class Charts'!$B:$N,2,False)),) -> 8 | AL3: =if('Welcome Page'!$P$6="Consolidated", if($AQ3>0, MAX(1,int((vlookup($AE3, 'Class Charts'!$B:$N,7,False)+Intelligence)/2)), ), if($AQ3>0, MAX(1,if('Welcome Page'!$P$8="ACTIVE", Max(4,vlookup($AE3, 'Class Charts'!$B:$N,7,False))+Intelligence, vlookup($AE3, 'Class Charts'!$B:$N,7,False)+Intelligence)), ) ) -> 14 | AM3: =if($AQ3>0, int(vlookup($AE3, 'Class Charts'!$B:$N,3,False)*$AQ3),) -> 2 | AN3: =if($AQ3>0, if(vlookup($AE3,'Class Charts'!$B:$N,4,false)="Good",2+INT($AQ3/2), if(vlookup($AE3,'Class Charts'!$B:$N,4,false)="Poor", int($AQ3/3), if(vlookup($AE3,'Class Charts'!$B:$N,4,false)="Prestige Good",INT(($AQ3+1)/2), if(vlookup($AE3,'Class Charts'!$B:$N,4,false)="Prestige Poor",INT(($AQ3+1)/3),)))),) -> 1 | AO3: =if($AQ3>0, if(vlookup($AE3,'Class Charts'!$B:$N,5,false)="Good",2+INT($AQ3/2), if(vlookup($AE3,'Class Charts'!$B:$N,5,false)="Poor", int($AQ3/3), if(vlookup($AE3,'Class Charts'!$B:$N,5,false)="Prestige Good",INT(($AQ3+1)/2), if(vlookup($AE3,'Class Charts'!$B:$N,5,false)="Prestige Poor",INT(($AQ3+1)/3),)))),) -> 1 | AP3: =if($AQ3>0, if(vlookup($AE3,'Class Charts'!$B:$N,6,false)="Good",2+INT($AQ3/2), if(vlookup($AE3,'Class Charts'!$B:$N,6,false)="Poor", int($AQ3/3), if(vlookup($AE3,'Class Charts'!$B:$N,6,false)="Prestige Good",INT(($AQ3+1)/2), if(vlookup($AE3,'Class Charts'!$B:$N,6,false)="Prestige Poor",INT(($AQ3+1)/3),)))),) -> 3 | AQ3: 3
W4: =iferror((HLOOKUP(V2,'Formula References'!B114:D134,AQ6+2,false)-V5)/1000&"k XP to next level","") -> 9k XP to next level | AA4: Bonus Skills | AD4: Monstrous | AK4: =if($AQ4>0, int(vlookup($AE4, 'Class Charts'!$B:$N,2,False)),) | AL4: =if('Welcome Page'!$P$6="Consolidated", if($AQ4>0, MAX(1,int((vlookup($AE4, 'Class Charts'!$B:$N,7,False)+Intelligence)/2)), ), if($AQ4>0, MAX(1,if('Welcome Page'!$P$8="ACTIVE", Max(4,vlookup($AE4, 'Class Charts'!$B:$N,7,False))+Intelligence, vlookup($AE4, 'Class Charts'!$B:$N,7,False)+Intelligence)), ) ) | AM4: =if($AQ4>0, int(vlookup($AE4, 'Class Charts'!$B:$N,3,False)*$AQ4),) | AN4: =if($AQ4>0, if(vlookup($AE4,'Class Charts'!$B:$N,4,false)="Good",2+INT($AQ4/2), if(vlookup($AE4,'Class Charts'!$B:$N,4,false)="Poor", int($AQ4/3), if(vlookup($AE4,'Class Charts'!$B:$N,4,false)="Prestige Good",INT(($AQ4+1)/2), if(vlookup($AE4,'Class Charts'!$B:$N,4,false)="Prestige Poor",INT(($AQ4+1)/3),)))),) | AO4: =if($AQ4>0, if(vlookup($AE4,'Class Charts'!$B:$N,5,false)="Good",2+INT($AQ4/2), if(vlookup($AE4,'Class Charts'!$B:$N,5,false)="Poor", int($AQ4/3), if(vlookup($AE4,'Class Charts'!$B:$N,5,false)="Prestige Good",INT(($AQ4+1)/2), if(vlookup($AE4,'Class Charts'!$B:$N,5,false)="Prestige Poor",INT(($AQ4+1)/3),)))),) | AP4: =if($AQ4>0, if(vlookup($AE4,'Class Charts'!$B:$N,6,false)="Good",2+INT($AQ4/2), if(vlookup($AE4,'Class Charts'!$B:$N,6,false)="Poor", int($AQ4/3), if(vlookup($AE4,'Class Charts'!$B:$N,6,false)="Prestige Good",INT(($AQ4+1)/2), if(vlookup($AE4,'Class Charts'!$B:$N,6,false)="Prestige Poor",INT(($AQ4+1)/3),)))),)
B5: Medium | D5: =iferror(OFFSET('Formula References'!$A$137,MIN(MAX(1,MATCH($B$5,'Formula References'!$B$138:$B$146,0)+AK74),9),0), OFFSET('Formula References'!$A$137,MIN(MAX(1,MATCH("Medium",'Formula References'!$B$138:$B$146,0)+AK74),9),0) ) -> M | F5: Adult | AA5: Other Bonus
B6: Base/Current Size | F6: Age Category | V6: Experience Points | Z6: Gestalt | AC6: TRUE | AD6: Totals | AK6: =if(AC6=FALSE, HLOOKUP($V$8,'Formula References'!H3:M4,2,false)+Z3,MAX(HLOOKUP($V$8,'Formula References'!H3:M8,3,false)+Z3,HLOOKUP($V$8,'Formula References'!H3:M8,4,false)+Z3,HLOOKUP($V$8,'Formula References'!H3:M8,5,false)+Z3)) -> 36 | AL6: {=if(AC6=FALSE, SUM(AL2:AL4*AQ2:AQ4,AS2:AS4)+Z4,MAX(AL2:AL4*AQ2:AQ4)+Z4)} -> 42 | AM6: =if(AC6=FALSE,SUM(AM2:AM5),MAX(AM2:AM5)) -> 2 | AN6: =if(AC6=FALSE,SUM(AN2:AN5),MAX(AN2:AN5)) -> 3 | AO6: =if(AC6=FALSE,SUM(AO2:AO5),MAX(AO2:AO5)) -> 1 | AP6: =if(AC6=FALSE,SUM(AP2:AP5), MAX(AP2:AP5)) -> 3 | AQ6: =if(AC6=TRUE,Max(AQ2:AQ4), SUM(AQ2:AQ4)) -> 3
AK7: HP | AL7: Ranks | AM7: BAB | AN7: Fort | AO7: Reflex | AP7: Will | AQ7: Level
B8: ABILITIES | F8: Score | G8: Modifier | I8: Base | J8: Enhance | K8: Inherent | L8: Temp. | M8: Penalty | O8: HIT POINTS | U8: HP Formula: | V8: Maximum | AD8: SKILLS | AH8: =SUM($AL$9:$AL$45)-if(OR('Welcome Page'!$P$6="Background Skills", 'Welcome Page'!$P$6="Ultimate Psionics + Background Skills")=TRUE,MIN(2*$AQ$6, sum($AL$35:$AL$45)),)&" / "&AL6 -> 42 / 42 | AJ8: Total | AL8: Ranks | AM8: Ability | AN8: Class | AO8: Misc. | AP8: Temp. | AQ8: Size & Armor
E9: STRENGTH | F9: =MAX(0,SUM(I9:L9)-ABS(M9)+iferror(vlookup(E9,'Formula References'!$A$28:$F$34,MATCH($F$5,'Formula References'!$A$28:$F$28,0),false),0)) -> 10 | G9: =MAX(-5,int((F9-10)/2)) -> 0 | H9: = | I9: 10 | L9: =IFERROR(__xludf.DUMMYFUNCTION("SUM(MAX(IFERROR(FILTER(S76:S116,$K76:$K116 = ""ACTIVE"",$G76:$G116 = ""Alchemical"",S76:S116>0)))+SUM(IFERROR(FILTER(S76:S116,$K76:$K116 = ""ACTIVE"",$G76:$G116 = ""Alchemical"",S76:S116<0))), MAX(IFERROR(FILTER(S76:S116,$K76:$K116 = ""ACTIVE"",$G76:$G116"&" = ""Armor"",S76:S116>0)))+SUM(IFERROR(FILTER(S76:S116,$K76:$K116 = ""ACTIVE"",$G76:$G116 = ""Armor"",S76:S116<0))), MAX(IFERROR(FILTER(S76:S116,$K76:$K116 = ""ACTIVE"",$G76:$G116 = ""Competence"",S76:S116>0)))+SUM(IFERROR(FILTER(S76:S116,$K76:$K116 = ""A"&"CTIVE"",$G76:$G116 = ""Competence"",S76:S116<0))), MAX(0,-$J$9+IFERROR(FILTER(S76:S116,$K76:$K116 = ""ACTIVE"",$G76:$G116 = ""Deflect/Enhance/Resist"",S76:S116>0)))+SUM(IFERROR(FILTER(S76:S116,$K76:$K116 = ""ACTIVE"",$G76:$G116 = ""Deflect/Enhance/Resist"&""",S76:S116<0))), MAX(IFERROR(FILTER(S76:S116,$K76:$K116 = ""ACTIVE"",$G76:$G116 = ""Insight"",S76:S116>0)))+SUM(IFERROR(FILTER(S76:S116,$K76:$K116 = ""ACTIVE"",$G76:$G116 = ""Insight"",S76:S116<0))), MAX(IFERROR(FILTER(S76:S116,$K76:$K116 = ""ACTIVE"",$G"&"76:$G116 = ""Luck"",S76:S116>0)))+SUM(IFERROR(FILTER(S76:S116,$K76:$K116 = ""ACTIVE"",$G76:$G116 = ""Luck"",S76:S116<0))), MAX(IFERROR(FILTER(S76:S116,$K76:$K116 = ""ACTIVE"",$G76:$G116 = ""Morale"",S76:S116>0)))+SUM(IFERROR(FILTER(S76:S116,$K76:$K116 = "&"""ACTIVE"",$G76:$G116 = ""Morale"",S76:S116<0))), MAX(IFERROR(FILTER(S76:S116,$K76:$K116 = ""ACTIVE"",$G76:$G116 = ""Precision Damage"",S76:S116>0)))+SUM(IFERROR(FILTER(S76:S116,$K76:$K116 = ""ACTIVE"",$G76:$G116 = ""Precision Damage"",S76:S116<0))), MAX("&"IFERROR(FILTER(S76:S116,$K76:$K116 = ""ACTIVE"",$G76:$G116 = ""Sacred / Profane"",S76:S116>0)))+SUM(IFERROR(FILTER(S76:S116,$K76:$K116 = ""ACTIVE"",$G76:$G116 = ""Sacred / Profane"",S76:S116<0))), MAX(IFERROR(FILTER(S76:S116,$K76:$K116 = ""ACTIVE"",$G76:$"&"G116 = ""Size"",S76:S116>0)))+SUM(IFERROR(FILTER(S76:S116,$K76:$K116 = ""ACTIVE"",$G76:$G116 = ""Size"",S76:S116<0))), SUM(IFERROR(FILTER(S76:S116,$K76:$K116 = ""ACTIVE"",$G76:$G116 = ""Untyped (stacks)"")),), SUM(IFERROR(FILTER(S76:S116,$K76:$K116 = ""AC"&"TIVE"",$G76:$G116 = ""Dodge (stacks)"")),), SUM(IFERROR(FILTER(S76:S116,$K76:$K116 = ""ACTIVE"",$G76:$G116 = ""Circumstance (stacks)"")),)) "),0.0) -> 0 | P9: Defenses | S9: =$AK$6-abs($S$13)-abs($Z$14)-iferror(5*$Y$39,"") & " / " & $AK$6-iferror(5*$Y$39,"") -> 36 / 36 | Z9: Health | AD9: =IF(OR( iferror(vlookup($AE$2, 'Class Skills'!$A:$BE,MATCH(AE9,'Class Skills'!$1:$1,0),false),"")="X", iferror(vlookup($AE$3, 'Class Skills'!$A:$BE,MATCH(AE9,'Class Skills'!$1:$1,0),false),"")="X", iferror(vlookup($AE$4, 'Class Skills'!$A:$BE,MATCH(AE9,'Class Skills'!$1:$1,0),false),"")="X", iferror(vlookup(#REF!, 'Class Skills'!$A:$BE,MATCH(AE9,'Class Skills'!$1:$1,0),false),"")="X"),"X",) -> X | AE9: =Offset('Formula References'!A271,1,Match('Welcome Page'!P6,'Formula References'!A271:E271,0)-1,34) -> Acrobatics | AI9: =HLOOKUP(AE9,'Class Skills'!$1:$3,3,false) -> Dex | AJ9: =if(AND(HLOOKUP(AE9,'Class Skills'!$1:$2,2,false)="Trained Only",AL9<1),,SUM(AL9:AQ9)) -> 9 | AK9: = | AL9: 3 | AM9: =IFERROR(__xludf.DUMMYFUNCTION("offset($E$8,match(AI9,ARRAYFORMULA(Proper(lower(REGEXEXTRACT($E$9:$E$14,""\w\w\w"")))),0),2)"),3.0) -> 3 | AN9: =if(AND(AL9 > 0,AD9 ="X"), 3, ) -> 3 | AP9: =IFERROR(__xludf.DUMMYFUNCTION("if( or(arrayformula(regexmatch($AR$76:$AR$110,AE9))), sum(arrayformula(iferror(value(regexextract(filter( $AR$76:$AR$110, $K$76:$K$110=""ACTIVE"", regexmatch($AR$76:$AR$110,AE9)), ""[-\d]+"")))))+tSkill,tSkill)"),0.0) -> 0 | AQ9: =iferror(if( if(hlookup(AE9,'Class Skills'!$1:$4,4,false)="Armor Penalty",'Formula References'!$Q$156,) +if(AND(isnumber($C$38),AE9="Climb"),8,) +if(AND(isnumber($C$39),AE9="Swim"),8,) +if(AE9="Fly", Vlookup(Size,SizeTable,5,False),) +if(AE9="Fly",if($M$37="Clumsy",-8,if($M$37="Poor",-4,if($M$37="Average",0,if($M$37="Good",4,if($M$37="Perfect",8,0)))))) +if(AE9="Stealth",Vlookup(Size,SizeTable,6,False)) =0,, if(hlookup(AE9,'Class Skills'!$1:$4,4,false)="Armor Penalty",'Formula References'!$Q$156,) +if(AND(isnumber($C$38),AE9="Climb"),8,) +if(AND(isnumber($C$39),AE9="Swim"),8,) +if(AE9="Fly", Vlookup(Size,SizeTable,5,False),) +if(AE9="Fly",if($M$37="Clumsy",-8,if($M$37="Poor",-4,if($M$37="Average",0,if($M$37="Good",4,if($M$37="Perfect",8,0)))))) +if(AE9="Stealth",Vlookup(Size,SizeTable,6,False))),"")
E10: DEXTERITY | F10: =MAX(0,SUM(I10:L10)-ABS(M10)+iferror(vlookup(E10,'Formula References'!$A$28:$F$34,MATCH($F$5,'Formula References'!$A$28:$F$28,0),false),0)) -> 16 | G10: =MAX(-5,int((F10-10)/2)) -> 3 | H10: = | I10: 16 | L10: =IFERROR(__xludf.DUMMYFUNCTION("SUM(MAX(IFERROR(FILTER(T76:T116,$K76:$K116 = ""ACTIVE"",$G76:$G116 = ""Alchemical"",T76:T116>0)))+SUM(IFERROR(FILTER(T76:T116,$K76:$K116 = ""ACTIVE"",$G76:$G116 = ""Alchemical"",T76:T116<0))), MAX(IFERROR(FILTER(T76:T116,$K76:$K116 = ""ACTIVE"",$G76:$G116"&" = ""Armor"",T76:T116>0)))+SUM(IFERROR(FILTER(T76:T116,$K76:$K116 = ""ACTIVE"",$G76:$G116 = ""Armor"",T76:T116<0))), MAX(IFERROR(FILTER(T76:T116,$K76:$K116 = ""ACTIVE"",$G76:$G116 = ""Competence"",T76:T116>0)))+SUM(IFERROR(FILTER(T76:T116,$K76:$K116 = ""A"&"CTIVE"",$G76:$G116 = ""Competence"",T76:T116<0))), MAX(0,-$J$10+IFERROR(FILTER(T76:T116,$K76:$K116 = ""ACTIVE"",$G76:$G116 = ""Deflect/Enhance/Resist"",T76:T116>0)))+SUM(IFERROR(FILTER(T76:T116,$K76:$K116 = ""ACTIVE"",$G76:$G116 = ""Deflect/Enhance/Resist"&""",T76:T116<0))), MAX(IFERROR(FILTER(T76:T116,$K76:$K116 = ""ACTIVE"",$G76:$G116 = ""Insight"",T76:T116>0)))+SUM(IFERROR(FILTER(T76:T116,$K76:$K116 = ""ACTIVE"",$G76:$G116 = ""Insight"",T76:T116<0))), MAX(IFERROR(FILTER(T76:T116,$K76:$K116 = ""ACTIVE"",$G"&"76:$G116 = ""Luck"",T76:T116>0)))+SUM(IFERROR(FILTER(T76:T116,$K76:$K116 = ""ACTIVE"",$G76:$G116 = ""Luck"",T76:T116<0))), MAX(IFERROR(FILTER(T76:T116,$K76:$K116 = ""ACTIVE"",$G76:$G116 = ""Morale"",T76:T116>0)))+SUM(IFERROR(FILTER(T76:T116,$K76:$K116 = "&"""ACTIVE"",$G76:$G116 = ""Morale"",T76:T116<0))), MAX(IFERROR(FILTER(T76:T116,$K76:$K116 = ""ACTIVE"",$G76:$G116 = ""Precision Damage"",T76:T116>0)))+SUM(IFERROR(FILTER(T76:T116,$K76:$K116 = ""ACTIVE"",$G76:$G116 = ""Precision Damage"",T76:T116<0))), MAX("&"IFERROR(FILTER(T76:T116,$K76:$K116 = ""ACTIVE"",$G76:$G116 = ""Sacred / Profane"",T76:T116>0)))+SUM(IFERROR(FILTER(T76:T116,$K76:$K116 = ""ACTIVE"",$G76:$G116 = ""Sacred / Profane"",T76:T116<0))), MAX(IFERROR(FILTER(T76:T116,$K76:$K116 = ""ACTIVE"",$G76:$"&"G116 = ""Size"",T76:T116>0)))+SUM(IFERROR(FILTER(T76:T116,$K76:$K116 = ""ACTIVE"",$G76:$G116 = ""Size"",T76:T116<0))), SUM(IFERROR(FILTER(T76:T116,$K76:$K116 = ""ACTIVE"",$G76:$G116 = ""Untyped (stacks)"")),), SUM(IFERROR(FILTER(T76:T116,$K76:$K116 = ""AC"&"TIVE"",$G76:$G116 = ""Dodge (stacks)"")),), SUM(IFERROR(FILTER(T76:T116,$K76:$K116 = ""ACTIVE"",$G76:$G116 = ""Circumstance (stacks)"")),)) "),0.0) -> 0 | O10: =IFERROR(__xludf.DUMMYFUNCTION("""DR "" & IF( AND(or(arrayformula(regexmatch($AR$74:$AR$116,""DR"")))), MAX(arrayformula(iferror(value(regexextract(filter( $AR$74:$AR$116, $K$74:$K$116=""ACTIVE"", regexmatch($AR$74:$AR$116,""DR"")), ""[-\d]+"")))))&""/"&"""&arrayformula(iferror(regexextract(filter( $AR$74:$AR$116, $K$74:$K$116=""ACTIVE"", regexmatch($AR$74:$AR$116,""DR"")), ""\(([A-Za-z]+)\)""))),""-"") &"" SR "" & IF( AND(or(arrayformula(regexmatch($AR$74:$AR$116,""SR""))))"&", MAX(arrayformula(iferror(value(regexextract(filter( $AR$74:$AR$116, $K$74:$K$116=""ACTIVE"", regexmatch($AR$74:$AR$116,""SR"")), ""[-\d]+""))))),""-"") "),"DR - SR -") -> DR - SR - | AD10: =IF(OR( iferror(vlookup($AE$2, 'Class Skills'!$A:$BE,MATCH(AE10,'Class Skills'!$1:$1,0),false),"")="X", iferror(vlookup($AE$3, 'Class Skills'!$A:$BE,MATCH(AE10,'Class Skills'!$1:$1,0),false),"")="X", iferror(vlookup($AE$4, 'Class Skills'!$A:$BE,MATCH(AE10,'Class Skills'!$1:$1,0),false),"")="X", iferror(vlookup(#REF!, 'Class Skills'!$A:$BE,MATCH(AE10,'Class Skills'!$1:$1,0),false),"")="X"),"X",) -> X | AE10: Bluff | AI10: =HLOOKUP(AE10,'Class Skills'!$1:$3,3,false) -> Cha | AJ10: =if(AND(HLOOKUP(AE10,'Class Skills'!$1:$2,2,false)="Trained Only",AL10<1),,SUM(AL10:AQ10)) -> 6 | AK10: = | AL10: 3 | AM10: =IFERROR(__xludf.DUMMYFUNCTION("offset($E$8,match(AI10,ARRAYFORMULA(Proper(lower(REGEXEXTRACT($E$9:$E$14,""\w\w\w"")))),0),2)"),0.0) -> 0 | AN10: =if(AND(AL10 > 0,AD10 ="X"), 3, ) -> 3 | AP10: =IFERROR(__xludf.DUMMYFUNCTION("if( or(arrayformula(regexmatch($AR$76:$AR$110,AE10))), sum(arrayformula(iferror(value(regexextract(filter( $AR$76:$AR$110, $K$76:$K$110=""ACTIVE"", regexmatch($AR$76:$AR$110,AE10)), ""[-\d]+"")))))+tSkill,tSkill)"),0.0) -> 0 | AQ10: =iferror(if( if(hlookup(AE10,'Class Skills'!$1:$4,4,false)="Armor Penalty",'Formula References'!$Q$156,) +if(AND(isnumber($C$38),AE10="Climb"),8,) +if(AND(isnumber($C$39),AE10="Swim"),8,) +if(AE10="Fly", Vlookup(Size,SizeTable,5,False),) +if(AE10="Fly",if($M$37="Clumsy",-8,if($M$37="Poor",-4,if($M$37="Average",0,if($M$37="Good",4,if($M$37="Perfect",8,0)))))) +if(AE10="Stealth",Vlookup(Size,SizeTable,6,False)) =0,, if(hlookup(AE10,'Class Skills'!$1:$4,4,false)="Armor Penalty",'Formula References'!$Q$156,) +if(AND(isnumber($C$38),AE10="Climb"),8,) +if(AND(isnumber($C$39),AE10="Swim"),8,) +if(AE10="Fly", Vlookup(Size,SizeTable,5,False),) +if(AE10="Fly",if($M$37="Clumsy",-8,if($M$37="Poor",-4,if($M$37="Average",0,if($M$37="Good",4,if($M$37="Perfect",8,0)))))) +if(AE10="Stealth",Vlookup(Size,SizeTable,6,False))),"")
E11: CONSTITUTION | F11: =MAX(0,SUM(I11:L11)-ABS(M11)+iferror(vlookup(E11,'Formula References'!$A$28:$F$34,MATCH($F$5,'Formula References'!$A$28:$F$28,0),false),0)) -> 18 | G11: =MAX(-5,int((F11-10)/2)) -> 4 | H11: = | I11: 18 | L11: =IFERROR(__xludf.DUMMYFUNCTION("SUM(MAX(IFERROR(FILTER(U76:U116,$K76:$K116 = ""ACTIVE"",$G76:$G116 = ""Alchemical"",U76:U116>0)))+SUM(IFERROR(FILTER(U76:U116,$K76:$K116 = ""ACTIVE"",$G76:$G116 = ""Alchemical"",U76:U116<0))), MAX(IFERROR(FILTER(U76:U116,$K76:$K116 = ""ACTIVE"",$G76:$G116"&" = ""Armor"",U76:U116>0)))+SUM(IFERROR(FILTER(U76:U116,$K76:$K116 = ""ACTIVE"",$G76:$G116 = ""Armor"",U76:U116<0))), MAX(IFERROR(FILTER(U76:U116,$K76:$K116 = ""ACTIVE"",$G76:$G116 = ""Competence"",U76:U116>0)))+SUM(IFERROR(FILTER(U76:U116,$K76:$K116 = ""A"&"CTIVE"",$G76:$G116 = ""Competence"",U76:U116<0))), MAX(0,-$J$11+IFERROR(FILTER(U76:U116,$K76:$K116 = ""ACTIVE"",$G76:$G116 = ""Deflect/Enhance/Resist"",U76:U116>0)))+SUM(IFERROR(FILTER(U76:U116,$K76:$K116 = ""ACTIVE"",$G76:$G116 = ""Deflect/Enhance/Resist"&""",U76:U116<0))), MAX(IFERROR(FILTER(U76:U116,$K76:$K116 = ""ACTIVE"",$G76:$G116 = ""Insight"",U76:U116>0)))+SUM(IFERROR(FILTER(U76:U116,$K76:$K116 = ""ACTIVE"",$G76:$G116 = ""Insight"",U76:U116<0))), MAX(IFERROR(FILTER(U76:U116,$K76:$K116 = ""ACTIVE"",$G"&"76:$G116 = ""Luck"",U76:U116>0)))+SUM(IFERROR(FILTER(U76:U116,$K76:$K116 = ""ACTIVE"",$G76:$G116 = ""Luck"",U76:U116<0))), MAX(IFERROR(FILTER(U76:U116,$K76:$K116 = ""ACTIVE"",$G76:$G116 = ""Morale"",U76:U116>0)))+SUM(IFERROR(FILTER(U76:U116,$K76:$K116 = "&"""ACTIVE"",$G76:$G116 = ""Morale"",U76:U116<0))), MAX(IFERROR(FILTER(U76:U116,$K76:$K116 = ""ACTIVE"",$G76:$G116 = ""Precision Damage"",U76:U116>0)))+SUM(IFERROR(FILTER(U76:U116,$K76:$K116 = ""ACTIVE"",$G76:$G116 = ""Precision Damage"",U76:U116<0))), MAX("&"IFERROR(FILTER(U76:U116,$K76:$K116 = ""ACTIVE"",$G76:$G116 = ""Sacred / Profane"",U76:U116>0)))+SUM(IFERROR(FILTER(U76:U116,$K76:$K116 = ""ACTIVE"",$G76:$G116 = ""Sacred / Profane"",U76:U116<0))), MAX(IFERROR(FILTER(U76:U116,$K76:$K116 = ""ACTIVE"",$G76:$"&"G116 = ""Size"",U76:U116>0)))+SUM(IFERROR(FILTER(U76:U116,$K76:$K116 = ""ACTIVE"",$G76:$G116 = ""Size"",U76:U116<0))), SUM(IFERROR(FILTER(U76:U116,$K76:$K116 = ""ACTIVE"",$G76:$G116 = ""Untyped (stacks)"")),), SUM(IFERROR(FILTER(U76:U116,$K76:$K116 = ""AC"&"TIVE"",$G76:$G116 = ""Dodge (stacks)"")),), SUM(IFERROR(FILTER(U76:U116,$K76:$K116 = ""ACTIVE"",$G76:$G116 = ""Circumstance (stacks)"")),)) "),0.0) -> 0 | AD11: =IF(OR( iferror(vlookup($AE$2, 'Class Skills'!$A:$BE,MATCH(AE11,'Class Skills'!$1:$1,0),false),"")="X", iferror(vlookup($AE$3, 'Class Skills'!$A:$BE,MATCH(AE11,'Class Skills'!$1:$1,0),false),"")="X", iferror(vlookup($AE$4, 'Class Skills'!$A:$BE,MATCH(AE11,'Class Skills'!$1:$1,0),false),"")="X", iferror(vlookup(#REF!, 'Class Skills'!$A:$BE,MATCH(AE11,'Class Skills'!$1:$1,0),false),"")="X"),"X",) -> X | AE11: Climb | AI11: =HLOOKUP(AE11,'Class Skills'!$1:$3,3,false) -> Str | AJ11: =if(AND(HLOOKUP(AE11,'Class Skills'!$1:$2,2,false)="Trained Only",AL11<1),,SUM(AL11:AQ11)) -> 0 | AK11: = | AM11: =IFERROR(__xludf.DUMMYFUNCTION("offset($E$8,match(AI11,ARRAYFORMULA(Proper(lower(REGEXEXTRACT($E$9:$E$14,""\w\w\w"")))),0),2)"),0.0) -> 0 | AN11: =if(AND(AL11 > 0,AD11 ="X"), 3, ) | AP11: =IFERROR(__xludf.DUMMYFUNCTION("if( or(arrayformula(regexmatch($AR$76:$AR$110,AE11))), sum(arrayformula(iferror(value(regexextract(filter( $AR$76:$AR$110, $K$76:$K$110=""ACTIVE"", regexmatch($AR$76:$AR$110,AE11)), ""[-\d]+"")))))+tSkill,tSkill)"),0.0) -> 0 | AQ11: =iferror(if( if(hlookup(AE11,'Class Skills'!$1:$4,4,false)="Armor Penalty",'Formula References'!$Q$156,) +if(AND(isnumber($C$38),AE11="Climb"),8,) +if(AND(isnumber($C$39),AE11="Swim"),8,) +if(AE11="Fly", Vlookup(Size,SizeTable,5,False),) +if(AE11="Fly",if($M$37="Clumsy",-8,if($M$37="Poor",-4,if($M$37="Average",0,if($M$37="Good",4,if($M$37="Perfect",8,0)))))) +if(AE11="Stealth",Vlookup(Size,SizeTable,6,False)) =0,, if(hlookup(AE11,'Class Skills'!$1:$4,4,false)="Armor Penalty",'Formula References'!$Q$156,) +if(AND(isnumber($C$38),AE11="Climb"),8,) +if(AND(isnumber($C$39),AE11="Swim"),8,) +if(AE11="Fly", Vlookup(Size,SizeTable,5,False),) +if(AE11="Fly",if($M$37="Clumsy",-8,if($M$37="Poor",-4,if($M$37="Average",0,if($M$37="Good",4,if($M$37="Perfect",8,0)))))) +if(AE11="Stealth",Vlookup(Size,SizeTable,6,False))),"")
E12: INTELLIGENCE | F12: =MAX(0,SUM(I12:L12)-ABS(M12)+iferror(vlookup(E12,'Formula References'!$A$28:$F$34,MATCH($F$5,'Formula References'!$A$28:$F$28,0),false),0)) -> 26 | G12: =MAX(-5,int((F12-10)/2)) -> 8 | H12: = | I12: 26 | L12: =IFERROR(__xludf.DUMMYFUNCTION("SUM(MAX(IFERROR(FILTER(V76:V116,$K76:$K116 = ""ACTIVE"",$G76:$G116 = ""Alchemical"",V76:V116>0)))+SUM(IFERROR(FILTER(V76:V116,$K76:$K116 = ""ACTIVE"",$G76:$G116 = ""Alchemical"",V76:V116<0))), MAX(IFERROR(FILTER(V76:V116,$K76:$K116 = ""ACTIVE"",$G76:$G116"&" = ""Armor"",V76:V116>0)))+SUM(IFERROR(FILTER(V76:V116,$K76:$K116 = ""ACTIVE"",$G76:$G116 = ""Armor"",V76:V116<0))), MAX(IFERROR(FILTER(V76:V116,$K76:$K116 = ""ACTIVE"",$G76:$G116 = ""Competence"",V76:V116>0)))+SUM(IFERROR(FILTER(V76:V116,$K76:$K116 = ""A"&"CTIVE"",$G76:$G116 = ""Competence"",V76:V116<0))), MAX(0,-$J$12+IFERROR(FILTER(V76:V116,$K76:$K116 = ""ACTIVE"",$G76:$G116 = ""Deflect/Enhance/Resist"",V76:V116>0)))+SUM(IFERROR(FILTER(V76:V116,$K76:$K116 = ""ACTIVE"",$G76:$G116 = ""Deflect/Enhance/Resist"&""",V76:V116<0))), MAX(IFERROR(FILTER(V76:V116,$K76:$K116 = ""ACTIVE"",$G76:$G116 = ""Insight"",V76:V116>0)))+SUM(IFERROR(FILTER(V76:V116,$K76:$K116 = ""ACTIVE"",$G76:$G116 = ""Insight"",V76:V116<0))), MAX(IFERROR(FILTER(V76:V116,$K76:$K116 = ""ACTIVE"",$G"&"76:$G116 = ""Luck"",V76:V116>0)))+SUM(IFERROR(FILTER(V76:V116,$K76:$K116 = ""ACTIVE"",$G76:$G116 = ""Luck"",V76:V116<0))), MAX(IFERROR(FILTER(V76:V116,$K76:$K116 = ""ACTIVE"",$G76:$G116 = ""Morale"",V76:V116>0)))+SUM(IFERROR(FILTER(V76:V116,$K76:$K116 = "&"""ACTIVE"",$G76:$G116 = ""Morale"",V76:V116<0))), MAX(IFERROR(FILTER(V76:V116,$K76:$K116 = ""ACTIVE"",$G76:$G116 = ""Precision Damage"",V76:V116>0)))+SUM(IFERROR(FILTER(V76:V116,$K76:$K116 = ""ACTIVE"",$G76:$G116 = ""Precision Damage"",V76:V116<0))), MAX("&"IFERROR(FILTER(V76:V116,$K76:$K116 = ""ACTIVE"",$G76:$G116 = ""Sacred / Profane"",V76:V116>0)))+SUM(IFERROR(FILTER(V76:V116,$K76:$K116 = ""ACTIVE"",$G76:$G116 = ""Sacred / Profane"",V76:V116<0))), MAX(IFERROR(FILTER(V76:V116,$K76:$K116 = ""ACTIVE"",$G76:$"&"G116 = ""Size"",V76:V116>0)))+SUM(IFERROR(FILTER(V76:V116,$K76:$K116 = ""ACTIVE"",$G76:$G116 = ""Size"",V76:V116<0))), SUM(IFERROR(FILTER(V76:V116,$K76:$K116 = ""ACTIVE"",$G76:$G116 = ""Untyped (stacks)"")),), SUM(IFERROR(FILTER(V76:V116,$K76:$K116 = ""AC"&"TIVE"",$G76:$G116 = ""Dodge (stacks)"")),), SUM(IFERROR(FILTER(V76:V116,$K76:$K116 = ""ACTIVE"",$G76:$G116 = ""Circumstance (stacks)"")),)) "),0.0) -> 0 | P12: Resistances | W12: =IFERROR(__xludf.DUMMYFUNCTION("IF($K$116=""ACTIVE"", IF(value(REGEXEXTRACT('Main Sheet'!$S$9,""\d+""))/value(regexextract(regexextract('Main Sheet'!$S$9,""/ \d+""),""\d+""))<0.25,""Critical! -3 to all actions and defenses!"", IF(value(REGEXEXTRACT('Main Sheet'!$S$9,""\d+""))/value(rege"&"xextract(regexextract('Main Sheet'!$S$9,""/ \d+""),""\d+""))<0.5,""Wounded: -2 to all actions and defenses"", IF(value(REGEXEXTRACT('Main Sheet'!$S$9,""\d+""))/value(regexextract(regexextract('Main Sheet'!$S$9,""/ \d+""),""\d+""))<0.75,""Grazed: -1 to all"&" actions and defenses"", ""Healthy: no penalties""))),) "),"") | AD12: =IF(OR( iferror(vlookup($AE$2, 'Class Skills'!$A:$BE,MATCH(AE12,'Class Skills'!$1:$1,0),false),"")="X", iferror(vlookup($AE$3, 'Class Skills'!$A:$BE,MATCH(AE12,'Class Skills'!$1:$1,0),false),"")="X", iferror(vlookup($AE$4, 'Class Skills'!$A:$BE,MATCH(AE12,'Class Skills'!$1:$1,0),false),"")="X", iferror(vlookup(#REF!, 'Class Skills'!$A:$BE,MATCH(AE12,'Class Skills'!$1:$1,0),false),"")="X"),"X",) -> X | AE12: Diplomacy | AI12: =HLOOKUP(AE12,'Class Skills'!$1:$3,3,false) -> Cha | AJ12: =if(AND(HLOOKUP(AE12,'Class Skills'!$1:$2,2,false)="Trained Only",AL12<1),,SUM(AL12:AQ12)) -> 6 | AK12: = | AL12: 3 | AM12: =IFERROR(__xludf.DUMMYFUNCTION("offset($E$8,match(AI12,ARRAYFORMULA(Proper(lower(REGEXEXTRACT($E$9:$E$14,""\w\w\w"")))),0),2)"),0.0) -> 0 | AN12: =if(AND(AL12 > 0,AD12 ="X"), 3, ) -> 3 | AP12: =IFERROR(__xludf.DUMMYFUNCTION("if( or(arrayformula(regexmatch($AR$76:$AR$110,AE12))), sum(arrayformula(iferror(value(regexextract(filter( $AR$76:$AR$110, $K$76:$K$110=""ACTIVE"", regexmatch($AR$76:$AR$110,AE12)), ""[-\d]+"")))))+tSkill,tSkill)"),0.0) -> 0 | AQ12: =iferror(if( if(hlookup(AE12,'Class Skills'!$1:$4,4,false)="Armor Penalty",'Formula References'!$Q$156,) +if(AND(isnumber($C$38),AE12="Climb"),8,) +if(AND(isnumber($C$39),AE12="Swim"),8,) +if(AE12="Fly", Vlookup(Size,SizeTable,5,False),) +if(AE12="Fly",if($M$37="Clumsy",-8,if($M$37="Poor",-4,if($M$37="Average",0,if($M$37="Good",4,if($M$37="Perfect",8,0)))))) +if(AE12="Stealth",Vlookup(Size,SizeTable,6,False)) =0,, if(hlookup(AE12,'Class Skills'!$1:$4,4,false)="Armor Penalty",'Formula References'!$Q$156,) +if(AND(isnumber($C$38),AE12="Climb"),8,) +if(AND(isnumber($C$39),AE12="Swim"),8,) +if(AE12="Fly", Vlookup(Size,SizeTable,5,False),) +if(AE12="Fly",if($M$37="Clumsy",-8,if($M$37="Poor",-4,if($M$37="Average",0,if($M$37="Good",4,if($M$37="Perfect",8,0)))))) +if(AE12="Stealth",Vlookup(Size,SizeTable,6,False))),"")
E13: WISDOM | F13: =MAX(0,SUM(I13:L13)-ABS(M13)+iferror(vlookup(E13,'Formula References'!$A$28:$F$34,MATCH($F$5,'Formula References'!$A$28:$F$28,0),false),0)) -> 10 | G13: =MAX(-5,int((F13-10)/2)) -> 0 | H13: = | I13: 10 | L13: =IFERROR(__xludf.DUMMYFUNCTION("SUM(MAX(IFERROR(FILTER(W76:W116,$K76:$K116 = ""ACTIVE"",$G76:$G116 = ""Alchemical"",W76:W116>0)))+SUM(IFERROR(FILTER(W76:W116,$K76:$K116 = ""ACTIVE"",$G76:$G116 = ""Alchemical"",W76:W116<0))), MAX(IFERROR(FILTER(W76:W116,$K76:$K116 = ""ACTIVE"",$G76:$G116"&" = ""Armor"",W76:W116>0)))+SUM(IFERROR(FILTER(W76:W116,$K76:$K116 = ""ACTIVE"",$G76:$G116 = ""Armor"",W76:W116<0))), MAX(IFERROR(FILTER(W76:W116,$K76:$K116 = ""ACTIVE"",$G76:$G116 = ""Competence"",W76:W116>0)))+SUM(IFERROR(FILTER(W76:W116,$K76:$K116 = ""A"&"CTIVE"",$G76:$G116 = ""Competence"",W76:W116<0))), MAX(0,-$J$13+IFERROR(FILTER(W76:W116,$K76:$K116 = ""ACTIVE"",$G76:$G116 = ""Deflect/Enhance/Resist"",W76:W116>0)))+SUM(IFERROR(FILTER(W76:W116,$K76:$K116 = ""ACTIVE"",$G76:$G116 = ""Deflect/Enhance/Resist"&""",W76:W116<0))), MAX(IFERROR(FILTER(W76:W116,$K76:$K116 = ""ACTIVE"",$G76:$G116 = ""Insight"",W76:W116>0)))+SUM(IFERROR(FILTER(W76:W116,$K76:$K116 = ""ACTIVE"",$G76:$G116 = ""Insight"",W76:W116<0))), MAX(IFERROR(FILTER(W76:W116,$K76:$K116 = ""ACTIVE"",$G"&"76:$G116 = ""Luck"",W76:W116>0)))+SUM(IFERROR(FILTER(W76:W116,$K76:$K116 = ""ACTIVE"",$G76:$G116 = ""Luck"",W76:W116<0))), MAX(IFERROR(FILTER(W76:W116,$K76:$K116 = ""ACTIVE"",$G76:$G116 = ""Morale"",W76:W116>0)))+SUM(IFERROR(FILTER(W76:W116,$K76:$K116 = "&"""ACTIVE"",$G76:$G116 = ""Morale"",W76:W116<0))), MAX(IFERROR(FILTER(W76:W116,$K76:$K116 = ""ACTIVE"",$G76:$G116 = ""Precision Damage"",W76:W116>0)))+SUM(IFERROR(FILTER(W76:W116,$K76:$K116 = ""ACTIVE"",$G76:$G116 = ""Precision Damage"",W76:W116<0))), MAX("&"IFERROR(FILTER(W76:W116,$K76:$K116 = ""ACTIVE"",$G76:$G116 = ""Sacred / Profane"",W76:W116>0)))+SUM(IFERROR(FILTER(W76:W116,$K76:$K116 = ""ACTIVE"",$G76:$G116 = ""Sacred / Profane"",W76:W116<0))), MAX(IFERROR(FILTER(W76:W116,$K76:$K116 = ""ACTIVE"",$G76:$"&"G116 = ""Size"",W76:W116>0)))+SUM(IFERROR(FILTER(W76:W116,$K76:$K116 = ""ACTIVE"",$G76:$G116 = ""Size"",W76:W116<0))), SUM(IFERROR(FILTER(W76:W116,$K76:$K116 = ""ACTIVE"",$G76:$G116 = ""Untyped (stacks)"")),), SUM(IFERROR(FILTER(W76:W116,$K76:$K116 = ""AC"&"TIVE"",$G76:$G116 = ""Dodge (stacks)"")),), SUM(IFERROR(FILTER(W76:W116,$K76:$K116 = ""ACTIVE"",$G76:$G116 = ""Circumstance (stacks)"")),)) "),0.0) -> 0 | O13: =IFERROR(__xludf.DUMMYFUNCTION("""Fire "" & IF( AND(or(arrayformula(regexmatch($AR$74:$AR$116,""Resistance""))), or(arrayformula(regexmatch($AR$74:$AR$116,""Fire"")))), MAX(arrayformula(iferror(value(regexextract(filter( $AR$74:$AR$116, $K$74:$K$116=""ACTIVE"", "&" regexmatch($AR$74:$AR$116,""Resistance""), regexmatch($AR$74:$AR$116,""Fire"")), ""[-\d]+""))))),""0"") & "" Cold "" & IF( AND(or(arrayformula(regexmatch($AR$74:$AR$116,""Resistance""))), or(arrayformula(regexmatch($AR$74:$AR$116,""Co"&"ld"")))), MAX(arrayformula(iferror(value(regexextract(filter( $AR$74:$AR$116, $K$74:$K$116=""ACTIVE"", regexmatch($AR$74:$AR$116,""Resistance""), regexmatch($AR$74:$AR$116,""Cold"")), ""[-\d]+""))))),""0"") & """&" Acid "" & IF( AND(or(arrayformula(regexmatch($AR$74:$AR$116,""Resistance""))), or(arrayformula(regexmatch($AR$74:$AR$116,""Acid"")))), MAX(arrayformula(iferror(value(regexextract(filter( $AR$74:$AR$116, $K$74:$K$116=""ACTIVE"", "&" regexmatch($AR$74:$AR$116,""Resistance""), regexmatch($AR$74:$AR$116,""Acid"")), ""[-\d]+""))))),""0"") & "" Elect "" & IF( AND(or(arrayformula(regexmatch($AR$74:$AR$116,""Resistance""))), or(arrayformula(regexmatch($AR$74:$AR$116,""Ele"&"ctricity"")))), MAX(arrayformula(iferror(value(regexextract(filter( $AR$74:$AR$116, $K$74:$K$116=""ACTIVE"", regexmatch($AR$74:$AR$116,""Resistance""), regexmatch($AR$74:$AR$116,""Electricity"")), ""[-\d]+""))))"&"),""0"")"),"Fire 0 Cold 0 Acid 0 Elect 0") -> Fire 0 Cold 0 Acid 0 Elect 0 | W13: Damage | AB13: Nonlethal | AD13: =IF(OR( iferror(vlookup($AE$2, 'Class Skills'!$A:$BE,MATCH(AE13,'Class Skills'!$1:$1,0),false),"")="X", iferror(vlookup($AE$3, 'Class Skills'!$A:$BE,MATCH(AE13,'Class Skills'!$1:$1,0),false),"")="X", iferror(vlookup($AE$4, 'Class Skills'!$A:$BE,MATCH(AE13,'Class Skills'!$1:$1,0),false),"")="X", iferror(vlookup(#REF!, 'Class Skills'!$A:$BE,MATCH(AE13,'Class Skills'!$1:$1,0),false),"")="X"),"X",) -> X | AE13: Disable Device | AI13: =HLOOKUP(AE13,'Class Skills'!$1:$3,3,false) -> Dex | AJ13: =if(AND(HLOOKUP(AE13,'Class Skills'!$1:$2,2,false)="Trained Only",AL13<1),,SUM(AL13:AQ13)) | AK13: = | AM13: =IFERROR(__xludf.DUMMYFUNCTION("offset($E$8,match(AI13,ARRAYFORMULA(Proper(lower(REGEXEXTRACT($E$9:$E$14,""\w\w\w"")))),0),2)"),3.0) -> 3 | AN13: =if(AND(AL13 > 0,AD13 ="X"), 3, ) | AP13: =IFERROR(__xludf.DUMMYFUNCTION("if( or(arrayformula(regexmatch($AR$76:$AR$110,AE13))), sum(arrayformula(iferror(value(regexextract(filter( $AR$76:$AR$110, $K$76:$K$110=""ACTIVE"", regexmatch($AR$76:$AR$110,AE13)), ""[-\d]+"")))))+tSkill,tSkill)"),0.0) -> 0 | AQ13: =iferror(if( if(hlookup(AE13,'Class Skills'!$1:$4,4,false)="Armor Penalty",'Formula References'!$Q$156,) +if(AND(isnumber($C$38),AE13="Climb"),8,) +if(AND(isnumber($C$39),AE13="Swim"),8,) +if(AE13="Fly", Vlookup(Size,SizeTable,5,False),) +if(AE13="Fly",if($M$37="Clumsy",-8,if($M$37="Poor",-4,if($M$37="Average",0,if($M$37="Good",4,if($M$37="Perfect",8,0)))))) +if(AE13="Stealth",Vlookup(Size,SizeTable,6,False)) =0,, if(hlookup(AE13,'Class Skills'!$1:$4,4,false)="Armor Penalty",'Formula References'!$Q$156,) +if(AND(isnumber($C$38),AE13="Climb"),8,) +if(AND(isnumber($C$39),AE13="Swim"),8,) +if(AE13="Fly", Vlookup(Size,SizeTable,5,False),) +if(AE13="Fly",if($M$37="Clumsy",-8,if($M$37="Poor",-4,if($M$37="Average",0,if($M$37="Good",4,if($M$37="Perfect",8,0)))))) +if(AE13="Stealth",Vlookup(Size,SizeTable,6,False))),"")
E14: CHARISMA | F14: =MAX(0,SUM(I14:L14)-ABS(M14)+iferror(vlookup(E14,'Formula References'!$A$28:$F$34,MATCH($F$5,'Formula References'!$A$28:$F$28,0),false),0)) -> 10 | G14: =MAX(-5,int((F14-10)/2)) -> 0 | H14: = | I14: 10 | L14: =IFERROR(__xludf.DUMMYFUNCTION("SUM(MAX(IFERROR(FILTER(X76:X116,$K76:$K116 = ""ACTIVE"",$G76:$G116 = ""Alchemical"",X76:X116>0)))+SUM(IFERROR(FILTER(X76:X116,$K76:$K116 = ""ACTIVE"",$G76:$G116 = ""Alchemical"",X76:X116<0))), MAX(IFERROR(FILTER(X76:X116,$K76:$K116 = ""ACTIVE"",$G76:$G116"&" = ""Armor"",X76:X116>0)))+SUM(IFERROR(FILTER(X76:X116,$K76:$K116 = ""ACTIVE"",$G76:$G116 = ""Armor"",X76:X116<0))), MAX(IFERROR(FILTER(X76:X116,$K76:$K116 = ""ACTIVE"",$G76:$G116 = ""Competence"",X76:X116>0)))+SUM(IFERROR(FILTER(X76:X116,$K76:$K116 = ""A"&"CTIVE"",$G76:$G116 = ""Competence"",X76:X116<0))), MAX(0,-$J$14+IFERROR(FILTER(X76:X116,$K76:$K116 = ""ACTIVE"",$G76:$G116 = ""Deflect/Enhance/Resist"",X76:X116>0)))+SUM(IFERROR(FILTER(X76:X116,$K76:$K116 = ""ACTIVE"",$G76:$G116 = ""Deflect/Enhance/Resist"&""",X76:X116<0))), MAX(IFERROR(FILTER(X76:X116,$K76:$K116 = ""ACTIVE"",$G76:$G116 = ""Insight"",X76:X116>0)))+SUM(IFERROR(FILTER(X76:X116,$K76:$K116 = ""ACTIVE"",$G76:$G116 = ""Insight"",X76:X116<0))), MAX(IFERROR(FILTER(X76:X116,$K76:$K116 = ""ACTIVE"",$G"&"76:$G116 = ""Luck"",X76:X116>0)))+SUM(IFERROR(FILTER(X76:X116,$K76:$K116 = ""ACTIVE"",$G76:$G116 = ""Luck"",X76:X116<0))), MAX(IFERROR(FILTER(X76:X116,$K76:$K116 = ""ACTIVE"",$G76:$G116 = ""Morale"",X76:X116>0)))+SUM(IFERROR(FILTER(X76:X116,$K76:$K116 = "&"""ACTIVE"",$G76:$G116 = ""Morale"",X76:X116<0))), MAX(IFERROR(FILTER(X76:X116,$K76:$K116 = ""ACTIVE"",$G76:$G116 = ""Precision Damage"",X76:X116>0)))+SUM(IFERROR(FILTER(X76:X116,$K76:$K116 = ""ACTIVE"",$G76:$G116 = ""Precision Damage"",X76:X116<0))), MAX("&"IFERROR(FILTER(X76:X116,$K76:$K116 = ""ACTIVE"",$G76:$G116 = ""Sacred / Profane"",X76:X116>0)))+SUM(IFERROR(FILTER(X76:X116,$K76:$K116 = ""ACTIVE"",$G76:$G116 = ""Sacred / Profane"",X76:X116<0))), MAX(IFERROR(FILTER(X76:X116,$K76:$K116 = ""ACTIVE"",$G76:$"&"G116 = ""Size"",X76:X116>0)))+SUM(IFERROR(FILTER(X76:X116,$K76:$K116 = ""ACTIVE"",$G76:$G116 = ""Size"",X76:X116<0))), SUM(IFERROR(FILTER(X76:X116,$K76:$K116 = ""ACTIVE"",$G76:$G116 = ""Untyped (stacks)"")),), SUM(IFERROR(FILTER(X76:X116,$K76:$K116 = ""AC"&"TIVE"",$G76:$G116 = ""Dodge (stacks)"")),), SUM(IFERROR(FILTER(X76:X116,$K76:$K116 = ""ACTIVE"",$G76:$G116 = ""Circumstance (stacks)"")),)) "),0.0) -> 0 | AD14: =IF(OR( iferror(vlookup($AE$2, 'Class Skills'!$A:$BE,MATCH(AE14,'Class Skills'!$1:$1,0),false),"")="X", iferror(vlookup($AE$3, 'Class Skills'!$A:$BE,MATCH(AE14,'Class Skills'!$1:$1,0),false),"")="X", iferror(vlookup($AE$4, 'Class Skills'!$A:$BE,MATCH(AE14,'Class Skills'!$1:$1,0),false),"")="X", iferror(vlookup(#REF!, 'Class Skills'!$A:$BE,MATCH(AE14,'Class Skills'!$1:$1,0),false),"")="X"),"X",) -> X | AE14: Disguise | AI14: =HLOOKUP(AE14,'Class Skills'!$1:$3,3,false) -> Cha | AJ14: =if(AND(HLOOKUP(AE14,'Class Skills'!$1:$2,2,false)="Trained Only",AL14<1),,SUM(AL14:AQ14)) -> 6 | AK14: = | AL14: 3 | AM14: =IFERROR(__xludf.DUMMYFUNCTION("offset($E$8,match(AI14,ARRAYFORMULA(Proper(lower(REGEXEXTRACT($E$9:$E$14,""\w\w\w"")))),0),2)"),0.0) -> 0 | AN14: =if(AND(AL14 > 0,AD14 ="X"), 3, ) -> 3 | AP14: =IFERROR(__xludf.DUMMYFUNCTION("if( or(arrayformula(regexmatch($AR$76:$AR$110,AE14))), sum(arrayformula(iferror(value(regexextract(filter( $AR$76:$AR$110, $K$76:$K$110=""ACTIVE"", regexmatch($AR$76:$AR$110,AE14)), ""[-\d]+"")))))+tSkill,tSkill)"),0.0) -> 0 | AQ14: =iferror(if( if(hlookup(AE14,'Class Skills'!$1:$4,4,false)="Armor Penalty",'Formula References'!$Q$156,) +if(AND(isnumber($C$38),AE14="Climb"),8,) +if(AND(isnumber($C$39),AE14="Swim"),8,) +if(AE14="Fly", Vlookup(Size,SizeTable,5,False),) +if(AE14="Fly",if($M$37="Clumsy",-8,if($M$37="Poor",-4,if($M$37="Average",0,if($M$37="Good",4,if($M$37="Perfect",8,0)))))) +if(AE14="Stealth",Vlookup(Size,SizeTable,6,False)) =0,, if(hlookup(AE14,'Class Skills'!$1:$4,4,false)="Armor Penalty",'Formula References'!$Q$156,) +if(AND(isnumber($C$38),AE14="Climb"),8,) +if(AND(isnumber($C$39),AE14="Swim"),8,) +if(AE14="Fly", Vlookup(Size,SizeTable,5,False),) +if(AE14="Fly",if($M$37="Clumsy",-8,if($M$37="Poor",-4,if($M$37="Average",0,if($M$37="Good",4,if($M$37="Perfect",8,0)))))) +if(AE14="Stealth",Vlookup(Size,SizeTable,6,False))),"")
AD15: =IF(OR( iferror(vlookup($AE$2, 'Class Skills'!$A:$BE,MATCH(AE15,'Class Skills'!$1:$1,0),false),"")="X", iferror(vlookup($AE$3, 'Class Skills'!$A:$BE,MATCH(AE15,'Class Skills'!$1:$1,0),false),"")="X", iferror(vlookup($AE$4, 'Class Skills'!$A:$BE,MATCH(AE15,'Class Skills'!$1:$1,0),false),"")="X", iferror(vlookup(#REF!, 'Class Skills'!$A:$BE,MATCH(AE15,'Class Skills'!$1:$1,0),false),"")="X"),"X",) -> X | AE15: Escape Artist | AI15: =HLOOKUP(AE15,'Class Skills'!$1:$3,3,false) -> Dex | AJ15: =if(AND(HLOOKUP(AE15,'Class Skills'!$1:$2,2,false)="Trained Only",AL15<1),,SUM(AL15:AQ15)) -> 9 | AK15: = | AL15: 3 | AM15: =IFERROR(__xludf.DUMMYFUNCTION("offset($E$8,match(AI15,ARRAYFORMULA(Proper(lower(REGEXEXTRACT($E$9:$E$14,""\w\w\w"")))),0),2)"),3.0) -> 3 | AN15: =if(AND(AL15 > 0,AD15 ="X"), 3, ) -> 3 | AP15: =IFERROR(__xludf.DUMMYFUNCTION("if( or(arrayformula(regexmatch($AR$76:$AR$110,AE15))), sum(arrayformula(iferror(value(regexextract(filter( $AR$76:$AR$110, $K$76:$K$110=""ACTIVE"", regexmatch($AR$76:$AR$110,AE15)), ""[-\d]+"")))))+tSkill,tSkill)"),0.0) -> 0 | AQ15: =iferror(if( if(hlookup(AE15,'Class Skills'!$1:$4,4,false)="Armor Penalty",'Formula References'!$Q$156,) +if(AND(isnumber($C$38),AE15="Climb"),8,) +if(AND(isnumber($C$39),AE15="Swim"),8,) +if(AE15="Fly", Vlookup(Size,SizeTable,5,False),) +if(AE15="Fly",if($M$37="Clumsy",-8,if($M$37="Poor",-4,if($M$37="Average",0,if($M$37="Good",4,if($M$37="Perfect",8,0)))))) +if(AE15="Stealth",Vlookup(Size,SizeTable,6,False)) =0,, if(hlookup(AE15,'Class Skills'!$1:$4,4,false)="Armor Penalty",'Formula References'!$Q$156,) +if(AND(isnumber($C$38),AE15="Climb"),8,) +if(AND(isnumber($C$39),AE15="Swim"),8,) +if(AE15="Fly", Vlookup(Size,SizeTable,5,False),) +if(AE15="Fly",if($M$37="Clumsy",-8,if($M$37="Poor",-4,if($M$37="Average",0,if($M$37="Good",4,if($M$37="Perfect",8,0)))))) +if(AE15="Stealth",Vlookup(Size,SizeTable,6,False))),"")
B16: SAVES | F16: Total | H16: Base | I16: Ability | J16: Resist | K16: Misc. | L16: Temp. | O16: DEFENSES | R16: Total | T16: Armor | U16: Shield | V16: Dex | W16: Size | X16: Natural | Y16: Deflect | Z16: Dodge | AA16: Misc. | AB16: Temp. | AD16: =IF(OR( iferror(vlookup($AE$2, 'Class Skills'!$A:$BE,MATCH(AE16,'Class Skills'!$1:$1,0),false),"")="X", iferror(vlookup($AE$3, 'Class Skills'!$A:$BE,MATCH(AE16,'Class Skills'!$1:$1,0),false),"")="X", iferror(vlookup($AE$4, 'Class Skills'!$A:$BE,MATCH(AE16,'Class Skills'!$1:$1,0),false),"")="X", iferror(vlookup(#REF!, 'Class Skills'!$A:$BE,MATCH(AE16,'Class Skills'!$1:$1,0),false),"")="X"),"X",) | AE16: Fly | AI16: =HLOOKUP(AE16,'Class Skills'!$1:$3,3,false) -> Dex | AJ16: =if(AND(HLOOKUP(AE16,'Class Skills'!$1:$2,2,false)="Trained Only",AL16<1),,SUM(AL16:AQ16)) -> 3 | AK16: = | AM16: =IFERROR(__xludf.DUMMYFUNCTION("offset($E$8,match(AI16,ARRAYFORMULA(Proper(lower(REGEXEXTRACT($E$9:$E$14,""\w\w\w"")))),0),2)"),3.0) -> 3 | AN16: =if(AND(AL16 > 0,AD16 ="X"), 3, ) | AP16: =IFERROR(__xludf.DUMMYFUNCTION("if( or(arrayformula(regexmatch($AR$76:$AR$110,AE16))), sum(arrayformula(iferror(value(regexextract(filter( $AR$76:$AR$110, $K$76:$K$110=""ACTIVE"", regexmatch($AR$76:$AR$110,AE16)), ""[-\d]+"")))))+tSkill,tSkill)"),0.0) -> 0 | AQ16: =iferror(if( if(hlookup(AE16,'Class Skills'!$1:$4,4,false)="Armor Penalty",'Formula References'!$Q$156,) +if(AND(isnumber($C$38),AE16="Climb"),8,) +if(AND(isnumber($C$39),AE16="Swim"),8,) +if(AE16="Fly", Vlookup(Size,SizeTable,5,False),) +if(AE16="Fly",if($M$37="Clumsy",-8,if($M$37="Poor",-4,if($M$37="Average",0,if($M$37="Good",4,if($M$37="Perfect",8,0)))))) +if(AE16="Stealth",Vlookup(Size,SizeTable,6,False)) =0,, if(hlookup(AE16,'Class Skills'!$1:$4,4,false)="Armor Penalty",'Formula References'!$Q$156,) +if(AND(isnumber($C$38),AE16="Climb"),8,) +if(AND(isnumber($C$39),AE16="Swim"),8,) +if(AE16="Fly", Vlookup(Size,SizeTable,5,False),) +if(AE16="Fly",if($M$37="Clumsy",-8,if($M$37="Poor",-4,if($M$37="Average",0,if($M$37="Good",4,if($M$37="Perfect",8,0)))))) +if(AE16="Stealth",Vlookup(Size,SizeTable,6,False))),"")
E17: FORTITUDE | F17: =SUM(H17:L17) -> 7 | G17: = | H17: =AN6 -> 3 | I17: =Constitution -> 4 | J17: =IFERROR(__xludf.DUMMYFUNCTION("SUM( MAX(IFERROR(FILTER(P76:P116,$K76:$K116 = ""ACTIVE"",$G76:$G116 = ""Deflect/Enhance/Resist"",P76:P116>0))) +SUM(IFERROR(FILTER(P76:P116,$K76:$K116 = ""ACTIVE"",$G76:$G116 = ""Deflect/Enhance/Resist"",P76:P116<0))) )"),0.0) -> 0 | L17: =IFERROR(__xludf.DUMMYFUNCTION("SUM(MAX(IFERROR(FILTER(P76:P116,$K76:$K116 = ""ACTIVE"",$G76:$G116 = ""Alchemical"",P76:P116>0)))+SUM(IFERROR(FILTER(P76:P116,$K76:$K116 = ""ACTIVE"",$G76:$G116 = ""Alchemical"",P76:P116<0))), MAX(IFERROR(FILTER(P76:P116,$K76:$K116 = ""ACTIVE"",$G76:$G116"&" = ""Armor"",P76:P116>0)))+SUM(IFERROR(FILTER(P76:P116,$K76:$K116 = ""ACTIVE"",$G76:$G116 = ""Armor"",P76:P116<0))), MAX(IFERROR(FILTER(P76:P116,$K76:$K116 = ""ACTIVE"",$G76:$G116 = ""Competence"",P76:P116>0)))+SUM(IFERROR(FILTER(P76:P116,$K76:$K116 = ""A"&"CTIVE"",$G76:$G116 = ""Competence"",P76:P116<0))), MAX(IFERROR(FILTER(P76:P116,$K76:$K116 = ""ACTIVE"",$G76:$G116 = ""Insight"",P76:P116>0)))+SUM(IFERROR(FILTER(P76:P116,$K76:$K116 = ""ACTIVE"",$G76:$G116 = ""Insight"",P76:P116<0))), MAX(IFERROR(FILTER(P7"&"6:P116,$K76:$K116 = ""ACTIVE"",$G76:$G116 = ""Luck"",P76:P116>0)))+SUM(IFERROR(FILTER(P76:P116,$K76:$K116 = ""ACTIVE"",$G76:$G116 = ""Luck"",P76:P116<0))), MAX(IFERROR(FILTER(P76:P116,$K76:$K116 = ""ACTIVE"",$G76:$G116 = ""Morale"",P76:P116>0)))+SUM(IFERR"&"OR(FILTER(P76:P116,$K76:$K116 = ""ACTIVE"",$G76:$G116 = ""Morale"",P76:P116<0))), MAX(IFERROR(FILTER(P76:P116,$K76:$K116 = ""ACTIVE"",$G76:$G116 = ""Precision Damage"",P76:P116>0)))+SUM(IFERROR(FILTER(P76:P116,$K76:$K116 = ""ACTIVE"",$G76:$G116 = ""Precis"&"ion Damage"",P76:P116<0))), MAX(IFERROR(FILTER(P76:P116,$K76:$K116 = ""ACTIVE"",$G76:$G116 = ""Sacred / Profane"",P76:P116>0)))+SUM(IFERROR(FILTER(P76:P116,$K76:$K116 = ""ACTIVE"",$G76:$G116 = ""Sacred / Profane"",P76:P116<0))), MAX(IFERROR(FILTER(P76:P11"&"6,$K76:$K116 = ""ACTIVE"",$G76:$G116 = ""Size"",P76:P116>0)))+SUM(IFERROR(FILTER(P76:P116,$K76:$K116 = ""ACTIVE"",$G76:$G116 = ""Size"",P76:P116<0))), SUM(IFERROR(FILTER(P76:P116,$K76:$K116 = ""ACTIVE"",$G76:$G116 = ""Untyped (stacks)"")),), SUM(IFERROR(F"&"ILTER(P76:P116,$K76:$K116 = ""ACTIVE"",$G76:$G116 = ""Dodge (stacks)"")),), SUM(IFERROR(FILTER(P76:P116,$K76:$K116 = ""ACTIVE"",$G76:$G116 = ""Circumstance (stacks)"")),))"),0.0) -> 0 | Q17: ARMOR CLASS | R17: =10+SUM(T17:AB17) -> 21 | S17: = | T17: =IFERROR(__xludf.DUMMYFUNCTION("MAX($O$42,MAX(IFERROR(FILTER(N76:N116,$K76:$K116 = ""ACTIVE"",$G76:$G116 = ""Armor"",N76:N116>0)))) +SUM(IFERROR(FILTER(N76:N116,$K76:$K116 = ""ACTIVE"",$G76:$G116 = ""Armor"",N76:N116<0)))+SUM(IFERROR(FILTER(N76:N116,$K76:$K116 = ""ACTIVE"",$G76:$G116 = "&"""Bonus AC (Stacks)"",N76:N116>0)))"),0.0) -> 0 | U17: =O43 -> 0 | V17: =Min(Dexterity,'Formula References'!$P$156) -> 3 | W17: =VLOOKUP(Size,SizeTable,3,false) -> 0 | X17: =$O$74 -> 0 | Y17: =IFERROR(__xludf.DUMMYFUNCTION(" MAX(IFERROR(FILTER(N76:N116,$K76:$K116 = ""ACTIVE"",$G76:$G116 = ""Deflect/Enhance/Resist"",N76:N116>0)))+SUM(IFERROR(FILTER(N76:N116,$K76:$K116 = ""ACTIVE"",$G76:$G116 = ""Deflect/Enhance/Resist"",N76:N116<0)))"),0.0) -> 0 | Z17: =IFERROR(__xludf.DUMMYFUNCTION(" SUM(IFERROR(FILTER(N76:N116,$K76:$K116 = ""ACTIVE"",$G76:$G116 = ""Dodge (stacks)"")),)"),8.0) -> 8 | AB17: =IFERROR(__xludf.DUMMYFUNCTION("SUM(MAX(IFERROR(FILTER(N76:N116,$K76:$K116 = ""ACTIVE"",$G76:$G116 = ""Alchemical"",N76:N116>0)))+SUM(IFERROR(FILTER(N76:N116,$K76:$K116 = ""ACTIVE"",$G76:$G116 = ""Alchemical"",N76:N116<0))), MAX(IFERROR(FILTER(N76:N116,$K76:$K116 = ""ACTIVE"",$G76:$G116"&" = ""Competence"",N76:N116>0)))+SUM(IFERROR(FILTER(N76:N116,$K76:$K116 = ""ACTIVE"",$G76:$G116 = ""Competence"",N76:N116<0))), MAX(IFERROR(FILTER(N76:N116,$K76:$K116 = ""ACTIVE"",$G76:$G116 = ""Insight"",N76:N116>0)))+SUM(IFERROR(FILTER(N76:N116,$K76:$K11"&"6 = ""ACTIVE"",$G76:$G116 = ""Insight"",N76:N116<0))), MAX(IFERROR(FILTER(N76:N116,$K76:$K116 = ""ACTIVE"",$G76:$G116 = ""Luck"",N76:N116>0)))+SUM(IFERROR(FILTER(N76:N116,$K76:$K116 = ""ACTIVE"",$G76:$G116 = ""Luck"",N76:N116<0))), MAX(IFERROR(FILTER(N76:"&"N116,$K76:$K116 = ""ACTIVE"",$G76:$G116 = ""Morale"",N76:N116>0)))+SUM(IFERROR(FILTER(N76:N116,$K76:$K116 = ""ACTIVE"",$G76:$G116 = ""Morale"",N76:N116<0))), MAX(IFERROR(FILTER(N76:N116,$K76:$K116 = ""ACTIVE"",$G76:$G116 = ""Precision Damage"",N76:N116>0)"&"))+SUM(IFERROR(FILTER(N76:N116,$K76:$K116 = ""ACTIVE"",$G76:$G116 = ""Precision Damage"",N76:N116<0))), MAX(IFERROR(FILTER(N76:N116,$K76:$K116 = ""ACTIVE"",$G76:$G116 = ""Sacred / Profane"",N76:N116>0)))+SUM(IFERROR(FILTER(N76:N116,$K76:$K116 = ""ACTIVE"""&",$G76:$G116 = ""Sacred / Profane"",N76:N116<0))), SUM(IFERROR(FILTER(N76:N116,$K76:$K116 = ""ACTIVE"",$G76:$G116 = ""Untyped (stacks)"")),), SUM(IFERROR(FILTER(N76:N116,$K76:$K116 = ""ACTIVE"",$G76:$G116 = ""Circumstance (stacks)"")),))"),0.0) -> 0 | AD17: =IF(OR( iferror(vlookup($AE$2, 'Class Skills'!$A:$BE,MATCH(AE17,'Class Skills'!$1:$1,0),false),"")="X", iferror(vlookup($AE$3, 'Class Skills'!$A:$BE,MATCH(AE17,'Class Skills'!$1:$1,0),false),"")="X", iferror(vlookup($AE$4, 'Class Skills'!$A:$BE,MATCH(AE17,'Class Skills'!$1:$1,0),false),"")="X", iferror(vlookup(#REF!, 'Class Skills'!$A:$BE,MATCH(AE17,'Class Skills'!$1:$1,0),false),"")="X"),"X",) -> X | AE17: Heal | AI17: =HLOOKUP(AE17,'Class Skills'!$1:$3,3,false) -> Wis | AJ17: =if(AND(HLOOKUP(AE17,'Class Skills'!$1:$2,2,false)="Trained Only",AL17<1),,SUM(AL17:AQ17)) -> 0 | AK17: = | AM17: =IFERROR(__xludf.DUMMYFUNCTION("offset($E$8,match(AI17,ARRAYFORMULA(Proper(lower(REGEXEXTRACT($E$9:$E$14,""\w\w\w"")))),0),2)"),0.0) -> 0 | AN17: =if(AND(AL17 > 0,AD17 ="X"), 3, ) | AP17: =IFERROR(__xludf.DUMMYFUNCTION("if( or(arrayformula(regexmatch($AR$76:$AR$110,AE17))), sum(arrayformula(iferror(value(regexextract(filter( $AR$76:$AR$110, $K$76:$K$110=""ACTIVE"", regexmatch($AR$76:$AR$110,AE17)), ""[-\d]+"")))))+tSkill,tSkill)"),0.0) -> 0 | AQ17: =iferror(if( if(hlookup(AE17,'Class Skills'!$1:$4,4,false)="Armor Penalty",'Formula References'!$Q$156,) +if(AND(isnumber($C$38),AE17="Climb"),8,) +if(AND(isnumber($C$39),AE17="Swim"),8,) +if(AE17="Fly", Vlookup(Size,SizeTable,5,False),) +if(AE17="Fly",if($M$37="Clumsy",-8,if($M$37="Poor",-4,if($M$37="Average",0,if($M$37="Good",4,if($M$37="Perfect",8,0)))))) +if(AE17="Stealth",Vlookup(Size,SizeTable,6,False)) =0,, if(hlookup(AE17,'Class Skills'!$1:$4,4,false)="Armor Penalty",'Formula References'!$Q$156,) +if(AND(isnumber($C$38),AE17="Climb"),8,) +if(AND(isnumber($C$39),AE17="Swim"),8,) +if(AE17="Fly", Vlookup(Size,SizeTable,5,False),) +if(AE17="Fly",if($M$37="Clumsy",-8,if($M$37="Poor",-4,if($M$37="Average",0,if($M$37="Good",4,if($M$37="Perfect",8,0)))))) +if(AE17="Stealth",Vlookup(Size,SizeTable,6,False))),"")
E18: REFLEX | F18: =SUM(H18:L18) -> 4 | G18: = | H18: =AO6 -> 1 | I18: =Dexterity -> 3 | J18: =IFERROR(__xludf.DUMMYFUNCTION("SUM( MAX(IFERROR(FILTER(Q76:Q116,$K76:$K116 = ""ACTIVE"",$G76:$G116 = ""Deflect/Enhance/Resist"",Q76:Q116>0))) +SUM(IFERROR(FILTER(Q76:Q116,$K76:$K116 = ""ACTIVE"",$G76:$G116 = ""Deflect/Enhance/Resist"",Q76:Q116<0))) )"),0.0) -> 0 | L18: =IFERROR(__xludf.DUMMYFUNCTION("SUM(MAX(IFERROR(FILTER(Q76:Q116,$K76:$K116 = ""ACTIVE"",$G76:$G116 = ""Alchemical"",Q76:Q116>0)))+SUM(IFERROR(FILTER(Q76:Q116,$K76:$K116 = ""ACTIVE"",$G76:$G116 = ""Alchemical"",Q76:Q116<0))), MAX(IFERROR(FILTER(Q76:Q116,$K76:$K116 = ""ACTIVE"",$G76:$G116"&" = ""Armor"",Q76:Q116>0)))+SUM(IFERROR(FILTER(Q76:Q116,$K76:$K116 = ""ACTIVE"",$G76:$G116 = ""Armor"",Q76:Q116<0))), MAX(IFERROR(FILTER(Q76:Q116,$K76:$K116 = ""ACTIVE"",$G76:$G116 = ""Competence"",Q76:Q116>0)))+SUM(IFERROR(FILTER(Q76:Q116,$K76:$K116 = ""A"&"CTIVE"",$G76:$G116 = ""Competence"",Q76:Q116<0))), MAX(IFERROR(FILTER(Q76:Q116,$K76:$K116 = ""ACTIVE"",$G76:$G116 = ""Insight"",Q76:Q116>0)))+SUM(IFERROR(FILTER(Q76:Q116,$K76:$K116 = ""ACTIVE"",$G76:$G116 = ""Insight"",Q76:Q116<0))), MAX(IFERROR(FILTER(Q7"&"6:Q116,$K76:$K116 = ""ACTIVE"",$G76:$G116 = ""Luck"",Q76:Q116>0)))+SUM(IFERROR(FILTER(Q76:Q116,$K76:$K116 = ""ACTIVE"",$G76:$G116 = ""Luck"",Q76:Q116<0))), MAX(IFERROR(FILTER(Q76:Q116,$K76:$K116 = ""ACTIVE"",$G76:$G116 = ""Morale"",Q76:Q116>0)))+SUM(IFERR"&"OR(FILTER(Q76:Q116,$K76:$K116 = ""ACTIVE"",$G76:$G116 = ""Morale"",Q76:Q116<0))), MAX(IFERROR(FILTER(Q76:Q116,$K76:$K116 = ""ACTIVE"",$G76:$G116 = ""Precision Damage"",Q76:Q116>0)))+SUM(IFERROR(FILTER(Q76:Q116,$K76:$K116 = ""ACTIVE"",$G76:$G116 = ""Precis"&"ion Damage"",Q76:Q116<0))), MAX(IFERROR(FILTER(Q76:Q116,$K76:$K116 = ""ACTIVE"",$G76:$G116 = ""Sacred / Profane"",Q76:Q116>0)))+SUM(IFERROR(FILTER(Q76:Q116,$K76:$K116 = ""ACTIVE"",$G76:$G116 = ""Sacred / Profane"",Q76:Q116<0))), MAX(IFERROR(FILTER(Q76:Q11"&"6,$K76:$K116 = ""ACTIVE"",$G76:$G116 = ""Size"",Q76:Q116>0)))+SUM(IFERROR(FILTER(Q76:Q116,$K76:$K116 = ""ACTIVE"",$G76:$G116 = ""Size"",Q76:Q116<0))), SUM(IFERROR(FILTER(Q76:Q116,$K76:$K116 = ""ACTIVE"",$G76:$G116 = ""Untyped (stacks)"")),), SUM(IFERROR(F"&"ILTER(Q76:Q116,$K76:$K116 = ""ACTIVE"",$G76:$G116 = ""Dodge (stacks)"")),), SUM(IFERROR(FILTER(Q76:Q116,$K76:$K116 = ""ACTIVE"",$G76:$G116 = ""Circumstance (stacks)"")),))"),0.0) -> 0 | Q18: FLAT-FOOTED | R18: =10+SUM(T18:AB18) -> 18 | S18: = | T18: =T17 -> 0 | U18: =U17 -> 0 | V18: =if(Dexterity<0,Dexterity,) | W18: =VLOOKUP(Size,SizeTable,3,false) -> 0 | X18: =X17 -> 0 | Y18: =Y17 -> 0 | Z18: =IFERROR(__xludf.DUMMYFUNCTION(" SUM(IFERROR(FILTER(N77:N117,$K77:$K117 = ""ACTIVE"",$G77:$G117 = ""Dodge (stacks)"")),)"),8.0) -> 8 | AB18: =$AB$17 -> 0 | AD18: =IF(OR( iferror(vlookup($AE$2, 'Class Skills'!$A:$BE,MATCH(AE18,'Class Skills'!$1:$1,0),false),"")="X", iferror(vlookup($AE$3, 'Class Skills'!$A:$BE,MATCH(AE18,'Class Skills'!$1:$1,0),false),"")="X", iferror(vlookup($AE$4, 'Class Skills'!$A:$BE,MATCH(AE18,'Class Skills'!$1:$1,0),false),"")="X", iferror(vlookup(#REF!, 'Class Skills'!$A:$BE,MATCH(AE18,'Class Skills'!$1:$1,0),false),"")="X"),"X",) -> X | AE18: Intimidate | AI18: Int | AJ18: =if(AND(HLOOKUP(AE18,'Class Skills'!$1:$2,2,false)="Trained Only",AL18<1),,SUM(AL18:AQ18)) -> 14 | AK18: = | AL18: 3 | AM18: =IFERROR(__xludf.DUMMYFUNCTION("offset($E$8,match(AI18,ARRAYFORMULA(Proper(lower(REGEXEXTRACT($E$9:$E$14,""\w\w\w"")))),0),2)"),8.0) -> 8 | AN18: =if(AND(AL18 > 0,AD18 ="X"), 3, ) -> 3 | AP18: =IFERROR(__xludf.DUMMYFUNCTION("if( or(arrayformula(regexmatch($AR$76:$AR$110,AE18))), sum(arrayformula(iferror(value(regexextract(filter( $AR$76:$AR$110, $K$76:$K$110=""ACTIVE"", regexmatch($AR$76:$AR$110,AE18)), ""[-\d]+"")))))+tSkill,tSkill)"),0.0) -> 0 | AQ18: =iferror(if( if(hlookup(AE18,'Class Skills'!$1:$4,4,false)="Armor Penalty",'Formula References'!$Q$156,) +if(AND(isnumber($C$38),AE18="Climb"),8,) +if(AND(isnumber($C$39),AE18="Swim"),8,) +if(AE18="Fly", Vlookup(Size,SizeTable,5,False),) +if(AE18="Fly",if($M$37="Clumsy",-8,if($M$37="Poor",-4,if($M$37="Average",0,if($M$37="Good",4,if($M$37="Perfect",8,0)))))) +if(AE18="Stealth",Vlookup(Size,SizeTable,6,False)) =0,, if(hlookup(AE18,'Class Skills'!$1:$4,4,false)="Armor Penalty",'Formula References'!$Q$156,) +if(AND(isnumber($C$38),AE18="Climb"),8,) +if(AND(isnumber($C$39),AE18="Swim"),8,) +if(AE18="Fly", Vlookup(Size,SizeTable,5,False),) +if(AE18="Fly",if($M$37="Clumsy",-8,if($M$37="Poor",-4,if($M$37="Average",0,if($M$37="Good",4,if($M$37="Perfect",8,0)))))) +if(AE18="Stealth",Vlookup(Size,SizeTable,6,False))),"")
E19: WILL | F19: =SUM(H19:L19) -> 3 | G19: = | H19: =AP6 -> 3 | I19: =Wisdom -> 0 | J19: =IFERROR(__xludf.DUMMYFUNCTION("SUM( MAX(IFERROR(FILTER(R76:R116,$K76:$K116 = ""ACTIVE"",$G76:$G116 = ""Deflect/Enhance/Resist"",R76:R116>0))) +SUM(IFERROR(FILTER(R76:R116,$K76:$K116 = ""ACTIVE"",$G76:$G116 = ""Deflect/Enhance/Resist"",R76:R116<0))) )"),0.0) -> 0 | L19: =IFERROR(__xludf.DUMMYFUNCTION("SUM(MAX(IFERROR(FILTER(R76:R116,$K76:$K116 = ""ACTIVE"",$G76:$G116 = ""Alchemical"",R76:R116>0)))+SUM(IFERROR(FILTER(R76:R116,$K76:$K116 = ""ACTIVE"",$G76:$G116 = ""Alchemical"",R76:R116<0))), MAX(IFERROR(FILTER(R76:R116,$K76:$K116 = ""ACTIVE"",$G76:$G116"&" = ""Armor"",R76:R116>0)))+SUM(IFERROR(FILTER(R76:R116,$K76:$K116 = ""ACTIVE"",$G76:$G116 = ""Armor"",R76:R116<0))), MAX(IFERROR(FILTER(R76:R116,$K76:$K116 = ""ACTIVE"",$G76:$G116 = ""Competence"",R76:R116>0)))+SUM(IFERROR(FILTER(R76:R116,$K76:$K116 = ""A"&"CTIVE"",$G76:$G116 = ""Competence"",R76:R116<0))), MAX(IFERROR(FILTER(R76:R116,$K76:$K116 = ""ACTIVE"",$G76:$G116 = ""Insight"",R76:R116>0)))+SUM(IFERROR(FILTER(R76:R116,$K76:$K116 = ""ACTIVE"",$G76:$G116 = ""Insight"",R76:R116<0))), MAX(IFERROR(FILTER(R7"&"6:R116,$K76:$K116 = ""ACTIVE"",$G76:$G116 = ""Luck"",R76:R116>0)))+SUM(IFERROR(FILTER(R76:R116,$K76:$K116 = ""ACTIVE"",$G76:$G116 = ""Luck"",R76:R116<0))), MAX(IFERROR(FILTER(R76:R116,$K76:$K116 = ""ACTIVE"",$G76:$G116 = ""Morale"",R76:R116>0)))+SUM(IFERR"&"OR(FILTER(R76:R116,$K76:$K116 = ""ACTIVE"",$G76:$G116 = ""Morale"",R76:R116<0))), MAX(IFERROR(FILTER(R76:R116,$K76:$K116 = ""ACTIVE"",$G76:$G116 = ""Precision Damage"",R76:R116>0)))+SUM(IFERROR(FILTER(R76:R116,$K76:$K116 = ""ACTIVE"",$G76:$G116 = ""Precis"&"ion Damage"",R76:R116<0))), MAX(IFERROR(FILTER(R76:R116,$K76:$K116 = ""ACTIVE"",$G76:$G116 = ""Sacred / Profane"",R76:R116>0)))+SUM(IFERROR(FILTER(R76:R116,$K76:$K116 = ""ACTIVE"",$G76:$G116 = ""Sacred / Profane"",R76:R116<0))), MAX(IFERROR(FILTER(R76:R11"&"6,$K76:$K116 = ""ACTIVE"",$G76:$G116 = ""Size"",R76:R116>0)))+SUM(IFERROR(FILTER(R76:R116,$K76:$K116 = ""ACTIVE"",$G76:$G116 = ""Size"",R76:R116<0))), SUM(IFERROR(FILTER(R76:R116,$K76:$K116 = ""ACTIVE"",$G76:$G116 = ""Untyped (stacks)"")),), SUM(IFERROR(F"&"ILTER(R76:R116,$K76:$K116 = ""ACTIVE"",$G76:$G116 = ""Dodge (stacks)"")),), SUM(IFERROR(FILTER(R76:R116,$K76:$K116 = ""ACTIVE"",$G76:$G116 = ""Circumstance (stacks)"")),))"),0.0) -> 0 | Q19: TOUCH | R19: =10+SUM(T19:AB19) -> 21 | S19: = | T19: BAB | U19: STR | V19: =V17 -> 3 | W19: =VLOOKUP(Size,SizeTable,3,false) -> 0 | Y19: =Y17 -> 0 | Z19: =Z17 -> 8 | AB19: =$AB$17 -> 0 | AD19: X | AE19: Kn. Arcana | AI19: =HLOOKUP(AE19,'Class Skills'!$1:$3,3,false) -> Int | AJ19: =if(AND(HLOOKUP(AE19,'Class Skills'!$1:$2,2,false)="Trained Only",AL19<1),,SUM(AL19:AQ19)) -> 22 | AK19: = | AL19: 3 | AM19: =IFERROR(__xludf.DUMMYFUNCTION("offset($E$8,match(AI19,ARRAYFORMULA(Proper(lower(REGEXEXTRACT($E$9:$E$14,""\w\w\w"")))),0),2)"),8.0) -> 8 | AN19: =if(AND(AL19 > 0,AD19 ="X"), 3, ) -> 3 | AO19: 8 | AP19: =IFERROR(__xludf.DUMMYFUNCTION("if( or(arrayformula(regexmatch($AR$76:$AR$110,AE19))), sum(arrayformula(iferror(value(regexextract(filter( $AR$76:$AR$110, $K$76:$K$110=""ACTIVE"", regexmatch($AR$76:$AR$110,AE19)), ""[-\d]+"")))))+tSkill,tSkill)"),0.0) -> 0 | AQ19: =iferror(if( if(hlookup(AE19,'Class Skills'!$1:$4,4,false)="Armor Penalty",'Formula References'!$Q$156,) +if(AND(isnumber($C$38),AE19="Climb"),8,) +if(AND(isnumber($C$39),AE19="Swim"),8,) +if(AE19="Fly", Vlookup(Size,SizeTable,5,False),) +if(AE19="Fly",if($M$37="Clumsy",-8,if($M$37="Poor",-4,if($M$37="Average",0,if($M$37="Good",4,if($M$37="Perfect",8,0)))))) +if(AE19="Stealth",Vlookup(Size,SizeTable,6,False)) =0,, if(hlookup(AE19,'Class Skills'!$1:$4,4,false)="Armor Penalty",'Formula References'!$Q$156,) +if(AND(isnumber($C$38),AE19="Climb"),8,) +if(AND(isnumber($C$39),AE19="Swim"),8,) +if(AE19="Fly", Vlookup(Size,SizeTable,5,False),) +if(AE19="Fly",if($M$37="Clumsy",-8,if($M$37="Poor",-4,if($M$37="Average",0,if($M$37="Good",4,if($M$37="Perfect",8,0)))))) +if(AE19="Stealth",Vlookup(Size,SizeTable,6,False))),"")
Q20: CMD | R20: =10+SUM(T20:AB20) -> 23 | S20: = | T20: =BaseAttack -> 2 | U20: =G9 -> 0 | V20: =Dexterity -> 3 | W20: =VLOOKUP(Size,SizeTable,4,false) -> 0 | Y20: =Y17 -> 0 | Z20: =Z17 -> 8 | AB20: =$AB$17 -> 0 | AD20: =IF(OR( iferror(vlookup($AE$2, 'Class Skills'!$A:$BE,MATCH(AE20,'Class Skills'!$1:$1,0),false),"")="X", iferror(vlookup($AE$3, 'Class Skills'!$A:$BE,MATCH(AE20,'Class Skills'!$1:$1,0),false),"")="X", iferror(vlookup($AE$4, 'Class Skills'!$A:$BE,MATCH(AE20,'Class Skills'!$1:$1,0),false),"")="X", iferror(vlookup(#REF!, 'Class Skills'!$A:$BE,MATCH(AE20,'Class Skills'!$1:$1,0),false),"")="X"),"X",) | AE20: Kn. Dungeoneering | AI20: =HLOOKUP(AE20,'Class Skills'!$1:$3,3,false) -> Int | AJ20: =if(AND(HLOOKUP(AE20,'Class Skills'!$1:$2,2,false)="Trained Only",AL20<1),,SUM(AL20:AQ20)) | AK20: = | AM20: =IFERROR(__xludf.DUMMYFUNCTION("offset($E$8,match(AI20,ARRAYFORMULA(Proper(lower(REGEXEXTRACT($E$9:$E$14,""\w\w\w"")))),0),2)"),8.0) -> 8 | AN20: =if(AND(AL20 > 0,AD20 ="X"), 3, ) | AP20: =IFERROR(__xludf.DUMMYFUNCTION("if( or(arrayformula(regexmatch($AR$76:$AR$110,AE20))), sum(arrayformula(iferror(value(regexextract(filter( $AR$76:$AR$110, $K$76:$K$110=""ACTIVE"", regexmatch($AR$76:$AR$110,AE20)), ""[-\d]+"")))))+tSkill,tSkill)"),0.0) -> 0 | AQ20: =iferror(if( if(hlookup(AE20,'Class Skills'!$1:$4,4,false)="Armor Penalty",'Formula References'!$Q$156,) +if(AND(isnumber($C$38),AE20="Climb"),8,) +if(AND(isnumber($C$39),AE20="Swim"),8,) +if(AE20="Fly", Vlookup(Size,SizeTable,5,False),) +if(AE20="Fly",if($M$37="Clumsy",-8,if($M$37="Poor",-4,if($M$37="Average",0,if($M$37="Good",4,if($M$37="Perfect",8,0)))))) +if(AE20="Stealth",Vlookup(Size,SizeTable,6,False)) =0,, if(hlookup(AE20,'Class Skills'!$1:$4,4,false)="Armor Penalty",'Formula References'!$Q$156,) +if(AND(isnumber($C$38),AE20="Climb"),8,) +if(AND(isnumber($C$39),AE20="Swim"),8,) +if(AE20="Fly", Vlookup(Size,SizeTable,5,False),) +if(AE20="Fly",if($M$37="Clumsy",-8,if($M$37="Poor",-4,if($M$37="Average",0,if($M$37="Good",4,if($M$37="Perfect",8,0)))))) +if(AE20="Stealth",Vlookup(Size,SizeTable,6,False))),"")
H21: Saving Throw Notes | V21: Armor Class Notes | AD21: =IF(OR( iferror(vlookup($AE$2, 'Class Skills'!$A:$BE,MATCH(AE21,'Class Skills'!$1:$1,0),false),"")="X", iferror(vlookup($AE$3, 'Class Skills'!$A:$BE,MATCH(AE21,'Class Skills'!$1:$1,0),false),"")="X", iferror(vlookup($AE$4, 'Class Skills'!$A:$BE,MATCH(AE21,'Class Skills'!$1:$1,0),false),"")="X", iferror(vlookup(#REF!, 'Class Skills'!$A:$BE,MATCH(AE21,'Class Skills'!$1:$1,0),false),"")="X"),"X",) -> X | AE21: Kn. Local | AI21: =HLOOKUP(AE21,'Class Skills'!$1:$3,3,false) -> Int | AJ21: =if(AND(HLOOKUP(AE21,'Class Skills'!$1:$2,2,false)="Trained Only",AL21<1),,SUM(AL21:AQ21)) -> 14 | AK21: = | AL21: 3 | AM21: =IFERROR(__xludf.DUMMYFUNCTION("offset($E$8,match(AI21,ARRAYFORMULA(Proper(lower(REGEXEXTRACT($E$9:$E$14,""\w\w\w"")))),0),2)"),8.0) -> 8 | AN21: =if(AND(AL21 > 0,AD21 ="X"), 3, ) -> 3 | AP21: =IFERROR(__xludf.DUMMYFUNCTION("if( or(arrayformula(regexmatch($AR$76:$AR$110,AE21))), sum(arrayformula(iferror(value(regexextract(filter( $AR$76:$AR$110, $K$76:$K$110=""ACTIVE"", regexmatch($AR$76:$AR$110,AE21)), ""[-\d]+"")))))+tSkill,tSkill)"),0.0) -> 0 | AQ21: =iferror(if( if(hlookup(AE21,'Class Skills'!$1:$4,4,false)="Armor Penalty",'Formula References'!$Q$156,) +if(AND(isnumber($C$38),AE21="Climb"),8,) +if(AND(isnumber($C$39),AE21="Swim"),8,) +if(AE21="Fly", Vlookup(Size,SizeTable,5,False),) +if(AE21="Fly",if($M$37="Clumsy",-8,if($M$37="Poor",-4,if($M$37="Average",0,if($M$37="Good",4,if($M$37="Perfect",8,0)))))) +if(AE21="Stealth",Vlookup(Size,SizeTable,6,False)) =0,, if(hlookup(AE21,'Class Skills'!$1:$4,4,false)="Armor Penalty",'Formula References'!$Q$156,) +if(AND(isnumber($C$38),AE21="Climb"),8,) +if(AND(isnumber($C$39),AE21="Swim"),8,) +if(AE21="Fly", Vlookup(Size,SizeTable,5,False),) +if(AE21="Fly",if($M$37="Clumsy",-8,if($M$37="Poor",-4,if($M$37="Average",0,if($M$37="Good",4,if($M$37="Perfect",8,0)))))) +if(AE21="Stealth",Vlookup(Size,SizeTable,6,False))),"")
AD22: =IF(OR( iferror(vlookup($AE$2, 'Class Skills'!$A:$BE,MATCH(AE22,'Class Skills'!$1:$1,0),false),"")="X", iferror(vlookup($AE$3, 'Class Skills'!$A:$BE,MATCH(AE22,'Class Skills'!$1:$1,0),false),"")="X", iferror(vlookup($AE$4, 'Class Skills'!$A:$BE,MATCH(AE22,'Class Skills'!$1:$1,0),false),"")="X", iferror(vlookup(#REF!, 'Class Skills'!$A:$BE,MATCH(AE22,'Class Skills'!$1:$1,0),false),"")="X"),"X",) -> X | AE22: Kn. Nature | AI22: =HLOOKUP(AE22,'Class Skills'!$1:$3,3,false) -> Int | AJ22: =if(AND(HLOOKUP(AE22,'Class Skills'!$1:$2,2,false)="Trained Only",AL22<1),,SUM(AL22:AQ22)) -> 14 | AK22: = | AL22: 3 | AM22: =IFERROR(__xludf.DUMMYFUNCTION("offset($E$8,match(AI22,ARRAYFORMULA(Proper(lower(REGEXEXTRACT($E$9:$E$14,""\w\w\w"")))),0),2)"),8.0) -> 8 | AN22: =if(AND(AL22 > 0,AD22 ="X"), 3, ) -> 3 | AP22: =IFERROR(__xludf.DUMMYFUNCTION("if( or(arrayformula(regexmatch($AR$76:$AR$110,AE22))), sum(arrayformula(iferror(value(regexextract(filter( $AR$76:$AR$110, $K$76:$K$110=""ACTIVE"", regexmatch($AR$76:$AR$110,AE22)), ""[-\d]+"")))))+tSkill,tSkill)"),0.0) -> 0 | AQ22: =iferror(if( if(hlookup(AE22,'Class Skills'!$1:$4,4,false)="Armor Penalty",'Formula References'!$Q$156,) +if(AND(isnumber($C$38),AE22="Climb"),8,) +if(AND(isnumber($C$39),AE22="Swim"),8,) +if(AE22="Fly", Vlookup(Size,SizeTable,5,False),) +if(AE22="Fly",if($M$37="Clumsy",-8,if($M$37="Poor",-4,if($M$37="Average",0,if($M$37="Good",4,if($M$37="Perfect",8,0)))))) +if(AE22="Stealth",Vlookup(Size,SizeTable,6,False)) =0,, if(hlookup(AE22,'Class Skills'!$1:$4,4,false)="Armor Penalty",'Formula References'!$Q$156,) +if(AND(isnumber($C$38),AE22="Climb"),8,) +if(AND(isnumber($C$39),AE22="Swim"),8,) +if(AE22="Fly", Vlookup(Size,SizeTable,5,False),) +if(AE22="Fly",if($M$37="Clumsy",-8,if($M$37="Poor",-4,if($M$37="Average",0,if($M$37="Good",4,if($M$37="Perfect",8,0)))))) +if(AE22="Stealth",Vlookup(Size,SizeTable,6,False))),"")
AD23: =IF(OR( iferror(vlookup($AE$2, 'Class Skills'!$A:$BE,MATCH(AE23,'Class Skills'!$1:$1,0),false),"")="X", iferror(vlookup($AE$3, 'Class Skills'!$A:$BE,MATCH(AE23,'Class Skills'!$1:$1,0),false),"")="X", iferror(vlookup($AE$4, 'Class Skills'!$A:$BE,MATCH(AE23,'Class Skills'!$1:$1,0),false),"")="X", iferror(vlookup(#REF!, 'Class Skills'!$A:$BE,MATCH(AE23,'Class Skills'!$1:$1,0),false),"")="X"),"X",) | AE23: Kn. Planes | AI23: =HLOOKUP(AE23,'Class Skills'!$1:$3,3,false) -> Int | AJ23: =if(AND(HLOOKUP(AE23,'Class Skills'!$1:$2,2,false)="Trained Only",AL23<1),,SUM(AL23:AQ23)) | AK23: = | AM23: =IFERROR(__xludf.DUMMYFUNCTION("offset($E$8,match(AI23,ARRAYFORMULA(Proper(lower(REGEXEXTRACT($E$9:$E$14,""\w\w\w"")))),0),2)"),8.0) -> 8 | AN23: =if(AND(AL23 > 0,AD23 ="X"), 3, ) | AP23: =IFERROR(__xludf.DUMMYFUNCTION("if( or(arrayformula(regexmatch($AR$76:$AR$110,AE23))), sum(arrayformula(iferror(value(regexextract(filter( $AR$76:$AR$110, $K$76:$K$110=""ACTIVE"", regexmatch($AR$76:$AR$110,AE23)), ""[-\d]+"")))))+tSkill,tSkill)"),0.0) -> 0 | AQ23: =iferror(if( if(hlookup(AE23,'Class Skills'!$1:$4,4,false)="Armor Penalty",'Formula References'!$Q$156,) +if(AND(isnumber($C$38),AE23="Climb"),8,) +if(AND(isnumber($C$39),AE23="Swim"),8,) +if(AE23="Fly", Vlookup(Size,SizeTable,5,False),) +if(AE23="Fly",if($M$37="Clumsy",-8,if($M$37="Poor",-4,if($M$37="Average",0,if($M$37="Good",4,if($M$37="Perfect",8,0)))))) +if(AE23="Stealth",Vlookup(Size,SizeTable,6,False)) =0,, if(hlookup(AE23,'Class Skills'!$1:$4,4,false)="Armor Penalty",'Formula References'!$Q$156,) +if(AND(isnumber($C$38),AE23="Climb"),8,) +if(AND(isnumber($C$39),AE23="Swim"),8,) +if(AE23="Fly", Vlookup(Size,SizeTable,5,False),) +if(AE23="Fly",if($M$37="Clumsy",-8,if($M$37="Poor",-4,if($M$37="Average",0,if($M$37="Good",4,if($M$37="Perfect",8,0)))))) +if(AE23="Stealth",Vlookup(Size,SizeTable,6,False))),"")
AD24: =IF(OR( iferror(vlookup($AE$2, 'Class Skills'!$A:$BE,MATCH(AE24,'Class Skills'!$1:$1,0),false),"")="X", iferror(vlookup($AE$3, 'Class Skills'!$A:$BE,MATCH(AE24,'Class Skills'!$1:$1,0),false),"")="X", iferror(vlookup($AE$4, 'Class Skills'!$A:$BE,MATCH(AE24,'Class Skills'!$1:$1,0),false),"")="X", iferror(vlookup(#REF!, 'Class Skills'!$A:$BE,MATCH(AE24,'Class Skills'!$1:$1,0),false),"")="X"),"X",) -> X | AE24: Kn. Religion | AI24: =HLOOKUP(AE24,'Class Skills'!$1:$3,3,false) -> Int | AJ24: =if(AND(HLOOKUP(AE24,'Class Skills'!$1:$2,2,false)="Trained Only",AL24<1),,SUM(AL24:AQ24)) -> 14 | AK24: = | AL24: 3 | AM24: =IFERROR(__xludf.DUMMYFUNCTION("offset($E$8,match(AI24,ARRAYFORMULA(Proper(lower(REGEXEXTRACT($E$9:$E$14,""\w\w\w"")))),0),2)"),8.0) -> 8 | AN24: =if(AND(AL24 > 0,AD24 ="X"), 3, ) -> 3 | AP24: =IFERROR(__xludf.DUMMYFUNCTION("if( or(arrayformula(regexmatch($AR$76:$AR$110,AE24))), sum(arrayformula(iferror(value(regexextract(filter( $AR$76:$AR$110, $K$76:$K$110=""ACTIVE"", regexmatch($AR$76:$AR$110,AE24)), ""[-\d]+"")))))+tSkill,tSkill)"),0.0) -> 0 | AQ24: =iferror(if( if(hlookup(AE24,'Class Skills'!$1:$4,4,false)="Armor Penalty",'Formula References'!$Q$156,) +if(AND(isnumber($C$38),AE24="Climb"),8,) +if(AND(isnumber($C$39),AE24="Swim"),8,) +if(AE24="Fly", Vlookup(Size,SizeTable,5,False),) +if(AE24="Fly",if($M$37="Clumsy",-8,if($M$37="Poor",-4,if($M$37="Average",0,if($M$37="Good",4,if($M$37="Perfect",8,0)))))) +if(AE24="Stealth",Vlookup(Size,SizeTable,6,False)) =0,, if(hlookup(AE24,'Class Skills'!$1:$4,4,false)="Armor Penalty",'Formula References'!$Q$156,) +if(AND(isnumber($C$38),AE24="Climb"),8,) +if(AND(isnumber($C$39),AE24="Swim"),8,) +if(AE24="Fly", Vlookup(Size,SizeTable,5,False),) +if(AE24="Fly",if($M$37="Clumsy",-8,if($M$37="Poor",-4,if($M$37="Average",0,if($M$37="Good",4,if($M$37="Perfect",8,0)))))) +if(AE24="Stealth",Vlookup(Size,SizeTable,6,False))),"")
B25: mAtk | C25: mDmg | D25: Enh. | E25: OFFENSES | M25: Formula Variables | Q25: Attacks | U25: Dice | W25: Damage | Y25: Crit | Z25: Mult | AA25: Range | AB25: Type | AD25: =IF(OR( iferror(vlookup($AE$2, 'Class Skills'!$A:$BE,MATCH(AE25,'Class Skills'!$1:$1,0),false),"")="X", iferror(vlookup($AE$3, 'Class Skills'!$A:$BE,MATCH(AE25,'Class Skills'!$1:$1,0),false),"")="X", iferror(vlookup($AE$4, 'Class Skills'!$A:$BE,MATCH(AE25,'Class Skills'!$1:$1,0),false),"")="X", iferror(vlookup(#REF!, 'Class Skills'!$A:$BE,MATCH(AE25,'Class Skills'!$1:$1,0),false),"")="X"),"X",) -> X | AE25: Perception | AI25: =HLOOKUP(AE25,'Class Skills'!$1:$3,3,false) -> Wis | AJ25: =if(AND(HLOOKUP(AE25,'Class Skills'!$1:$2,2,false)="Trained Only",AL25<1),,SUM(AL25:AQ25)) -> 6 | AK25: = | AL25: 3 | AM25: =IFERROR(__xludf.DUMMYFUNCTION("offset($E$8,match(AI25,ARRAYFORMULA(Proper(lower(REGEXEXTRACT($E$9:$E$14,""\w\w\w"")))),0),2)"),0.0) -> 0 | AN25: =if(AND(AL25 > 0,AD25 ="X"), 3, ) -> 3 | AP25: =IFERROR(__xludf.DUMMYFUNCTION("if( or(arrayformula(regexmatch($AR$76:$AR$110,AE25))), sum(arrayformula(iferror(value(regexextract(filter( $AR$76:$AR$110, $K$76:$K$110=""ACTIVE"", regexmatch($AR$76:$AR$110,AE25)), ""[-\d]+"")))))+tSkill,tSkill)"),0.0) -> 0 | AQ25: =iferror(if( if(hlookup(AE25,'Class Skills'!$1:$4,4,false)="Armor Penalty",'Formula References'!$Q$156,) +if(AND(isnumber($C$38),AE25="Climb"),8,) +if(AND(isnumber($C$39),AE25="Swim"),8,) +if(AE25="Fly", Vlookup(Size,SizeTable,5,False),) +if(AE25="Fly",if($M$37="Clumsy",-8,if($M$37="Poor",-4,if($M$37="Average",0,if($M$37="Good",4,if($M$37="Perfect",8,0)))))) +if(AE25="Stealth",Vlookup(Size,SizeTable,6,False)) =0,, if(hlookup(AE25,'Class Skills'!$1:$4,4,false)="Armor Penalty",'Formula References'!$Q$156,) +if(AND(isnumber($C$38),AE25="Climb"),8,) +if(AND(isnumber($C$39),AE25="Swim"),8,) +if(AE25="Fly", Vlookup(Size,SizeTable,5,False),) +if(AE25="Fly",if($M$37="Clumsy",-8,if($M$37="Poor",-4,if($M$37="Average",0,if($M$37="Good",4,if($M$37="Perfect",8,0)))))) +if(AE25="Stealth",Vlookup(Size,SizeTable,6,False))),"")
E26: Izanami's Nodachi | M26: Melee Attack | N26: INT to hit, INT to damage | O26: =IFERROR(__xludf.DUMMYFUNCTION("if(istext(N26), if(M26 = ""Melee Attack"",""+""& if(Vlookup(M26,INDIRECT('Formula References'!$B71),3,FALSE)>0, VLOOKUP(N26,INDIRECT('Formula References'!$B71),2,False)+$B26+if($D26 = ""Masterwork"", 1, $D26),)+$AC$74& "&" if($AI$74>0, "" / +"" & VLOOKUP(N26,INDIRECT('Formula References'!$B71),2,False)+$B26+if($D26 = ""Masterwork"", 1, $D26),)& if(Vlookup(M26,INDIRECT('Formula References'!$B71),3,FALSE)>1, "" / +"" & VLOOKUP(N26,INDIRECT('Formula Refe"&"rences'!$B71),2,False)+$B26+if($D26 = ""Masterwork"", 1, $D26)-5,) & if(Vlookup(M26,INDIRECT('Formula References'!$B71),3,FALSE)>2, "" / +"" & VLOOKUP(N26,INDIRECT('Formula References'!$B71),2,False)+$B26+if($D26 = ""Masterwork"", 1, $D26)-10,) & if"&"(Vlookup(M26,INDIRECT('Formula References'!$B71),3,FALSE)>3, "" / +"" & VLOOKUP(N26,INDIRECT('Formula References'!$B71),2,False)+$B26+if($D26 = ""Masterwork"", 1, $D26)-15,) ,)& if(M26 = ""Ranged Attack"", if($AJ$74>0, ""+""&VLOOKUP(N26,INDIRECT('Form"&"ula References'!$B71),2,False)+$B26+if($D26 = ""Masterwork"", 1, $D26)& "" / "",) & if($AJ$74>1, ""+""&VLOOKUP(N26,INDIRECT('Formula References'!$B71),2,False)+$B26+if($D26 = ""Masterwork"", 1, $D26)& "" / "",) & if(Vlookup(M26,INDIRECT('Formula Ref"&"erences'!$B71),3,FALSE)>0, ""+""&VLOOKUP(N26,INDIRECT('Formula References'!$B71),2,False)+$B26+if($D26 = ""Masterwork"", 1, $D26),) & if(Vlookup(M26,INDIRECT('Formula References'!$B71),3,FALSE)>1, "" / +"" & VLOOKUP(N26,INDIRECT('Formula References'!$B"&"71),2,False)+$B26+if($D26 = ""Masterwork"", 1, $D26)-5,) & if(Vlookup(M26,INDIRECT('Formula References'!$B71),3,FALSE)>2, "" / +"" & VLOOKUP(N26,INDIRECT('Formula References'!$B71),2,False)+$B26+if($D26 = ""Masterwork"", 1, $D26)-10,) & if(Vlookup(M"&"26,INDIRECT('Formula References'!$B71),3,FALSE)>3, "" / +"" & VLOOKUP(N26,INDIRECT('Formula References'!$B71),2,False)+$B26+if($D26 = ""Masterwork"", 1, $D26)-15,) ,)& if(M26 = ""Off-Hand Melee Attack (must have TWF 1, 2, or 3 active on Buff Table)"", "&" if(Vlookup(M26,INDIRECT('Formula References'!$B71),3,FALSE)>0, ""+""&VLOOKUP(N26,INDIRECT('Formula References'!$B71),2,False)+$B26+if($D26 = ""Masterwork"", 1, $D26),) & if(Vlookup(M26,INDIRECT('Formula References'!$B71),3,FALSE)>1, "" / +"" & VLOOKUP"&"(N26,INDIRECT('Formula References'!$B71),2,False)+$B26+if($D26 = ""Masterwork"", 1, $D26)-5,) & if(Vlookup(M26,INDIRECT('Formula References'!$B71),3,FALSE)>2, "" / +"" & VLOOKUP(N26,INDIRECT('Formula References'!$B71),2,False)+$B26+if($D26 = ""Masterwo"&"rk"", 1, $D26)-10,) & if(Vlookup(M26,INDIRECT('Formula References'!$B71),3,FALSE)>3, "" / +"" & VLOOKUP(N26,INDIRECT('Formula References'!$B71),2,False)+$B26+if($D26 = ""Masterwork"", 1, $D26)-15,) ,)& if(M26 = ""Off-Hand Ranged Attack (must have TWF "&"1, 2, or 3 active on Buff Table)"", if(Vlookup(M26,INDIRECT('Formula References'!$B71),3,FALSE)>0, ""+""&VLOOKUP(N26,INDIRECT('Formula References'!$B71),2,False)+$B26+if($D26 = ""Masterwork"", 1, $D26),) & if(Vlookup(M26,INDIRECT('Formula References"&"'!$B71),3,FALSE)>1, "" / +"" & VLOOKUP(N26,INDIRECT('Formula References'!$B71),2,False)+$B26+if($D26 = ""Masterwork"", 1, $D26)-5,) & if(Vlookup(M26,INDIRECT('Formula References'!$B71),3,FALSE)>2, "" / +"" & VLOOKUP(N26,INDIRECT('Formula References'!$B"&"71),2,False)+$B26+if($D26 = ""Masterwork"", 1, $D26)-10,) & if(Vlookup(M26,INDIRECT('Formula References'!$B71),3,FALSE)>3, "" / +"" & VLOOKUP(N26,INDIRECT('Formula References'!$B71),2,False)+$B26+if($D26 = ""Masterwork"", 1, $D26)-15,) ,)& if(M26 = """&"Combat Maneuver"", if(Vlookup(M26,INDIRECT('Formula References'!$B71),3,FALSE)>0, ""+""&VLOOKUP(N26,INDIRECT('Formula References'!$B71),2,False)+$B26+if($D26 = ""Masterwork"", 1, $D26)+$AC$74,) ,)& if(M26 = ""Magic"", if(Vlookup(M26,INDIRECT('Formu"&"la References'!$B71),3,FALSE)>0, ""+""&VLOOKUP(N26,INDIRECT('Formula References'!$B71),2,False)+$B26+if($D26 = ""Masterwork"", 1, $D26),) ,)& if(M26 = ""Monk Flurry"", if(OR(arrayformula(regexmatch($AE$2:$AE$4,""Monk \(Unchained\)""))), if(Vlookup"&"(M26,INDIRECT('Formula References'!$B71),3,FALSE)>0, ""+"" & VLOOKUP(N26,INDIRECT('Formula References'!$B71),2,False)+$B26+if($D26 = ""Masterwork"", 1, $D26)+$AC$74,)& if(AND($AJ$74>0,regexmatch(N26,""Ranged"")), "" / +"" & VLOOKUP(N26,I"&"NDIRECT('Formula References'!$B71),2,False)+$B26+if($D26 = ""Masterwork"", 1, $D26),)& if(AND($AJ$74>1,regexmatch(N26,""Ranged"")), "" / +"" & VLOOKUP(N26,INDIRECT('Formula References'!$B71),2,False)+$B26+if($D26 = ""Masterwork"", 1, $D2"&"6),)& if(AND($AJ$74>3,regexmatch(N26,""Ranged"")), "" / +"" & VLOOKUP(N26,INDIRECT('Formula References'!$B71),2,False)+$B26+if($D26 = ""Masterwork"", 1, $D26),)& if(AND($AI$74>0,regexmatch(N26,""Melee"")), "" / +"" & VL"&"OOKUP(N26,INDIRECT('Formula References'!$B71),2,False)+$B26+if($D26 = ""Masterwork"", 1, $D26),)& if(Vlookup(""Monk (Unchained)"",$AE$2:$AQ$4,13,false)>0 , "" / +"" & VLOOKUP(N26,INDIRECT('Formula References'!$B71),2,False)+$B26+if($D26 = ""Masterwor"&"k"", 1, $D26),) & if(Vlookup(""Monk (Unchained)"",$AE$2:$AQ$4,13,false)>10, "" / +"" & VLOOKUP(N26,INDIRECT('Formula References'!$B71),2,False)+$B26+if($D26 = ""Masterwork"", 1, $D26),) & if(Vlookup(M26,INDIRECT('Formula References'!$B71),3,FALS"&"E)>1, "" / +"" & VLOOKUP(N26,INDIRECT('Formula References'!$B71),2,False)+$B26+if($D26 = ""Masterwork"", 1, $D26)-5,) & if(Vlookup(M26,INDIRECT('Formula References'!$B71),3,FALSE)>2, "" / +"" & VLOOKUP(N26,INDIRECT('Formula References'!$B71),2,False)"&"+$B26+if($D26 = ""Masterwork"", 1, $D26)-10,) & if(Vlookup(M26,INDIRECT('Formula References'!$B71),3,FALSE)>3, "" / +"" & VLOOKUP(N26,INDIRECT('Formula References'!$B71),2,False)+$B26+if($D26 = ""Masterwork"", 1, $D26)-15,) , if(Vlookup(M26,"&"INDIRECT('Formula References'!$B71),3,FALSE)>0, ""+"" & VLOOKUP(N26,INDIRECT('Formula References'!$B71),2,False)+$B26+if($D26 = ""Masterwork"", 1, $D26)+$AC$74-2,)& if(AND($AJ$74>0,regexmatch(N26,""Ranged"")), "" / +"" & VLOOKUP(N26,INDI"&"RECT('Formula References'!$B71),2,False)+$B26+if($D26 = ""Masterwork"", 1, $D26)-2,)& if(AND($AJ$74>1,regexmatch(N26,""Ranged"")), "" / +"" & VLOOKUP(N26,INDIRECT('Formula References'!$B71),2,False)+$B26+if($D26 = ""Masterwork"", 1, $D26"&")-2,)& if(AND($AJ$74>3,regexmatch(N26,""Ranged"")), "" / +"" & VLOOKUP(N26,INDIRECT('Formula References'!$B71),2,False)+$B26+if($D26 = ""Masterwork"", 1, $D26)-2,)& if(AND($AI$74>0,regexmatch(N26,""Melee"")), "" / +"" &"&" VLOOKUP(N26,INDIRECT('Formula References'!$B71),2,False)+$B26+if($D26 = ""Masterwork"", 1, $D26)-2,)& if(Vlookup(""Monk"",$AE$2:$AQ$4,13,false)>0 , "" / +"" & VLOOKUP(N26,INDIRECT('Formula References'!$B71),2,False)+$B26+if($D26 = ""Masterwork"", 1,"&" $D26)-2,) & if(Vlookup(M26,INDIRECT('Formula References'!$B71),3,FALSE)>1, "" / +"" & VLOOKUP(N26,INDIRECT('Formula References'!$B71),2,False)+$B26+if($D26 = ""Masterwork"", 1, $D26)-7,) & if(Vlookup(""Monk"",$AE$2:$AQ$4,13,false)>5 , "" / +"" "&"& VLOOKUP(N26,INDIRECT('Formula References'!$B71),2,False)+$B26+if($D26 = ""Masterwork"", 1, $D26)-7,) & if(Vlookup(M26,INDIRECT('Formula References'!$B71),3,FALSE)>2, "" / +"" & VLOOKUP(N26,INDIRECT('Formula References'!$B71),2,False)+$B26+if($D26 ="&" ""Masterwork"", 1, $D26)-12,) & if(Vlookup(""Monk"",$AE$2:$AQ$4,13,false)>10 , "" / +"" & VLOOKUP(N26,INDIRECT('Formula References'!$B71),2,False)+$B26+if($D26 = ""Masterwork"", 1, $D26)-12,) & if(Vlookup(""Monk"",$AE$2:$AQ$4,13,false)>15 , "" "&"/ +"" & VLOOKUP(N26,INDIRECT('Formula References'!$B71),2,False)+$B26+if($D26 = ""Masterwork"", 1, $D26)-17,) ),)& if(M26 = ""Single Attack"", if(Vlookup(M26,INDIRECT('Formula References'!$B71),3,FALSE)>0, ""+""&VLOOKUP(N26,INDIRECT('Formula Reference"&"s'!$B71),2,False)+$B26+if($D26 = ""Masterwork"", 1, $D26)+$AC$74,) ,)& if(M26 = ""Natural Attacks (Searches attack name for # of attacks, defaults to 1)"", ""+""&VLOOKUP(N26,INDIRECT('Formula References'!$B71),2,False)"&"+$B26+if($D26 = ""Masterwork"", 1, $D26)+if(REGEXMATCH(N26,""Haste Applies""),$AC$74,)& if(AND(REGEXMATCH(N26,""Haste Applies""),$AI$74>0), "" / +"" & VLOOKUP(N26,INDIRECT('Formula References'!$B71),2,False)+$B26+if($D26 = ""Masterwork"", 1, $D26),)& "&" if(REGEXMATCH(E26,""[2-9]+""), "" / +""&VLOOKUP(N26,INDIRECT('Formula References'!$B71),2,False)+$B26+if($D26 = ""Masterwork"", 1, $D26),)& if(REGEXMATCH(E26,""[3-9]+""), "" / +""&VLOOKUP(N26,INDIRECT('Formula References'!$B71),2,False)+$B26+if($D26 "&"= ""Masterwork"", 1, $D26),)& if(REGEXMATCH(E26,""[4-9]+""), "" / +""&VLOOKUP(N26,INDIRECT('Formula References'!$B71),2,False)+$B26+if($D26 = ""Masterwork"", 1, $D26),)& if(REGEXMATCH(E26,""[5-9]+""), "" / +""&VLOOKUP(N26,INDIRECT('Formula Reference"&"s'!$B71),2,False)+$B26+if($D26 = ""Masterwork"", 1, $D26),)& if(REGEXMATCH(E26,""[6-9]+""), "" / +""&VLOOKUP(N26,INDIRECT('Formula References'!$B71),2,False)+$B26+if($D26 = ""Masterwork"", 1, $D26),) ,)& if( M26 = ""Other"", if( N26=""Alc"&"hemist Bomb (DEX to hit, INT to damage) (No Rapid Bomb Discovery)"", if(1+int(BaseAttack/5)>0, ""+""&VLOOKUP(N26,INDIRECT('Formula References'!$B71),2,False)+$B26+if($D26 = ""Masterwork"", 1, $D26),) ,)& if( N26=""Alchemist Bomb (DEX "&"to hit, INT to damage) (Rapid Bomb)"", if($AJ$74=1, ""+""&VLOOKUP(N26,INDIRECT('Formula References'!$B71),2,False)+$B26+if($D26 = ""Masterwork"", 1, $D26)& "" / "",) & if($AJ$74=2, ""+""&VLOOKUP(N26,INDIRECT('Formula References'!$B71),2,False)"&"+$B26+if($D26 = ""Masterwork"", 1, $D26)& "" / "",) & if(1+int(BaseAttack/5)>0, ""+""&VLOOKUP(N26,INDIRECT('Formula References'!$B71),2,False)+$B26+if($D26 = ""Masterwork"", 1, $D26),) & if(1+int(BaseAttack/5)>1, "" / +"" & VLOOKUP(N26,INDIREC"&"T('Formula References'!$B71),2,False)+$B26+if($D26 = ""Masterwork"", 1, $D26)-5,) & if(1+int(BaseAttack/5)>2, "" / +"" & VLOOKUP(N26,INDIRECT('Formula References'!$B71),2,False)+$B26+if($D26 = ""Masterwork"", 1, $D26)-10,) & if(1+int(BaseAttac"&"k/5)>3, "" / +"" & VLOOKUP(N26,INDIRECT('Formula References'!$B71),2,False)+$B26+if($D26 = ""Masterwork"", 1, $D26)-15,) ,)& if( N26=""Witch Prehensile Hair (INT to hit / INT to damage)"", if(1+int(BaseAttack/5)>0, ""+""&VLOOKUP(N26,I"&"NDIRECT('Formula References'!$B71),2,False)+$B26+if($D26 = ""Masterwork"", 1, $D26)+$AC$74,) ,)& if(REGEXMATCH(N26,""Kineticist""), if(REGEXMATCH(N26,""Ranged""), ""+""&VLOOKUP(N26,INDIRECT('Formula References'!$B71),2,False)+$B26+if($D26 ="&" ""Masterwork"", 1, $D26),)& if(AND(REGEXMATCH(N26,""Melee""),Vlookup(M26,INDIRECT('Formula References'!$B71),3,FALSE)>0), ""+""&VLOOKUP(N26,INDIRECT('Formula References'!$B71),2,False)+$B26+if($D26 = ""Masterwork"", 1, $D26)+$AC$74,)& if(A"&"ND(REGEXMATCH(N26,""Melee""),$AI$74>0), "" / +""&VLOOKUP(N26,INDIRECT('Formula References'!$B71),2,False)+$B26+if($D26 = ""Masterwork"", 1, $D26),)& if(AND(REGEXMATCH(N26,""Melee""),Vlookup(M26,INDIR"&"ECT('Formula References'!$B71),3,FALSE)>1), "" / +""&VLOOKUP(N26,INDIRECT('Formula References'!$B71),2,False)+$B26+if($D26 = ""Masterwork"", 1, $D26)-5,)& if(AND(REGEXMATCH(N26,""Melee""),Vlookup(M26,INDIRECT('Formula References'!$B71),3,FALSE)>2), "&""" / +""&VLOOKUP(N26,INDIRECT('Formula References'!$B71),2,False)+$B26+if($D26 = ""Masterwork"", 1, $D26)-10,)& if(AND(REGEXMATCH(N26,""Melee""),Vlookup(M26,INDIRECT('Formula References'!$B71),3,FALSE)>3), "" / +""&VLOOKUP(N26,INDIRECT('Formula Refe"&"rences'!$B71),2,False)+$B26+if($D26 = ""Masterwork"", 1, $D26)-15,) ,) ,) ,)"),"+10") -> +10 | U26: 1d10 + 2d4+1 (Bleed) | V26: {=iferror(if(istext(N26),U26 & " + " & vlookup(N26,INDIRECT('Formula References'!B71),3,False)+if(isnumber(D26),D26)+C26,),"")} -> 1d10 + 2d4+1 (Bleed) + 8 | Y26: 18-20 | AD26: =IF(OR( iferror(vlookup($AE$2, 'Class Skills'!$A:$BE,MATCH(AE26,'Class Skills'!$1:$1,0),false),"")="X", iferror(vlookup($AE$3, 'Class Skills'!$A:$BE,MATCH(AE26,'Class Skills'!$1:$1,0),false),"")="X", iferror(vlookup($AE$4, 'Class Skills'!$A:$BE,MATCH(AE26,'Class Skills'!$1:$1,0),false),"")="X", iferror(vlookup(#REF!, 'Class Skills'!$A:$BE,MATCH(AE26,'Class Skills'!$1:$1,0),false),"")="X"),"X",) -> X | AE26: Ride | AI26: =HLOOKUP(AE26,'Class Skills'!$1:$3,3,false) -> Dex | AJ26: =if(AND(HLOOKUP(AE26,'Class Skills'!$1:$2,2,false)="Trained Only",AL26<1),,SUM(AL26:AQ26)) -> 3 | AK26: = | AM26: =IFERROR(__xludf.DUMMYFUNCTION("offset($E$8,match(AI26,ARRAYFORMULA(Proper(lower(REGEXEXTRACT($E$9:$E$14,""\w\w\w"")))),0),2)"),3.0) -> 3 | AN26: =if(AND(AL26 > 0,AD26 ="X"), 3, ) | AP26: =IFERROR(__xludf.DUMMYFUNCTION("if( or(arrayformula(regexmatch($AR$76:$AR$110,AE26))), sum(arrayformula(iferror(value(regexextract(filter( $AR$76:$AR$110, $K$76:$K$110=""ACTIVE"", regexmatch($AR$76:$AR$110,AE26)), ""[-\d]+"")))))+tSkill,tSkill)"),0.0) -> 0 | AQ26: =iferror(if( if(hlookup(AE26,'Class Skills'!$1:$4,4,false)="Armor Penalty",'Formula References'!$Q$156,) +if(AND(isnumber($C$38),AE26="Climb"),8,) +if(AND(isnumber($C$39),AE26="Swim"),8,) +if(AE26="Fly", Vlookup(Size,SizeTable,5,False),) +if(AE26="Fly",if($M$37="Clumsy",-8,if($M$37="Poor",-4,if($M$37="Average",0,if($M$37="Good",4,if($M$37="Perfect",8,0)))))) +if(AE26="Stealth",Vlookup(Size,SizeTable,6,False)) =0,, if(hlookup(AE26,'Class Skills'!$1:$4,4,false)="Armor Penalty",'Formula References'!$Q$156,) +if(AND(isnumber($C$38),AE26="Climb"),8,) +if(AND(isnumber($C$39),AE26="Swim"),8,) +if(AE26="Fly", Vlookup(Size,SizeTable,5,False),) +if(AE26="Fly",if($M$37="Clumsy",-8,if($M$37="Poor",-4,if($M$37="Average",0,if($M$37="Good",4,if($M$37="Perfect",8,0)))))) +if(AE26="Stealth",Vlookup(Size,SizeTable,6,False))),"")
E27: Izanami's Nodachi (Soulburn) | M27: Melee Attack | N27: INT to hit, INT to damage | O27: =IFERROR(__xludf.DUMMYFUNCTION("if(istext(N27), if(M27 = ""Melee Attack"",""+""& if(Vlookup(M27,INDIRECT('Formula References'!$B72),3,FALSE)>0, VLOOKUP(N27,INDIRECT('Formula References'!$B72),2,False)+$B27+if($D27 = ""Masterwork"", 1, $D27),)+$AC$74& "&" if($AI$74>0, "" / +"" & VLOOKUP(N27,INDIRECT('Formula References'!$B72),2,False)+$B27+if($D27 = ""Masterwork"", 1, $D27),)& if(Vlookup(M27,INDIRECT('Formula References'!$B72),3,FALSE)>1, "" / +"" & VLOOKUP(N27,INDIRECT('Formula Refe"&"rences'!$B72),2,False)+$B27+if($D27 = ""Masterwork"", 1, $D27)-5,) & if(Vlookup(M27,INDIRECT('Formula References'!$B72),3,FALSE)>2, "" / +"" & VLOOKUP(N27,INDIRECT('Formula References'!$B72),2,False)+$B27+if($D27 = ""Masterwork"", 1, $D27)-10,) & if"&"(Vlookup(M27,INDIRECT('Formula References'!$B72),3,FALSE)>3, "" / +"" & VLOOKUP(N27,INDIRECT('Formula References'!$B72),2,False)+$B27+if($D27 = ""Masterwork"", 1, $D27)-15,) ,)& if(M27 = ""Ranged Attack"", if($AJ$74>0, ""+""&VLOOKUP(N27,INDIRECT('Form"&"ula References'!$B72),2,False)+$B27+if($D27 = ""Masterwork"", 1, $D27)& "" / "",) & if($AJ$74>1, ""+""&VLOOKUP(N27,INDIRECT('Formula References'!$B72),2,False)+$B27+if($D27 = ""Masterwork"", 1, $D27)& "" / "",) & if(Vlookup(M27,INDIRECT('Formula Ref"&"erences'!$B72),3,FALSE)>0, ""+""&VLOOKUP(N27,INDIRECT('Formula References'!$B72),2,False)+$B27+if($D27 = ""Masterwork"", 1, $D27),) & if(Vlookup(M27,INDIRECT('Formula References'!$B72),3,FALSE)>1, "" / +"" & VLOOKUP(N27,INDIRECT('Formula References'!$B"&"72),2,False)+$B27+if($D27 = ""Masterwork"", 1, $D27)-5,) & if(Vlookup(M27,INDIRECT('Formula References'!$B72),3,FALSE)>2, "" / +"" & VLOOKUP(N27,INDIRECT('Formula References'!$B72),2,False)+$B27+if($D27 = ""Masterwork"", 1, $D27)-10,) & if(Vlookup(M"&"27,INDIRECT('Formula References'!$B72),3,FALSE)>3, "" / +"" & VLOOKUP(N27,INDIRECT('Formula References'!$B72),2,False)+$B27+if($D27 = ""Masterwork"", 1, $D27)-15,) ,)& if(M27 = ""Off-Hand Melee Attack (must have TWF 1, 2, or 3 active on Buff Table)"", "&" if(Vlookup(M27,INDIRECT('Formula References'!$B72),3,FALSE)>0, ""+""&VLOOKUP(N27,INDIRECT('Formula References'!$B72),2,False)+$B27+if($D27 = ""Masterwork"", 1, $D27),) & if(Vlookup(M27,INDIRECT('Formula References'!$B72),3,FALSE)>1, "" / +"" & VLOOKUP"&"(N27,INDIRECT('Formula References'!$B72),2,False)+$B27+if($D27 = ""Masterwork"", 1, $D27)-5,) & if(Vlookup(M27,INDIRECT('Formula References'!$B72),3,FALSE)>2, "" / +"" & VLOOKUP(N27,INDIRECT('Formula References'!$B72),2,False)+$B27+if($D27 = ""Masterwo"&"rk"", 1, $D27)-10,) & if(Vlookup(M27,INDIRECT('Formula References'!$B72),3,FALSE)>3, "" / +"" & VLOOKUP(N27,INDIRECT('Formula References'!$B72),2,False)+$B27+if($D27 = ""Masterwork"", 1, $D27)-15,) ,)& if(M27 = ""Off-Hand Ranged Attack (must have TWF "&"1, 2, or 3 active on Buff Table)"", if(Vlookup(M27,INDIRECT('Formula References'!$B72),3,FALSE)>0, ""+""&VLOOKUP(N27,INDIRECT('Formula References'!$B72),2,False)+$B27+if($D27 = ""Masterwork"", 1, $D27),) & if(Vlookup(M27,INDIRECT('Formula References"&"'!$B72),3,FALSE)>1, "" / +"" & VLOOKUP(N27,INDIRECT('Formula References'!$B72),2,False)+$B27+if($D27 = ""Masterwork"", 1, $D27)-5,) & if(Vlookup(M27,INDIRECT('Formula References'!$B72),3,FALSE)>2, "" / +"" & VLOOKUP(N27,INDIRECT('Formula References'!$B"&"72),2,False)+$B27+if($D27 = ""Masterwork"", 1, $D27)-10,) & if(Vlookup(M27,INDIRECT('Formula References'!$B72),3,FALSE)>3, "" / +"" & VLOOKUP(N27,INDIRECT('Formula References'!$B72),2,False)+$B27+if($D27 = ""Masterwork"", 1, $D27)-15,) ,)& if(M27 = """&"Combat Maneuver"", if(Vlookup(M27,INDIRECT('Formula References'!$B72),3,FALSE)>0, ""+""&VLOOKUP(N27,INDIRECT('Formula References'!$B72),2,False)+$B27+if($D27 = ""Masterwork"", 1, $D27)+$AC$74,) ,)& if(M27 = ""Magic"", if(Vlookup(M27,INDIRECT('Formu"&"la References'!$B72),3,FALSE)>0, ""+""&VLOOKUP(N27,INDIRECT('Formula References'!$B72),2,False)+$B27+if($D27 = ""Masterwork"", 1, $D27),) ,)& if(M27 = ""Monk Flurry"", if(OR(arrayformula(regexmatch($AE$2:$AE$4,""Monk \(Unchained\)""))), if(Vlookup"&"(M27,INDIRECT('Formula References'!$B72),3,FALSE)>0, ""+"" & VLOOKUP(N27,INDIRECT('Formula References'!$B72),2,False)+$B27+if($D27 = ""Masterwork"", 1, $D27)+$AC$74,)& if(AND($AJ$74>0,regexmatch(N27,""Ranged"")), "" / +"" & VLOOKUP(N27,I"&"NDIRECT('Formula References'!$B72),2,False)+$B27+if($D27 = ""Masterwork"", 1, $D27),)& if(AND($AJ$74>1,regexmatch(N27,""Ranged"")), "" / +"" & VLOOKUP(N27,INDIRECT('Formula References'!$B72),2,False)+$B27+if($D27 = ""Masterwork"", 1, $D2"&"7),)& if(AND($AJ$74>3,regexmatch(N27,""Ranged"")), "" / +"" & VLOOKUP(N27,INDIRECT('Formula References'!$B72),2,False)+$B27+if($D27 = ""Masterwork"", 1, $D27),)& if(AND($AI$74>0,regexmatch(N27,""Melee"")), "" / +"" & VL"&"OOKUP(N27,INDIRECT('Formula References'!$B72),2,False)+$B27+if($D27 = ""Masterwork"", 1, $D27),)& if(Vlookup(""Monk (Unchained)"",$AE$2:$AQ$4,13,false)>0 , "" / +"" & VLOOKUP(N27,INDIRECT('Formula References'!$B72),2,False)+$B27+if($D27 = ""Masterwor"&"k"", 1, $D27),) & if(Vlookup(""Monk (Unchained)"",$AE$2:$AQ$4,13,false)>10, "" / +"" & VLOOKUP(N27,INDIRECT('Formula References'!$B72),2,False)+$B27+if($D27 = ""Masterwork"", 1, $D27),) & if(Vlookup(M27,INDIRECT('Formula References'!$B72),3,FALS"&"E)>1, "" / +"" & VLOOKUP(N27,INDIRECT('Formula References'!$B72),2,False)+$B27+if($D27 = ""Masterwork"", 1, $D27)-5,) & if(Vlookup(M27,INDIRECT('Formula References'!$B72),3,FALSE)>2, "" / +"" & VLOOKUP(N27,INDIRECT('Formula References'!$B72),2,False)"&"+$B27+if($D27 = ""Masterwork"", 1, $D27)-10,) & if(Vlookup(M27,INDIRECT('Formula References'!$B72),3,FALSE)>3, "" / +"" & VLOOKUP(N27,INDIRECT('Formula References'!$B72),2,False)+$B27+if($D27 = ""Masterwork"", 1, $D27)-15,) , if(Vlookup(M27,"&"INDIRECT('Formula References'!$B72),3,FALSE)>0, ""+"" & VLOOKUP(N27,INDIRECT('Formula References'!$B72),2,False)+$B27+if($D27 = ""Masterwork"", 1, $D27)+$AC$74-2,)& if(AND($AJ$74>0,regexmatch(N27,""Ranged"")), "" / +"" & VLOOKUP(N27,INDI"&"RECT('Formula References'!$B72),2,False)+$B27+if($D27 = ""Masterwork"", 1, $D27)-2,)& if(AND($AJ$74>1,regexmatch(N27,""Ranged"")), "" / +"" & VLOOKUP(N27,INDIRECT('Formula References'!$B72),2,False)+$B27+if($D27 = ""Masterwork"", 1, $D27"&")-2,)& if(AND($AJ$74>3,regexmatch(N27,""Ranged"")), "" / +"" & VLOOKUP(N27,INDIRECT('Formula References'!$B72),2,False)+$B27+if($D27 = ""Masterwork"", 1, $D27)-2,)& if(AND($AI$74>0,regexmatch(N27,""Melee"")), "" / +"" &"&" VLOOKUP(N27,INDIRECT('Formula References'!$B72),2,False)+$B27+if($D27 = ""Masterwork"", 1, $D27)-2,)& if(Vlookup(""Monk"",$AE$2:$AQ$4,13,false)>0 , "" / +"" & VLOOKUP(N27,INDIRECT('Formula References'!$B72),2,False)+$B27+if($D27 = ""Masterwork"", 1,"&" $D27)-2,) & if(Vlookup(M27,INDIRECT('Formula References'!$B72),3,FALSE)>1, "" / +"" & VLOOKUP(N27,INDIRECT('Formula References'!$B72),2,False)+$B27+if($D27 = ""Masterwork"", 1, $D27)-7,) & if(Vlookup(""Monk"",$AE$2:$AQ$4,13,false)>5 , "" / +"" "&"& VLOOKUP(N27,INDIRECT('Formula References'!$B72),2,False)+$B27+if($D27 = ""Masterwork"", 1, $D27)-7,) & if(Vlookup(M27,INDIRECT('Formula References'!$B72),3,FALSE)>2, "" / +"" & VLOOKUP(N27,INDIRECT('Formula References'!$B72),2,False)+$B27+if($D27 ="&" ""Masterwork"", 1, $D27)-12,) & if(Vlookup(""Monk"",$AE$2:$AQ$4,13,false)>10 , "" / +"" & VLOOKUP(N27,INDIRECT('Formula References'!$B72),2,False)+$B27+if($D27 = ""Masterwork"", 1, $D27)-12,) & if(Vlookup(""Monk"",$AE$2:$AQ$4,13,false)>15 , "" "&"/ +"" & VLOOKUP(N27,INDIRECT('Formula References'!$B72),2,False)+$B27+if($D27 = ""Masterwork"", 1, $D27)-17,) ),)& if(M27 = ""Single Attack"", if(Vlookup(M27,INDIRECT('Formula References'!$B72),3,FALSE)>0, ""+""&VLOOKUP(N27,INDIRECT('Formula Reference"&"s'!$B72),2,False)+$B27+if($D27 = ""Masterwork"", 1, $D27)+$AC$74,) ,)& if(M27 = ""Natural Attacks (Searches attack name for # of attacks, defaults to 1)"", ""+""&VLOOKUP(N27,INDIRECT('Formula References'!$B72),2,False)"&"+$B27+if($D27 = ""Masterwork"", 1, $D27)+if(REGEXMATCH(N27,""Haste Applies""),$AC$74,)& if(AND(REGEXMATCH(N27,""Haste Applies""),$AI$74>0), "" / +"" & VLOOKUP(N27,INDIRECT('Formula References'!$B72),2,False)+$B27+if($D27 = ""Masterwork"", 1, $D27),)& "&" if(REGEXMATCH(E27,""[2-9]+""), "" / +""&VLOOKUP(N27,INDIRECT('Formula References'!$B72),2,False)+$B27+if($D27 = ""Masterwork"", 1, $D27),)& if(REGEXMATCH(E27,""[3-9]+""), "" / +""&VLOOKUP(N27,INDIRECT('Formula References'!$B72),2,False)+$B27+if($D27 "&"= ""Masterwork"", 1, $D27),)& if(REGEXMATCH(E27,""[4-9]+""), "" / +""&VLOOKUP(N27,INDIRECT('Formula References'!$B72),2,False)+$B27+if($D27 = ""Masterwork"", 1, $D27),)& if(REGEXMATCH(E27,""[5-9]+""), "" / +""&VLOOKUP(N27,INDIRECT('Formula Reference"&"s'!$B72),2,False)+$B27+if($D27 = ""Masterwork"", 1, $D27),)& if(REGEXMATCH(E27,""[6-9]+""), "" / +""&VLOOKUP(N27,INDIRECT('Formula References'!$B72),2,False)+$B27+if($D27 = ""Masterwork"", 1, $D27),) ,)& if( M27 = ""Other"", if( N27=""Alc"&"hemist Bomb (DEX to hit, INT to damage) (No Rapid Bomb Discovery)"", if(1+int(BaseAttack/5)>0, ""+""&VLOOKUP(N27,INDIRECT('Formula References'!$B72),2,False)+$B27+if($D27 = ""Masterwork"", 1, $D27),) ,)& if( N27=""Alchemist Bomb (DEX "&"to hit, INT to damage) (Rapid Bomb)"", if($AJ$74=1, ""+""&VLOOKUP(N27,INDIRECT('Formula References'!$B72),2,False)+$B27+if($D27 = ""Masterwork"", 1, $D27)& "" / "",) & if($AJ$74=2, ""+""&VLOOKUP(N27,INDIRECT('Formula References'!$B72),2,False)"&"+$B27+if($D27 = ""Masterwork"", 1, $D27)& "" / "",) & if(1+int(BaseAttack/5)>0, ""+""&VLOOKUP(N27,INDIRECT('Formula References'!$B72),2,False)+$B27+if($D27 = ""Masterwork"", 1, $D27),) & if(1+int(BaseAttack/5)>1, "" / +"" & VLOOKUP(N27,INDIREC"&"T('Formula References'!$B72),2,False)+$B27+if($D27 = ""Masterwork"", 1, $D27)-5,) & if(1+int(BaseAttack/5)>2, "" / +"" & VLOOKUP(N27,INDIRECT('Formula References'!$B72),2,False)+$B27+if($D27 = ""Masterwork"", 1, $D27)-10,) & if(1+int(BaseAttac"&"k/5)>3, "" / +"" & VLOOKUP(N27,INDIRECT('Formula References'!$B72),2,False)+$B27+if($D27 = ""Masterwork"", 1, $D27)-15,) ,)& if( N27=""Witch Prehensile Hair (INT to hit / INT to damage)"", if(1+int(BaseAttack/5)>0, ""+""&VLOOKUP(N27,I"&"NDIRECT('Formula References'!$B72),2,False)+$B27+if($D27 = ""Masterwork"", 1, $D27)+$AC$74,) ,)& if(REGEXMATCH(N27,""Kineticist""), if(REGEXMATCH(N27,""Ranged""), ""+""&VLOOKUP(N27,INDIRECT('Formula References'!$B72),2,False)+$B27+if($D27 ="&" ""Masterwork"", 1, $D27),)& if(AND(REGEXMATCH(N27,""Melee""),Vlookup(M27,INDIRECT('Formula References'!$B72),3,FALSE)>0), ""+""&VLOOKUP(N27,INDIRECT('Formula References'!$B72),2,False)+$B27+if($D27 = ""Masterwork"", 1, $D27)+$AC$74,)& if(A"&"ND(REGEXMATCH(N27,""Melee""),$AI$74>0), "" / +""&VLOOKUP(N27,INDIRECT('Formula References'!$B72),2,False)+$B27+if($D27 = ""Masterwork"", 1, $D27),)& if(AND(REGEXMATCH(N27,""Melee""),Vlookup(M27,INDIR"&"ECT('Formula References'!$B72),3,FALSE)>1), "" / +""&VLOOKUP(N27,INDIRECT('Formula References'!$B72),2,False)+$B27+if($D27 = ""Masterwork"", 1, $D27)-5,)& if(AND(REGEXMATCH(N27,""Melee""),Vlookup(M27,INDIRECT('Formula References'!$B72),3,FALSE)>2), "&""" / +""&VLOOKUP(N27,INDIRECT('Formula References'!$B72),2,False)+$B27+if($D27 = ""Masterwork"", 1, $D27)-10,)& if(AND(REGEXMATCH(N27,""Melee""),Vlookup(M27,INDIRECT('Formula References'!$B72),3,FALSE)>3), "" / +""&VLOOKUP(N27,INDIRECT('Formula Refe"&"rences'!$B72),2,False)+$B27+if($D27 = ""Masterwork"", 1, $D27)-15,) ,) ,) ,)"),"+10") -> +10 | U27: 1d10 + 1d6 + 2d4+1 (Bleed) | V27: {=iferror(if(istext(N27),U27 & " + " & vlookup(N27,INDIRECT('Formula References'!B72),3,False)+if(isnumber(D27),D27)+C27,),"")} -> 1d10 + 1d6 + 2d4+1 (Bleed) + 8 | Y27: 18-20 | AD27: =IF(OR( iferror(vlookup($AE$2, 'Class Skills'!$A:$BE,MATCH(AE27,'Class Skills'!$1:$1,0),false),"")="X", iferror(vlookup($AE$3, 'Class Skills'!$A:$BE,MATCH(AE27,'Class Skills'!$1:$1,0),false),"")="X", iferror(vlookup($AE$4, 'Class Skills'!$A:$BE,MATCH(AE27,'Class Skills'!$1:$1,0),false),"")="X", iferror(vlookup(#REF!, 'Class Skills'!$A:$BE,MATCH(AE27,'Class Skills'!$1:$1,0),false),"")="X"),"X",) -> X | AE27: Sense Motive | AI27: =HLOOKUP(AE27,'Class Skills'!$1:$3,3,false) -> Wis | AJ27: =if(AND(HLOOKUP(AE27,'Class Skills'!$1:$2,2,false)="Trained Only",AL27<1),,SUM(AL27:AQ27)) -> 0 | AK27: = | AM27: =IFERROR(__xludf.DUMMYFUNCTION("offset($E$8,match(AI27,ARRAYFORMULA(Proper(lower(REGEXEXTRACT($E$9:$E$14,""\w\w\w"")))),0),2)"),0.0) -> 0 | AN27: =if(AND(AL27 > 0,AD27 ="X"), 3, ) | AP27: =IFERROR(__xludf.DUMMYFUNCTION("if( or(arrayformula(regexmatch($AR$76:$AR$110,AE27))), sum(arrayformula(iferror(value(regexextract(filter( $AR$76:$AR$110, $K$76:$K$110=""ACTIVE"", regexmatch($AR$76:$AR$110,AE27)), ""[-\d]+"")))))+tSkill,tSkill)"),0.0) -> 0 | AQ27: =iferror(if( if(hlookup(AE27,'Class Skills'!$1:$4,4,false)="Armor Penalty",'Formula References'!$Q$156,) +if(AND(isnumber($C$38),AE27="Climb"),8,) +if(AND(isnumber($C$39),AE27="Swim"),8,) +if(AE27="Fly", Vlookup(Size,SizeTable,5,False),) +if(AE27="Fly",if($M$37="Clumsy",-8,if($M$37="Poor",-4,if($M$37="Average",0,if($M$37="Good",4,if($M$37="Perfect",8,0)))))) +if(AE27="Stealth",Vlookup(Size,SizeTable,6,False)) =0,, if(hlookup(AE27,'Class Skills'!$1:$4,4,false)="Armor Penalty",'Formula References'!$Q$156,) +if(AND(isnumber($C$38),AE27="Climb"),8,) +if(AND(isnumber($C$39),AE27="Swim"),8,) +if(AE27="Fly", Vlookup(Size,SizeTable,5,False),) +if(AE27="Fly",if($M$37="Clumsy",-8,if($M$37="Poor",-4,if($M$37="Average",0,if($M$37="Good",4,if($M$37="Perfect",8,0)))))) +if(AE27="Stealth",Vlookup(Size,SizeTable,6,False))),"")
O28: =IFERROR(__xludf.DUMMYFUNCTION("if(istext(N28), if(M28 = ""Melee Attack"",""+""& if(Vlookup(M28,INDIRECT('Formula References'!$B73),3,FALSE)>0, VLOOKUP(N28,INDIRECT('Formula References'!$B73),2,False)+$B28+if($D28 = ""Masterwork"", 1, $D28),)+$AC$74& "&" if($AI$74>0, "" / +"" & VLOOKUP(N28,INDIRECT('Formula References'!$B73),2,False)+$B28+if($D28 = ""Masterwork"", 1, $D28),)& if(Vlookup(M28,INDIRECT('Formula References'!$B73),3,FALSE)>1, "" / +"" & VLOOKUP(N28,INDIRECT('Formula Refe"&"rences'!$B73),2,False)+$B28+if($D28 = ""Masterwork"", 1, $D28)-5,) & if(Vlookup(M28,INDIRECT('Formula References'!$B73),3,FALSE)>2, "" / +"" & VLOOKUP(N28,INDIRECT('Formula References'!$B73),2,False)+$B28+if($D28 = ""Masterwork"", 1, $D28)-10,) & if"&"(Vlookup(M28,INDIRECT('Formula References'!$B73),3,FALSE)>3, "" / +"" & VLOOKUP(N28,INDIRECT('Formula References'!$B73),2,False)+$B28+if($D28 = ""Masterwork"", 1, $D28)-15,) ,)& if(M28 = ""Ranged Attack"", if($AJ$74>0, ""+""&VLOOKUP(N28,INDIRECT('Form"&"ula References'!$B73),2,False)+$B28+if($D28 = ""Masterwork"", 1, $D28)& "" / "",) & if($AJ$74>1, ""+""&VLOOKUP(N28,INDIRECT('Formula References'!$B73),2,False)+$B28+if($D28 = ""Masterwork"", 1, $D28)& "" / "",) & if(Vlookup(M28,INDIRECT('Formula Ref"&"erences'!$B73),3,FALSE)>0, ""+""&VLOOKUP(N28,INDIRECT('Formula References'!$B73),2,False)+$B28+if($D28 = ""Masterwork"", 1, $D28),) & if(Vlookup(M28,INDIRECT('Formula References'!$B73),3,FALSE)>1, "" / +"" & VLOOKUP(N28,INDIRECT('Formula References'!$B"&"73),2,False)+$B28+if($D28 = ""Masterwork"", 1, $D28)-5,) & if(Vlookup(M28,INDIRECT('Formula References'!$B73),3,FALSE)>2, "" / +"" & VLOOKUP(N28,INDIRECT('Formula References'!$B73),2,False)+$B28+if($D28 = ""Masterwork"", 1, $D28)-10,) & if(Vlookup(M"&"28,INDIRECT('Formula References'!$B73),3,FALSE)>3, "" / +"" & VLOOKUP(N28,INDIRECT('Formula References'!$B73),2,False)+$B28+if($D28 = ""Masterwork"", 1, $D28)-15,) ,)& if(M28 = ""Off-Hand Melee Attack (must have TWF 1, 2, or 3 active on Buff Table)"", "&" if(Vlookup(M28,INDIRECT('Formula References'!$B73),3,FALSE)>0, ""+""&VLOOKUP(N28,INDIRECT('Formula References'!$B73),2,False)+$B28+if($D28 = ""Masterwork"", 1, $D28),) & if(Vlookup(M28,INDIRECT('Formula References'!$B73),3,FALSE)>1, "" / +"" & VLOOKUP"&"(N28,INDIRECT('Formula References'!$B73),2,False)+$B28+if($D28 = ""Masterwork"", 1, $D28)-5,) & if(Vlookup(M28,INDIRECT('Formula References'!$B73),3,FALSE)>2, "" / +"" & VLOOKUP(N28,INDIRECT('Formula References'!$B73),2,False)+$B28+if($D28 = ""Masterwo"&"rk"", 1, $D28)-10,) & if(Vlookup(M28,INDIRECT('Formula References'!$B73),3,FALSE)>3, "" / +"" & VLOOKUP(N28,INDIRECT('Formula References'!$B73),2,False)+$B28+if($D28 = ""Masterwork"", 1, $D28)-15,) ,)& if(M28 = ""Off-Hand Ranged Attack (must have TWF "&"1, 2, or 3 active on Buff Table)"", if(Vlookup(M28,INDIRECT('Formula References'!$B73),3,FALSE)>0, ""+""&VLOOKUP(N28,INDIRECT('Formula References'!$B73),2,False)+$B28+if($D28 = ""Masterwork"", 1, $D28),) & if(Vlookup(M28,INDIRECT('Formula References"&"'!$B73),3,FALSE)>1, "" / +"" & VLOOKUP(N28,INDIRECT('Formula References'!$B73),2,False)+$B28+if($D28 = ""Masterwork"", 1, $D28)-5,) & if(Vlookup(M28,INDIRECT('Formula References'!$B73),3,FALSE)>2, "" / +"" & VLOOKUP(N28,INDIRECT('Formula References'!$B"&"73),2,False)+$B28+if($D28 = ""Masterwork"", 1, $D28)-10,) & if(Vlookup(M28,INDIRECT('Formula References'!$B73),3,FALSE)>3, "" / +"" & VLOOKUP(N28,INDIRECT('Formula References'!$B73),2,False)+$B28+if($D28 = ""Masterwork"", 1, $D28)-15,) ,)& if(M28 = """&"Combat Maneuver"", if(Vlookup(M28,INDIRECT('Formula References'!$B73),3,FALSE)>0, ""+""&VLOOKUP(N28,INDIRECT('Formula References'!$B73),2,False)+$B28+if($D28 = ""Masterwork"", 1, $D28)+$AC$74,) ,)& if(M28 = ""Magic"", if(Vlookup(M28,INDIRECT('Formu"&"la References'!$B73),3,FALSE)>0, ""+""&VLOOKUP(N28,INDIRECT('Formula References'!$B73),2,False)+$B28+if($D28 = ""Masterwork"", 1, $D28),) ,)& if(M28 = ""Monk Flurry"", if(OR(arrayformula(regexmatch($AE$2:$AE$4,""Monk \(Unchained\)""))), if(Vlookup"&"(M28,INDIRECT('Formula References'!$B73),3,FALSE)>0, ""+"" & VLOOKUP(N28,INDIRECT('Formula References'!$B73),2,False)+$B28+if($D28 = ""Masterwork"", 1, $D28)+$AC$74,)& if(AND($AJ$74>0,regexmatch(N28,""Ranged"")), "" / +"" & VLOOKUP(N28,I"&"NDIRECT('Formula References'!$B73),2,False)+$B28+if($D28 = ""Masterwork"", 1, $D28),)& if(AND($AJ$74>1,regexmatch(N28,""Ranged"")), "" / +"" & VLOOKUP(N28,INDIRECT('Formula References'!$B73),2,False)+$B28+if($D28 = ""Masterwork"", 1, $D2"&"8),)& if(AND($AJ$74>3,regexmatch(N28,""Ranged"")), "" / +"" & VLOOKUP(N28,INDIRECT('Formula References'!$B73),2,False)+$B28+if($D28 = ""Masterwork"", 1, $D28),)& if(AND($AI$74>0,regexmatch(N28,""Melee"")), "" / +"" & VL"&"OOKUP(N28,INDIRECT('Formula References'!$B73),2,False)+$B28+if($D28 = ""Masterwork"", 1, $D28),)& if(Vlookup(""Monk (Unchained)"",$AE$2:$AQ$4,13,false)>0 , "" / +"" & VLOOKUP(N28,INDIRECT('Formula References'!$B73),2,False)+$B28+if($D28 = ""Masterwor"&"k"", 1, $D28),) & if(Vlookup(""Monk (Unchained)"",$AE$2:$AQ$4,13,false)>10, "" / +"" & VLOOKUP(N28,INDIRECT('Formula References'!$B73),2,False)+$B28+if($D28 = ""Masterwork"", 1, $D28),) & if(Vlookup(M28,INDIRECT('Formula References'!$B73),3,FALS"&"E)>1, "" / +"" & VLOOKUP(N28,INDIRECT('Formula References'!$B73),2,False)+$B28+if($D28 = ""Masterwork"", 1, $D28)-5,) & if(Vlookup(M28,INDIRECT('Formula References'!$B73),3,FALSE)>2, "" / +"" & VLOOKUP(N28,INDIRECT('Formula References'!$B73),2,False)"&"+$B28+if($D28 = ""Masterwork"", 1, $D28)-10,) & if(Vlookup(M28,INDIRECT('Formula References'!$B73),3,FALSE)>3, "" / +"" & VLOOKUP(N28,INDIRECT('Formula References'!$B73),2,False)+$B28+if($D28 = ""Masterwork"", 1, $D28)-15,) , if(Vlookup(M28,"&"INDIRECT('Formula References'!$B73),3,FALSE)>0, ""+"" & VLOOKUP(N28,INDIRECT('Formula References'!$B73),2,False)+$B28+if($D28 = ""Masterwork"", 1, $D28)+$AC$74-2,)& if(AND($AJ$74>0,regexmatch(N28,""Ranged"")), "" / +"" & VLOOKUP(N28,INDI"&"RECT('Formula References'!$B73),2,False)+$B28+if($D28 = ""Masterwork"", 1, $D28)-2,)& if(AND($AJ$74>1,regexmatch(N28,""Ranged"")), "" / +"" & VLOOKUP(N28,INDIRECT('Formula References'!$B73),2,False)+$B28+if($D28 = ""Masterwork"", 1, $D28"&")-2,)& if(AND($AJ$74>3,regexmatch(N28,""Ranged"")), "" / +"" & VLOOKUP(N28,INDIRECT('Formula References'!$B73),2,False)+$B28+if($D28 = ""Masterwork"", 1, $D28)-2,)& if(AND($AI$74>0,regexmatch(N28,""Melee"")), "" / +"" &"&" VLOOKUP(N28,INDIRECT('Formula References'!$B73),2,False)+$B28+if($D28 = ""Masterwork"", 1, $D28)-2,)& if(Vlookup(""Monk"",$AE$2:$AQ$4,13,false)>0 , "" / +"" & VLOOKUP(N28,INDIRECT('Formula References'!$B73),2,False)+$B28+if($D28 = ""Masterwork"", 1,"&" $D28)-2,) & if(Vlookup(M28,INDIRECT('Formula References'!$B73),3,FALSE)>1, "" / +"" & VLOOKUP(N28,INDIRECT('Formula References'!$B73),2,False)+$B28+if($D28 = ""Masterwork"", 1, $D28)-7,) & if(Vlookup(""Monk"",$AE$2:$AQ$4,13,false)>5 , "" / +"" "&"& VLOOKUP(N28,INDIRECT('Formula References'!$B73),2,False)+$B28+if($D28 = ""Masterwork"", 1, $D28)-7,) & if(Vlookup(M28,INDIRECT('Formula References'!$B73),3,FALSE)>2, "" / +"" & VLOOKUP(N28,INDIRECT('Formula References'!$B73),2,False)+$B28+if($D28 ="&" ""Masterwork"", 1, $D28)-12,) & if(Vlookup(""Monk"",$AE$2:$AQ$4,13,false)>10 , "" / +"" & VLOOKUP(N28,INDIRECT('Formula References'!$B73),2,False)+$B28+if($D28 = ""Masterwork"", 1, $D28)-12,) & if(Vlookup(""Monk"",$AE$2:$AQ$4,13,false)>15 , "" "&"/ +"" & VLOOKUP(N28,INDIRECT('Formula References'!$B73),2,False)+$B28+if($D28 = ""Masterwork"", 1, $D28)-17,) ),)& if(M28 = ""Single Attack"", if(Vlookup(M28,INDIRECT('Formula References'!$B73),3,FALSE)>0, ""+""&VLOOKUP(N28,INDIRECT('Formula Reference"&"s'!$B73),2,False)+$B28+if($D28 = ""Masterwork"", 1, $D28)+$AC$74,) ,)& if(M28 = ""Natural Attacks (Searches attack name for # of attacks, defaults to 1)"", ""+""&VLOOKUP(N28,INDIRECT('Formula References'!$B73),2,False)"&"+$B28+if($D28 = ""Masterwork"", 1, $D28)+if(REGEXMATCH(N28,""Haste Applies""),$AC$74,)& if(AND(REGEXMATCH(N28,""Haste Applies""),$AI$74>0), "" / +"" & VLOOKUP(N28,INDIRECT('Formula References'!$B73),2,False)+$B28+if($D28 = ""Masterwork"", 1, $D28),)& "&" if(REGEXMATCH(E28,""[2-9]+""), "" / +""&VLOOKUP(N28,INDIRECT('Formula References'!$B73),2,False)+$B28+if($D28 = ""Masterwork"", 1, $D28),)& if(REGEXMATCH(E28,""[3-9]+""), "" / +""&VLOOKUP(N28,INDIRECT('Formula References'!$B73),2,False)+$B28+if($D28 "&"= ""Masterwork"", 1, $D28),)& if(REGEXMATCH(E28,""[4-9]+""), "" / +""&VLOOKUP(N28,INDIRECT('Formula References'!$B73),2,False)+$B28+if($D28 = ""Masterwork"", 1, $D28),)& if(REGEXMATCH(E28,""[5-9]+""), "" / +""&VLOOKUP(N28,INDIRECT('Formula Reference"&"s'!$B73),2,False)+$B28+if($D28 = ""Masterwork"", 1, $D28),)& if(REGEXMATCH(E28,""[6-9]+""), "" / +""&VLOOKUP(N28,INDIRECT('Formula References'!$B73),2,False)+$B28+if($D28 = ""Masterwork"", 1, $D28),) ,)& if( M28 = ""Other"", if( N28=""Alc"&"hemist Bomb (DEX to hit, INT to damage) (No Rapid Bomb Discovery)"", if(1+int(BaseAttack/5)>0, ""+""&VLOOKUP(N28,INDIRECT('Formula References'!$B73),2,False)+$B28+if($D28 = ""Masterwork"", 1, $D28),) ,)& if( N28=""Alchemist Bomb (DEX "&"to hit, INT to damage) (Rapid Bomb)"", if($AJ$74=1, ""+""&VLOOKUP(N28,INDIRECT('Formula References'!$B73),2,False)+$B28+if($D28 = ""Masterwork"", 1, $D28)& "" / "",) & if($AJ$74=2, ""+""&VLOOKUP(N28,INDIRECT('Formula References'!$B73),2,False)"&"+$B28+if($D28 = ""Masterwork"", 1, $D28)& "" / "",) & if(1+int(BaseAttack/5)>0, ""+""&VLOOKUP(N28,INDIRECT('Formula References'!$B73),2,False)+$B28+if($D28 = ""Masterwork"", 1, $D28),) & if(1+int(BaseAttack/5)>1, "" / +"" & VLOOKUP(N28,INDIREC"&"T('Formula References'!$B73),2,False)+$B28+if($D28 = ""Masterwork"", 1, $D28)-5,) & if(1+int(BaseAttack/5)>2, "" / +"" & VLOOKUP(N28,INDIRECT('Formula References'!$B73),2,False)+$B28+if($D28 = ""Masterwork"", 1, $D28)-10,) & if(1+int(BaseAttac"&"k/5)>3, "" / +"" & VLOOKUP(N28,INDIRECT('Formula References'!$B73),2,False)+$B28+if($D28 = ""Masterwork"", 1, $D28)-15,) ,)& if( N28=""Witch Prehensile Hair (INT to hit / INT to damage)"", if(1+int(BaseAttack/5)>0, ""+""&VLOOKUP(N28,I"&"NDIRECT('Formula References'!$B73),2,False)+$B28+if($D28 = ""Masterwork"", 1, $D28)+$AC$74,) ,)& if(REGEXMATCH(N28,""Kineticist""), if(REGEXMATCH(N28,""Ranged""), ""+""&VLOOKUP(N28,INDIRECT('Formula References'!$B73),2,False)+$B28+if($D28 ="&" ""Masterwork"", 1, $D28),)& if(AND(REGEXMATCH(N28,""Melee""),Vlookup(M28,INDIRECT('Formula References'!$B73),3,FALSE)>0), ""+""&VLOOKUP(N28,INDIRECT('Formula References'!$B73),2,False)+$B28+if($D28 = ""Masterwork"", 1, $D28)+$AC$74,)& if(A"&"ND(REGEXMATCH(N28,""Melee""),$AI$74>0), "" / +""&VLOOKUP(N28,INDIRECT('Formula References'!$B73),2,False)+$B28+if($D28 = ""Masterwork"", 1, $D28),)& if(AND(REGEXMATCH(N28,""Melee""),Vlookup(M28,INDIR"&"ECT('Formula References'!$B73),3,FALSE)>1), "" / +""&VLOOKUP(N28,INDIRECT('Formula References'!$B73),2,False)+$B28+if($D28 = ""Masterwork"", 1, $D28)-5,)& if(AND(REGEXMATCH(N28,""Melee""),Vlookup(M28,INDIRECT('Formula References'!$B73),3,FALSE)>2), "&""" / +""&VLOOKUP(N28,INDIRECT('Formula References'!$B73),2,False)+$B28+if($D28 = ""Masterwork"", 1, $D28)-10,)& if(AND(REGEXMATCH(N28,""Melee""),Vlookup(M28,INDIRECT('Formula References'!$B73),3,FALSE)>3), "" / +""&VLOOKUP(N28,INDIRECT('Formula Refe"&"rences'!$B73),2,False)+$B28+if($D28 = ""Masterwork"", 1, $D28)-15,) ,) ,) ,)"),"") | U28: 1d6 | V28: {=iferror(if(istext(N28),U28 & " + " & vlookup(N28,INDIRECT('Formula References'!B73),3,False)+if(isnumber(D28),D28)+C28,),"")} | AD28: =IF(OR( iferror(vlookup($AE$2, 'Class Skills'!$A:$BE,MATCH(AE28,'Class Skills'!$1:$1,0),false),"")="X", iferror(vlookup($AE$3, 'Class Skills'!$A:$BE,MATCH(AE28,'Class Skills'!$1:$1,0),false),"")="X", iferror(vlookup($AE$4, 'Class Skills'!$A:$BE,MATCH(AE28,'Class Skills'!$1:$1,0),false),"")="X", iferror(vlookup(#REF!, 'Class Skills'!$A:$BE,MATCH(AE28,'Class Skills'!$1:$1,0),false),"")="X"),"X",) -> X | AE28: Spellcraft | AI28: =HLOOKUP(AE28,'Class Skills'!$1:$3,3,false) -> Int | AJ28: =if(AND(HLOOKUP(AE28,'Class Skills'!$1:$2,2,false)="Trained Only",AL28<1),,SUM(AL28:AQ28)) -> 14 | AK28: = | AL28: 3 | AM28: =IFERROR(__xludf.DUMMYFUNCTION("offset($E$8,match(AI28,ARRAYFORMULA(Proper(lower(REGEXEXTRACT($E$9:$E$14,""\w\w\w"")))),0),2)"),8.0) -> 8 | AN28: =if(AND(AL28 > 0,AD28 ="X"), 3, ) -> 3 | AP28: =IFERROR(__xludf.DUMMYFUNCTION("if( or(arrayformula(regexmatch($AR$76:$AR$110,AE28))), sum(arrayformula(iferror(value(regexextract(filter( $AR$76:$AR$110, $K$76:$K$110=""ACTIVE"", regexmatch($AR$76:$AR$110,AE28)), ""[-\d]+"")))))+tSkill,tSkill)"),0.0) -> 0 | AQ28: =iferror(if( if(hlookup(AE28,'Class Skills'!$1:$4,4,false)="Armor Penalty",'Formula References'!$Q$156,) +if(AND(isnumber($C$38),AE28="Climb"),8,) +if(AND(isnumber($C$39),AE28="Swim"),8,) +if(AE28="Fly", Vlookup(Size,SizeTable,5,False),) +if(AE28="Fly",if($M$37="Clumsy",-8,if($M$37="Poor",-4,if($M$37="Average",0,if($M$37="Good",4,if($M$37="Perfect",8,0)))))) +if(AE28="Stealth",Vlookup(Size,SizeTable,6,False)) =0,, if(hlookup(AE28,'Class Skills'!$1:$4,4,false)="Armor Penalty",'Formula References'!$Q$156,) +if(AND(isnumber($C$38),AE28="Climb"),8,) +if(AND(isnumber($C$39),AE28="Swim"),8,) +if(AE28="Fly", Vlookup(Size,SizeTable,5,False),) +if(AE28="Fly",if($M$37="Clumsy",-8,if($M$37="Poor",-4,if($M$37="Average",0,if($M$37="Good",4,if($M$37="Perfect",8,0)))))) +if(AE28="Stealth",Vlookup(Size,SizeTable,6,False))),"")
O29: =IFERROR(__xludf.DUMMYFUNCTION("if(istext(N29), if(M29 = ""Melee Attack"",""+""& if(Vlookup(M29,INDIRECT('Formula References'!$B74),3,FALSE)>0, VLOOKUP(N29,INDIRECT('Formula References'!$B74),2,False)+$B29+if($D29 = ""Masterwork"", 1, $D29),)+$AC$74& "&" if($AI$74>0, "" / +"" & VLOOKUP(N29,INDIRECT('Formula References'!$B74),2,False)+$B29+if($D29 = ""Masterwork"", 1, $D29),)& if(Vlookup(M29,INDIRECT('Formula References'!$B74),3,FALSE)>1, "" / +"" & VLOOKUP(N29,INDIRECT('Formula Refe"&"rences'!$B74),2,False)+$B29+if($D29 = ""Masterwork"", 1, $D29)-5,) & if(Vlookup(M29,INDIRECT('Formula References'!$B74),3,FALSE)>2, "" / +"" & VLOOKUP(N29,INDIRECT('Formula References'!$B74),2,False)+$B29+if($D29 = ""Masterwork"", 1, $D29)-10,) & if"&"(Vlookup(M29,INDIRECT('Formula References'!$B74),3,FALSE)>3, "" / +"" & VLOOKUP(N29,INDIRECT('Formula References'!$B74),2,False)+$B29+if($D29 = ""Masterwork"", 1, $D29)-15,) ,)& if(M29 = ""Ranged Attack"", if($AJ$74>0, ""+""&VLOOKUP(N29,INDIRECT('Form"&"ula References'!$B74),2,False)+$B29+if($D29 = ""Masterwork"", 1, $D29)& "" / "",) & if($AJ$74>1, ""+""&VLOOKUP(N29,INDIRECT('Formula References'!$B74),2,False)+$B29+if($D29 = ""Masterwork"", 1, $D29)& "" / "",) & if(Vlookup(M29,INDIRECT('Formula Ref"&"erences'!$B74),3,FALSE)>0, ""+""&VLOOKUP(N29,INDIRECT('Formula References'!$B74),2,False)+$B29+if($D29 = ""Masterwork"", 1, $D29),) & if(Vlookup(M29,INDIRECT('Formula References'!$B74),3,FALSE)>1, "" / +"" & VLOOKUP(N29,INDIRECT('Formula References'!$B"&"74),2,False)+$B29+if($D29 = ""Masterwork"", 1, $D29)-5,) & if(Vlookup(M29,INDIRECT('Formula References'!$B74),3,FALSE)>2, "" / +"" & VLOOKUP(N29,INDIRECT('Formula References'!$B74),2,False)+$B29+if($D29 = ""Masterwork"", 1, $D29)-10,) & if(Vlookup(M"&"29,INDIRECT('Formula References'!$B74),3,FALSE)>3, "" / +"" & VLOOKUP(N29,INDIRECT('Formula References'!$B74),2,False)+$B29+if($D29 = ""Masterwork"", 1, $D29)-15,) ,)& if(M29 = ""Off-Hand Melee Attack (must have TWF 1, 2, or 3 active on Buff Table)"", "&" if(Vlookup(M29,INDIRECT('Formula References'!$B74),3,FALSE)>0, ""+""&VLOOKUP(N29,INDIRECT('Formula References'!$B74),2,False)+$B29+if($D29 = ""Masterwork"", 1, $D29),) & if(Vlookup(M29,INDIRECT('Formula References'!$B74),3,FALSE)>1, "" / +"" & VLOOKUP"&"(N29,INDIRECT('Formula References'!$B74),2,False)+$B29+if($D29 = ""Masterwork"", 1, $D29)-5,) & if(Vlookup(M29,INDIRECT('Formula References'!$B74),3,FALSE)>2, "" / +"" & VLOOKUP(N29,INDIRECT('Formula References'!$B74),2,False)+$B29+if($D29 = ""Masterwo"&"rk"", 1, $D29)-10,) & if(Vlookup(M29,INDIRECT('Formula References'!$B74),3,FALSE)>3, "" / +"" & VLOOKUP(N29,INDIRECT('Formula References'!$B74),2,False)+$B29+if($D29 = ""Masterwork"", 1, $D29)-15,) ,)& if(M29 = ""Off-Hand Ranged Attack (must have TWF "&"1, 2, or 3 active on Buff Table)"", if(Vlookup(M29,INDIRECT('Formula References'!$B74),3,FALSE)>0, ""+""&VLOOKUP(N29,INDIRECT('Formula References'!$B74),2,False)+$B29+if($D29 = ""Masterwork"", 1, $D29),) & if(Vlookup(M29,INDIRECT('Formula References"&"'!$B74),3,FALSE)>1, "" / +"" & VLOOKUP(N29,INDIRECT('Formula References'!$B74),2,False)+$B29+if($D29 = ""Masterwork"", 1, $D29)-5,) & if(Vlookup(M29,INDIRECT('Formula References'!$B74),3,FALSE)>2, "" / +"" & VLOOKUP(N29,INDIRECT('Formula References'!$B"&"74),2,False)+$B29+if($D29 = ""Masterwork"", 1, $D29)-10,) & if(Vlookup(M29,INDIRECT('Formula References'!$B74),3,FALSE)>3, "" / +"" & VLOOKUP(N29,INDIRECT('Formula References'!$B74),2,False)+$B29+if($D29 = ""Masterwork"", 1, $D29)-15,) ,)& if(M29 = """&"Combat Maneuver"", if(Vlookup(M29,INDIRECT('Formula References'!$B74),3,FALSE)>0, ""+""&VLOOKUP(N29,INDIRECT('Formula References'!$B74),2,False)+$B29+if($D29 = ""Masterwork"", 1, $D29)+$AC$74,) ,)& if(M29 = ""Magic"", if(Vlookup(M29,INDIRECT('Formu"&"la References'!$B74),3,FALSE)>0, ""+""&VLOOKUP(N29,INDIRECT('Formula References'!$B74),2,False)+$B29+if($D29 = ""Masterwork"", 1, $D29),) ,)& if(M29 = ""Monk Flurry"", if(OR(arrayformula(regexmatch($AE$2:$AE$4,""Monk \(Unchained\)""))), if(Vlookup"&"(M29,INDIRECT('Formula References'!$B74),3,FALSE)>0, ""+"" & VLOOKUP(N29,INDIRECT('Formula References'!$B74),2,False)+$B29+if($D29 = ""Masterwork"", 1, $D29)+$AC$74,)& if(AND($AJ$74>0,regexmatch(N29,""Ranged"")), "" / +"" & VLOOKUP(N29,I"&"NDIRECT('Formula References'!$B74),2,False)+$B29+if($D29 = ""Masterwork"", 1, $D29),)& if(AND($AJ$74>1,regexmatch(N29,""Ranged"")), "" / +"" & VLOOKUP(N29,INDIRECT('Formula References'!$B74),2,False)+$B29+if($D29 = ""Masterwork"", 1, $D2"&"9),)& if(AND($AJ$74>3,regexmatch(N29,""Ranged"")), "" / +"" & VLOOKUP(N29,INDIRECT('Formula References'!$B74),2,False)+$B29+if($D29 = ""Masterwork"", 1, $D29),)& if(AND($AI$74>0,regexmatch(N29,""Melee"")), "" / +"" & VL"&"OOKUP(N29,INDIRECT('Formula References'!$B74),2,False)+$B29+if($D29 = ""Masterwork"", 1, $D29),)& if(Vlookup(""Monk (Unchained)"",$AE$2:$AQ$4,13,false)>0 , "" / +"" & VLOOKUP(N29,INDIRECT('Formula References'!$B74),2,False)+$B29+if($D29 = ""Masterwor"&"k"", 1, $D29),) & if(Vlookup(""Monk (Unchained)"",$AE$2:$AQ$4,13,false)>10, "" / +"" & VLOOKUP(N29,INDIRECT('Formula References'!$B74),2,False)+$B29+if($D29 = ""Masterwork"", 1, $D29),) & if(Vlookup(M29,INDIRECT('Formula References'!$B74),3,FALS"&"E)>1, "" / +"" & VLOOKUP(N29,INDIRECT('Formula References'!$B74),2,False)+$B29+if($D29 = ""Masterwork"", 1, $D29)-5,) & if(Vlookup(M29,INDIRECT('Formula References'!$B74),3,FALSE)>2, "" / +"" & VLOOKUP(N29,INDIRECT('Formula References'!$B74),2,False)"&"+$B29+if($D29 = ""Masterwork"", 1, $D29)-10,) & if(Vlookup(M29,INDIRECT('Formula References'!$B74),3,FALSE)>3, "" / +"" & VLOOKUP(N29,INDIRECT('Formula References'!$B74),2,False)+$B29+if($D29 = ""Masterwork"", 1, $D29)-15,) , if(Vlookup(M29,"&"INDIRECT('Formula References'!$B74),3,FALSE)>0, ""+"" & VLOOKUP(N29,INDIRECT('Formula References'!$B74),2,False)+$B29+if($D29 = ""Masterwork"", 1, $D29)+$AC$74-2,)& if(AND($AJ$74>0,regexmatch(N29,""Ranged"")), "" / +"" & VLOOKUP(N29,INDI"&"RECT('Formula References'!$B74),2,False)+$B29+if($D29 = ""Masterwork"", 1, $D29)-2,)& if(AND($AJ$74>1,regexmatch(N29,""Ranged"")), "" / +"" & VLOOKUP(N29,INDIRECT('Formula References'!$B74),2,False)+$B29+if($D29 = ""Masterwork"", 1, $D29"&")-2,)& if(AND($AJ$74>3,regexmatch(N29,""Ranged"")), "" / +"" & VLOOKUP(N29,INDIRECT('Formula References'!$B74),2,False)+$B29+if($D29 = ""Masterwork"", 1, $D29)-2,)& if(AND($AI$74>0,regexmatch(N29,""Melee"")), "" / +"" &"&" VLOOKUP(N29,INDIRECT('Formula References'!$B74),2,False)+$B29+if($D29 = ""Masterwork"", 1, $D29)-2,)& if(Vlookup(""Monk"",$AE$2:$AQ$4,13,false)>0 , "" / +"" & VLOOKUP(N29,INDIRECT('Formula References'!$B74),2,False)+$B29+if($D29 = ""Masterwork"", 1,"&" $D29)-2,) & if(Vlookup(M29,INDIRECT('Formula References'!$B74),3,FALSE)>1, "" / +"" & VLOOKUP(N29,INDIRECT('Formula References'!$B74),2,False)+$B29+if($D29 = ""Masterwork"", 1, $D29)-7,) & if(Vlookup(""Monk"",$AE$2:$AQ$4,13,false)>5 , "" / +"" "&"& VLOOKUP(N29,INDIRECT('Formula References'!$B74),2,False)+$B29+if($D29 = ""Masterwork"", 1, $D29)-7,) & if(Vlookup(M29,INDIRECT('Formula References'!$B74),3,FALSE)>2, "" / +"" & VLOOKUP(N29,INDIRECT('Formula References'!$B74),2,False)+$B29+if($D29 ="&" ""Masterwork"", 1, $D29)-12,) & if(Vlookup(""Monk"",$AE$2:$AQ$4,13,false)>10 , "" / +"" & VLOOKUP(N29,INDIRECT('Formula References'!$B74),2,False)+$B29+if($D29 = ""Masterwork"", 1, $D29)-12,) & if(Vlookup(""Monk"",$AE$2:$AQ$4,13,false)>15 , "" "&"/ +"" & VLOOKUP(N29,INDIRECT('Formula References'!$B74),2,False)+$B29+if($D29 = ""Masterwork"", 1, $D29)-17,) ),)& if(M29 = ""Single Attack"", if(Vlookup(M29,INDIRECT('Formula References'!$B74),3,FALSE)>0, ""+""&VLOOKUP(N29,INDIRECT('Formula Reference"&"s'!$B74),2,False)+$B29+if($D29 = ""Masterwork"", 1, $D29)+$AC$74,) ,)& if(M29 = ""Natural Attacks (Searches attack name for # of attacks, defaults to 1)"", ""+""&VLOOKUP(N29,INDIRECT('Formula References'!$B74),2,False)"&"+$B29+if($D29 = ""Masterwork"", 1, $D29)+if(REGEXMATCH(N29,""Haste Applies""),$AC$74,)& if(AND(REGEXMATCH(N29,""Haste Applies""),$AI$74>0), "" / +"" & VLOOKUP(N29,INDIRECT('Formula References'!$B74),2,False)+$B29+if($D29 = ""Masterwork"", 1, $D29),)& "&" if(REGEXMATCH(E29,""[2-9]+""), "" / +""&VLOOKUP(N29,INDIRECT('Formula References'!$B74),2,False)+$B29+if($D29 = ""Masterwork"", 1, $D29),)& if(REGEXMATCH(E29,""[3-9]+""), "" / +""&VLOOKUP(N29,INDIRECT('Formula References'!$B74),2,False)+$B29+if($D29 "&"= ""Masterwork"", 1, $D29),)& if(REGEXMATCH(E29,""[4-9]+""), "" / +""&VLOOKUP(N29,INDIRECT('Formula References'!$B74),2,False)+$B29+if($D29 = ""Masterwork"", 1, $D29),)& if(REGEXMATCH(E29,""[5-9]+""), "" / +""&VLOOKUP(N29,INDIRECT('Formula Reference"&"s'!$B74),2,False)+$B29+if($D29 = ""Masterwork"", 1, $D29),)& if(REGEXMATCH(E29,""[6-9]+""), "" / +""&VLOOKUP(N29,INDIRECT('Formula References'!$B74),2,False)+$B29+if($D29 = ""Masterwork"", 1, $D29),) ,)& if( M29 = ""Other"", if( N29=""Alc"&"hemist Bomb (DEX to hit, INT to damage) (No Rapid Bomb Discovery)"", if(1+int(BaseAttack/5)>0, ""+""&VLOOKUP(N29,INDIRECT('Formula References'!$B74),2,False)+$B29+if($D29 = ""Masterwork"", 1, $D29),) ,)& if( N29=""Alchemist Bomb (DEX "&"to hit, INT to damage) (Rapid Bomb)"", if($AJ$74=1, ""+""&VLOOKUP(N29,INDIRECT('Formula References'!$B74),2,False)+$B29+if($D29 = ""Masterwork"", 1, $D29)& "" / "",) & if($AJ$74=2, ""+""&VLOOKUP(N29,INDIRECT('Formula References'!$B74),2,False)"&"+$B29+if($D29 = ""Masterwork"", 1, $D29)& "" / "",) & if(1+int(BaseAttack/5)>0, ""+""&VLOOKUP(N29,INDIRECT('Formula References'!$B74),2,False)+$B29+if($D29 = ""Masterwork"", 1, $D29),) & if(1+int(BaseAttack/5)>1, "" / +"" & VLOOKUP(N29,INDIREC"&"T('Formula References'!$B74),2,False)+$B29+if($D29 = ""Masterwork"", 1, $D29)-5,) & if(1+int(BaseAttack/5)>2, "" / +"" & VLOOKUP(N29,INDIRECT('Formula References'!$B74),2,False)+$B29+if($D29 = ""Masterwork"", 1, $D29)-10,) & if(1+int(BaseAttac"&"k/5)>3, "" / +"" & VLOOKUP(N29,INDIRECT('Formula References'!$B74),2,False)+$B29+if($D29 = ""Masterwork"", 1, $D29)-15,) ,)& if( N29=""Witch Prehensile Hair (INT to hit / INT to damage)"", if(1+int(BaseAttack/5)>0, ""+""&VLOOKUP(N29,I"&"NDIRECT('Formula References'!$B74),2,False)+$B29+if($D29 = ""Masterwork"", 1, $D29)+$AC$74,) ,)& if(REGEXMATCH(N29,""Kineticist""), if(REGEXMATCH(N29,""Ranged""), ""+""&VLOOKUP(N29,INDIRECT('Formula References'!$B74),2,False)+$B29+if($D29 ="&" ""Masterwork"", 1, $D29),)& if(AND(REGEXMATCH(N29,""Melee""),Vlookup(M29,INDIRECT('Formula References'!$B74),3,FALSE)>0), ""+""&VLOOKUP(N29,INDIRECT('Formula References'!$B74),2,False)+$B29+if($D29 = ""Masterwork"", 1, $D29)+$AC$74,)& if(A"&"ND(REGEXMATCH(N29,""Melee""),$AI$74>0), "" / +""&VLOOKUP(N29,INDIRECT('Formula References'!$B74),2,False)+$B29+if($D29 = ""Masterwork"", 1, $D29),)& if(AND(REGEXMATCH(N29,""Melee""),Vlookup(M29,INDIR"&"ECT('Formula References'!$B74),3,FALSE)>1), "" / +""&VLOOKUP(N29,INDIRECT('Formula References'!$B74),2,False)+$B29+if($D29 = ""Masterwork"", 1, $D29)-5,)& if(AND(REGEXMATCH(N29,""Melee""),Vlookup(M29,INDIRECT('Formula References'!$B74),3,FALSE)>2), "&""" / +""&VLOOKUP(N29,INDIRECT('Formula References'!$B74),2,False)+$B29+if($D29 = ""Masterwork"", 1, $D29)-10,)& if(AND(REGEXMATCH(N29,""Melee""),Vlookup(M29,INDIRECT('Formula References'!$B74),3,FALSE)>3), "" / +""&VLOOKUP(N29,INDIRECT('Formula Refe"&"rences'!$B74),2,False)+$B29+if($D29 = ""Masterwork"", 1, $D29)-15,) ,) ,) ,)"),"") | V29: {=iferror(if(istext(N29),U29 & " + " & vlookup(N29,INDIRECT('Formula References'!B74),3,False)+if(isnumber(D29),D29)+C29,),"")} | AD29: =IF(OR( iferror(vlookup($AE$2, 'Class Skills'!$A:$BE,MATCH(AE29,'Class Skills'!$1:$1,0),false),"")="X", iferror(vlookup($AE$3, 'Class Skills'!$A:$BE,MATCH(AE29,'Class Skills'!$1:$1,0),false),"")="X", iferror(vlookup($AE$4, 'Class Skills'!$A:$BE,MATCH(AE29,'Class Skills'!$1:$1,0),false),"")="X", iferror(vlookup(#REF!, 'Class Skills'!$A:$BE,MATCH(AE29,'Class Skills'!$1:$1,0),false),"")="X"),"X",) -> X | AE29: Stealth | AI29: =HLOOKUP(AE29,'Class Skills'!$1:$3,3,false) -> Dex | AJ29: =if(AND(HLOOKUP(AE29,'Class Skills'!$1:$2,2,false)="Trained Only",AL29<1),,SUM(AL29:AQ29)) -> 9 | AK29: = | AL29: 3 | AM29: =IFERROR(__xludf.DUMMYFUNCTION("offset($E$8,match(AI29,ARRAYFORMULA(Proper(lower(REGEXEXTRACT($E$9:$E$14,""\w\w\w"")))),0),2)"),3.0) -> 3 | AN29: =if(AND(AL29 > 0,AD29 ="X"), 3, ) -> 3 | AP29: =IFERROR(__xludf.DUMMYFUNCTION("if( or(arrayformula(regexmatch($AR$76:$AR$110,AE29))), sum(arrayformula(iferror(value(regexextract(filter( $AR$76:$AR$110, $K$76:$K$110=""ACTIVE"", regexmatch($AR$76:$AR$110,AE29)), ""[-\d]+"")))))+tSkill,tSkill)"),0.0) -> 0 | AQ29: =iferror(if( if(hlookup(AE29,'Class Skills'!$1:$4,4,false)="Armor Penalty",'Formula References'!$Q$156,) +if(AND(isnumber($C$38),AE29="Climb"),8,) +if(AND(isnumber($C$39),AE29="Swim"),8,) +if(AE29="Fly", Vlookup(Size,SizeTable,5,False),) +if(AE29="Fly",if($M$37="Clumsy",-8,if($M$37="Poor",-4,if($M$37="Average",0,if($M$37="Good",4,if($M$37="Perfect",8,0)))))) +if(AE29="Stealth",Vlookup(Size,SizeTable,6,False)) =0,, if(hlookup(AE29,'Class Skills'!$1:$4,4,false)="Armor Penalty",'Formula References'!$Q$156,) +if(AND(isnumber($C$38),AE29="Climb"),8,) +if(AND(isnumber($C$39),AE29="Swim"),8,) +if(AE29="Fly", Vlookup(Size,SizeTable,5,False),) +if(AE29="Fly",if($M$37="Clumsy",-8,if($M$37="Poor",-4,if($M$37="Average",0,if($M$37="Good",4,if($M$37="Perfect",8,0)))))) +if(AE29="Stealth",Vlookup(Size,SizeTable,6,False))),"")
O30: =IFERROR(__xludf.DUMMYFUNCTION("if(istext(N30), if(M30 = ""Melee Attack"",""+""& if(Vlookup(M30,INDIRECT('Formula References'!$B75),3,FALSE)>0, VLOOKUP(N30,INDIRECT('Formula References'!$B75),2,False)+$B30+if($D30 = ""Masterwork"", 1, $D30),)+$AC$74& "&" if($AI$74>0, "" / +"" & VLOOKUP(N30,INDIRECT('Formula References'!$B75),2,False)+$B30+if($D30 = ""Masterwork"", 1, $D30),)& if(Vlookup(M30,INDIRECT('Formula References'!$B75),3,FALSE)>1, "" / +"" & VLOOKUP(N30,INDIRECT('Formula Refe"&"rences'!$B75),2,False)+$B30+if($D30 = ""Masterwork"", 1, $D30)-5,) & if(Vlookup(M30,INDIRECT('Formula References'!$B75),3,FALSE)>2, "" / +"" & VLOOKUP(N30,INDIRECT('Formula References'!$B75),2,False)+$B30+if($D30 = ""Masterwork"", 1, $D30)-10,) & if"&"(Vlookup(M30,INDIRECT('Formula References'!$B75),3,FALSE)>3, "" / +"" & VLOOKUP(N30,INDIRECT('Formula References'!$B75),2,False)+$B30+if($D30 = ""Masterwork"", 1, $D30)-15,) ,)& if(M30 = ""Ranged Attack"", if($AJ$74>0, ""+""&VLOOKUP(N30,INDIRECT('Form"&"ula References'!$B75),2,False)+$B30+if($D30 = ""Masterwork"", 1, $D30)& "" / "",) & if($AJ$74>1, ""+""&VLOOKUP(N30,INDIRECT('Formula References'!$B75),2,False)+$B30+if($D30 = ""Masterwork"", 1, $D30)& "" / "",) & if(Vlookup(M30,INDIRECT('Formula Ref"&"erences'!$B75),3,FALSE)>0, ""+""&VLOOKUP(N30,INDIRECT('Formula References'!$B75),2,False)+$B30+if($D30 = ""Masterwork"", 1, $D30),) & if(Vlookup(M30,INDIRECT('Formula References'!$B75),3,FALSE)>1, "" / +"" & VLOOKUP(N30,INDIRECT('Formula References'!$B"&"75),2,False)+$B30+if($D30 = ""Masterwork"", 1, $D30)-5,) & if(Vlookup(M30,INDIRECT('Formula References'!$B75),3,FALSE)>2, "" / +"" & VLOOKUP(N30,INDIRECT('Formula References'!$B75),2,False)+$B30+if($D30 = ""Masterwork"", 1, $D30)-10,) & if(Vlookup(M"&"30,INDIRECT('Formula References'!$B75),3,FALSE)>3, "" / +"" & VLOOKUP(N30,INDIRECT('Formula References'!$B75),2,False)+$B30+if($D30 = ""Masterwork"", 1, $D30)-15,) ,)& if(M30 = ""Off-Hand Melee Attack (must have TWF 1, 2, or 3 active on Buff Table)"", "&" if(Vlookup(M30,INDIRECT('Formula References'!$B75),3,FALSE)>0, ""+""&VLOOKUP(N30,INDIRECT('Formula References'!$B75),2,False)+$B30+if($D30 = ""Masterwork"", 1, $D30),) & if(Vlookup(M30,INDIRECT('Formula References'!$B75),3,FALSE)>1, "" / +"" & VLOOKUP"&"(N30,INDIRECT('Formula References'!$B75),2,False)+$B30+if($D30 = ""Masterwork"", 1, $D30)-5,) & if(Vlookup(M30,INDIRECT('Formula References'!$B75),3,FALSE)>2, "" / +"" & VLOOKUP(N30,INDIRECT('Formula References'!$B75),2,False)+$B30+if($D30 = ""Masterwo"&"rk"", 1, $D30)-10,) & if(Vlookup(M30,INDIRECT('Formula References'!$B75),3,FALSE)>3, "" / +"" & VLOOKUP(N30,INDIRECT('Formula References'!$B75),2,False)+$B30+if($D30 = ""Masterwork"", 1, $D30)-15,) ,)& if(M30 = ""Off-Hand Ranged Attack (must have TWF "&"1, 2, or 3 active on Buff Table)"", if(Vlookup(M30,INDIRECT('Formula References'!$B75),3,FALSE)>0, ""+""&VLOOKUP(N30,INDIRECT('Formula References'!$B75),2,False)+$B30+if($D30 = ""Masterwork"", 1, $D30),) & if(Vlookup(M30,INDIRECT('Formula References"&"'!$B75),3,FALSE)>1, "" / +"" & VLOOKUP(N30,INDIRECT('Formula References'!$B75),2,False)+$B30+if($D30 = ""Masterwork"", 1, $D30)-5,) & if(Vlookup(M30,INDIRECT('Formula References'!$B75),3,FALSE)>2, "" / +"" & VLOOKUP(N30,INDIRECT('Formula References'!$B"&"75),2,False)+$B30+if($D30 = ""Masterwork"", 1, $D30)-10,) & if(Vlookup(M30,INDIRECT('Formula References'!$B75),3,FALSE)>3, "" / +"" & VLOOKUP(N30,INDIRECT('Formula References'!$B75),2,False)+$B30+if($D30 = ""Masterwork"", 1, $D30)-15,) ,)& if(M30 = """&"Combat Maneuver"", if(Vlookup(M30,INDIRECT('Formula References'!$B75),3,FALSE)>0, ""+""&VLOOKUP(N30,INDIRECT('Formula References'!$B75),2,False)+$B30+if($D30 = ""Masterwork"", 1, $D30)+$AC$74,) ,)& if(M30 = ""Magic"", if(Vlookup(M30,INDIRECT('Formu"&"la References'!$B75),3,FALSE)>0, ""+""&VLOOKUP(N30,INDIRECT('Formula References'!$B75),2,False)+$B30+if($D30 = ""Masterwork"", 1, $D30),) ,)& if(M30 = ""Monk Flurry"", if(OR(arrayformula(regexmatch($AE$2:$AE$4,""Monk \(Unchained\)""))), if(Vlookup"&"(M30,INDIRECT('Formula References'!$B75),3,FALSE)>0, ""+"" & VLOOKUP(N30,INDIRECT('Formula References'!$B75),2,False)+$B30+if($D30 = ""Masterwork"", 1, $D30)+$AC$74,)& if(AND($AJ$74>0,regexmatch(N30,""Ranged"")), "" / +"" & VLOOKUP(N30,I"&"NDIRECT('Formula References'!$B75),2,False)+$B30+if($D30 = ""Masterwork"", 1, $D30),)& if(AND($AJ$74>1,regexmatch(N30,""Ranged"")), "" / +"" & VLOOKUP(N30,INDIRECT('Formula References'!$B75),2,False)+$B30+if($D30 = ""Masterwork"", 1, $D3"&"0),)& if(AND($AJ$74>3,regexmatch(N30,""Ranged"")), "" / +"" & VLOOKUP(N30,INDIRECT('Formula References'!$B75),2,False)+$B30+if($D30 = ""Masterwork"", 1, $D30),)& if(AND($AI$74>0,regexmatch(N30,""Melee"")), "" / +"" & VL"&"OOKUP(N30,INDIRECT('Formula References'!$B75),2,False)+$B30+if($D30 = ""Masterwork"", 1, $D30),)& if(Vlookup(""Monk (Unchained)"",$AE$2:$AQ$4,13,false)>0 , "" / +"" & VLOOKUP(N30,INDIRECT('Formula References'!$B75),2,False)+$B30+if($D30 = ""Masterwor"&"k"", 1, $D30),) & if(Vlookup(""Monk (Unchained)"",$AE$2:$AQ$4,13,false)>10, "" / +"" & VLOOKUP(N30,INDIRECT('Formula References'!$B75),2,False)+$B30+if($D30 = ""Masterwork"", 1, $D30),) & if(Vlookup(M30,INDIRECT('Formula References'!$B75),3,FALS"&"E)>1, "" / +"" & VLOOKUP(N30,INDIRECT('Formula References'!$B75),2,False)+$B30+if($D30 = ""Masterwork"", 1, $D30)-5,) & if(Vlookup(M30,INDIRECT('Formula References'!$B75),3,FALSE)>2, "" / +"" & VLOOKUP(N30,INDIRECT('Formula References'!$B75),2,False)"&"+$B30+if($D30 = ""Masterwork"", 1, $D30)-10,) & if(Vlookup(M30,INDIRECT('Formula References'!$B75),3,FALSE)>3, "" / +"" & VLOOKUP(N30,INDIRECT('Formula References'!$B75),2,False)+$B30+if($D30 = ""Masterwork"", 1, $D30)-15,) , if(Vlookup(M30,"&"INDIRECT('Formula References'!$B75),3,FALSE)>0, ""+"" & VLOOKUP(N30,INDIRECT('Formula References'!$B75),2,False)+$B30+if($D30 = ""Masterwork"", 1, $D30)+$AC$74-2,)& if(AND($AJ$74>0,regexmatch(N30,""Ranged"")), "" / +"" & VLOOKUP(N30,INDI"&"RECT('Formula References'!$B75),2,False)+$B30+if($D30 = ""Masterwork"", 1, $D30)-2,)& if(AND($AJ$74>1,regexmatch(N30,""Ranged"")), "" / +"" & VLOOKUP(N30,INDIRECT('Formula References'!$B75),2,False)+$B30+if($D30 = ""Masterwork"", 1, $D30"&")-2,)& if(AND($AJ$74>3,regexmatch(N30,""Ranged"")), "" / +"" & VLOOKUP(N30,INDIRECT('Formula References'!$B75),2,False)+$B30+if($D30 = ""Masterwork"", 1, $D30)-2,)& if(AND($AI$74>0,regexmatch(N30,""Melee"")), "" / +"" &"&" VLOOKUP(N30,INDIRECT('Formula References'!$B75),2,False)+$B30+if($D30 = ""Masterwork"", 1, $D30)-2,)& if(Vlookup(""Monk"",$AE$2:$AQ$4,13,false)>0 , "" / +"" & VLOOKUP(N30,INDIRECT('Formula References'!$B75),2,False)+$B30+if($D30 = ""Masterwork"", 1,"&" $D30)-2,) & if(Vlookup(M30,INDIRECT('Formula References'!$B75),3,FALSE)>1, "" / +"" & VLOOKUP(N30,INDIRECT('Formula References'!$B75),2,False)+$B30+if($D30 = ""Masterwork"", 1, $D30)-7,) & if(Vlookup(""Monk"",$AE$2:$AQ$4,13,false)>5 , "" / +"" "&"& VLOOKUP(N30,INDIRECT('Formula References'!$B75),2,False)+$B30+if($D30 = ""Masterwork"", 1, $D30)-7,) & if(Vlookup(M30,INDIRECT('Formula References'!$B75),3,FALSE)>2, "" / +"" & VLOOKUP(N30,INDIRECT('Formula References'!$B75),2,False)+$B30+if($D30 ="&" ""Masterwork"", 1, $D30)-12,) & if(Vlookup(""Monk"",$AE$2:$AQ$4,13,false)>10 , "" / +"" & VLOOKUP(N30,INDIRECT('Formula References'!$B75),2,False)+$B30+if($D30 = ""Masterwork"", 1, $D30)-12,) & if(Vlookup(""Monk"",$AE$2:$AQ$4,13,false)>15 , "" "&"/ +"" & VLOOKUP(N30,INDIRECT('Formula References'!$B75),2,False)+$B30+if($D30 = ""Masterwork"", 1, $D30)-17,) ),)& if(M30 = ""Single Attack"", if(Vlookup(M30,INDIRECT('Formula References'!$B75),3,FALSE)>0, ""+""&VLOOKUP(N30,INDIRECT('Formula Reference"&"s'!$B75),2,False)+$B30+if($D30 = ""Masterwork"", 1, $D30)+$AC$74,) ,)& if(M30 = ""Natural Attacks (Searches attack name for # of attacks, defaults to 1)"", ""+""&VLOOKUP(N30,INDIRECT('Formula References'!$B75),2,False)"&"+$B30+if($D30 = ""Masterwork"", 1, $D30)+if(REGEXMATCH(N30,""Haste Applies""),$AC$74,)& if(AND(REGEXMATCH(N30,""Haste Applies""),$AI$74>0), "" / +"" & VLOOKUP(N30,INDIRECT('Formula References'!$B75),2,False)+$B30+if($D30 = ""Masterwork"", 1, $D30),)& "&" if(REGEXMATCH(E30,""[2-9]+""), "" / +""&VLOOKUP(N30,INDIRECT('Formula References'!$B75),2,False)+$B30+if($D30 = ""Masterwork"", 1, $D30),)& if(REGEXMATCH(E30,""[3-9]+""), "" / +""&VLOOKUP(N30,INDIRECT('Formula References'!$B75),2,False)+$B30+if($D30 "&"= ""Masterwork"", 1, $D30),)& if(REGEXMATCH(E30,""[4-9]+""), "" / +""&VLOOKUP(N30,INDIRECT('Formula References'!$B75),2,False)+$B30+if($D30 = ""Masterwork"", 1, $D30),)& if(REGEXMATCH(E30,""[5-9]+""), "" / +""&VLOOKUP(N30,INDIRECT('Formula Reference"&"s'!$B75),2,False)+$B30+if($D30 = ""Masterwork"", 1, $D30),)& if(REGEXMATCH(E30,""[6-9]+""), "" / +""&VLOOKUP(N30,INDIRECT('Formula References'!$B75),2,False)+$B30+if($D30 = ""Masterwork"", 1, $D30),) ,)& if( M30 = ""Other"", if( N30=""Alc"&"hemist Bomb (DEX to hit, INT to damage) (No Rapid Bomb Discovery)"", if(1+int(BaseAttack/5)>0, ""+""&VLOOKUP(N30,INDIRECT('Formula References'!$B75),2,False)+$B30+if($D30 = ""Masterwork"", 1, $D30),) ,)& if( N30=""Alchemist Bomb (DEX "&"to hit, INT to damage) (Rapid Bomb)"", if($AJ$74=1, ""+""&VLOOKUP(N30,INDIRECT('Formula References'!$B75),2,False)+$B30+if($D30 = ""Masterwork"", 1, $D30)& "" / "",) & if($AJ$74=2, ""+""&VLOOKUP(N30,INDIRECT('Formula References'!$B75),2,False)"&"+$B30+if($D30 = ""Masterwork"", 1, $D30)& "" / "",) & if(1+int(BaseAttack/5)>0, ""+""&VLOOKUP(N30,INDIRECT('Formula References'!$B75),2,False)+$B30+if($D30 = ""Masterwork"", 1, $D30),) & if(1+int(BaseAttack/5)>1, "" / +"" & VLOOKUP(N30,INDIREC"&"T('Formula References'!$B75),2,False)+$B30+if($D30 = ""Masterwork"", 1, $D30)-5,) & if(1+int(BaseAttack/5)>2, "" / +"" & VLOOKUP(N30,INDIRECT('Formula References'!$B75),2,False)+$B30+if($D30 = ""Masterwork"", 1, $D30)-10,) & if(1+int(BaseAttac"&"k/5)>3, "" / +"" & VLOOKUP(N30,INDIRECT('Formula References'!$B75),2,False)+$B30+if($D30 = ""Masterwork"", 1, $D30)-15,) ,)& if( N30=""Witch Prehensile Hair (INT to hit / INT to damage)"", if(1+int(BaseAttack/5)>0, ""+""&VLOOKUP(N30,I"&"NDIRECT('Formula References'!$B75),2,False)+$B30+if($D30 = ""Masterwork"", 1, $D30)+$AC$74,) ,)& if(REGEXMATCH(N30,""Kineticist""), if(REGEXMATCH(N30,""Ranged""), ""+""&VLOOKUP(N30,INDIRECT('Formula References'!$B75),2,False)+$B30+if($D30 ="&" ""Masterwork"", 1, $D30),)& if(AND(REGEXMATCH(N30,""Melee""),Vlookup(M30,INDIRECT('Formula References'!$B75),3,FALSE)>0), ""+""&VLOOKUP(N30,INDIRECT('Formula References'!$B75),2,False)+$B30+if($D30 = ""Masterwork"", 1, $D30)+$AC$74,)& if(A"&"ND(REGEXMATCH(N30,""Melee""),$AI$74>0), "" / +""&VLOOKUP(N30,INDIRECT('Formula References'!$B75),2,False)+$B30+if($D30 = ""Masterwork"", 1, $D30),)& if(AND(REGEXMATCH(N30,""Melee""),Vlookup(M30,INDIR"&"ECT('Formula References'!$B75),3,FALSE)>1), "" / +""&VLOOKUP(N30,INDIRECT('Formula References'!$B75),2,False)+$B30+if($D30 = ""Masterwork"", 1, $D30)-5,)& if(AND(REGEXMATCH(N30,""Melee""),Vlookup(M30,INDIRECT('Formula References'!$B75),3,FALSE)>2), "&""" / +""&VLOOKUP(N30,INDIRECT('Formula References'!$B75),2,False)+$B30+if($D30 = ""Masterwork"", 1, $D30)-10,)& if(AND(REGEXMATCH(N30,""Melee""),Vlookup(M30,INDIRECT('Formula References'!$B75),3,FALSE)>3), "" / +""&VLOOKUP(N30,INDIRECT('Formula Refe"&"rences'!$B75),2,False)+$B30+if($D30 = ""Masterwork"", 1, $D30)-15,) ,) ,) ,)"),"") | V30: {=iferror(if(istext(N30),U30 & " + " & vlookup(N30,INDIRECT('Formula References'!B75),3,False)+if(isnumber(D30),D30)+C30,),"")} | AD30: =IF(OR( iferror(vlookup($AE$2, 'Class Skills'!$A:$BE,MATCH(AE30,'Class Skills'!$1:$1,0),false),"")="X", iferror(vlookup($AE$3, 'Class Skills'!$A:$BE,MATCH(AE30,'Class Skills'!$1:$1,0),false),"")="X", iferror(vlookup($AE$4, 'Class Skills'!$A:$BE,MATCH(AE30,'Class Skills'!$1:$1,0),false),"")="X", iferror(vlookup(#REF!, 'Class Skills'!$A:$BE,MATCH(AE30,'Class Skills'!$1:$1,0),false),"")="X"),"X",) | AE30: Survival | AI30: =HLOOKUP(AE30,'Class Skills'!$1:$3,3,false) -> Wis | AJ30: =if(AND(HLOOKUP(AE30,'Class Skills'!$1:$2,2,false)="Trained Only",AL30<1),,SUM(AL30:AQ30)) -> 0 | AK30: = | AM30: =IFERROR(__xludf.DUMMYFUNCTION("offset($E$8,match(AI30,ARRAYFORMULA(Proper(lower(REGEXEXTRACT($E$9:$E$14,""\w\w\w"")))),0),2)"),0.0) -> 0 | AN30: =if(AND(AL30 > 0,AD30 ="X"), 3, ) | AP30: =IFERROR(__xludf.DUMMYFUNCTION("if( or(arrayformula(regexmatch($AR$76:$AR$110,AE30))), sum(arrayformula(iferror(value(regexextract(filter( $AR$76:$AR$110, $K$76:$K$110=""ACTIVE"", regexmatch($AR$76:$AR$110,AE30)), ""[-\d]+"")))))+tSkill,tSkill)"),0.0) -> 0 | AQ30: =iferror(if( if(hlookup(AE30,'Class Skills'!$1:$4,4,false)="Armor Penalty",'Formula References'!$Q$156,) +if(AND(isnumber($C$38),AE30="Climb"),8,) +if(AND(isnumber($C$39),AE30="Swim"),8,) +if(AE30="Fly", Vlookup(Size,SizeTable,5,False),) +if(AE30="Fly",if($M$37="Clumsy",-8,if($M$37="Poor",-4,if($M$37="Average",0,if($M$37="Good",4,if($M$37="Perfect",8,0)))))) +if(AE30="Stealth",Vlookup(Size,SizeTable,6,False)) =0,, if(hlookup(AE30,'Class Skills'!$1:$4,4,false)="Armor Penalty",'Formula References'!$Q$156,) +if(AND(isnumber($C$38),AE30="Climb"),8,) +if(AND(isnumber($C$39),AE30="Swim"),8,) +if(AE30="Fly", Vlookup(Size,SizeTable,5,False),) +if(AE30="Fly",if($M$37="Clumsy",-8,if($M$37="Poor",-4,if($M$37="Average",0,if($M$37="Good",4,if($M$37="Perfect",8,0)))))) +if(AE30="Stealth",Vlookup(Size,SizeTable,6,False))),"") | BD30: SOURCE
O31: =IFERROR(__xludf.DUMMYFUNCTION("if(istext(N31), if(M31 = ""Melee Attack"",""+""& if(Vlookup(M31,INDIRECT('Formula References'!$B76),3,FALSE)>0, VLOOKUP(N31,INDIRECT('Formula References'!$B76),2,False)+$B31+if($D31 = ""Masterwork"", 1, $D31),)+$AC$74& "&" if($AI$74>0, "" / +"" & VLOOKUP(N31,INDIRECT('Formula References'!$B76),2,False)+$B31+if($D31 = ""Masterwork"", 1, $D31),)& if(Vlookup(M31,INDIRECT('Formula References'!$B76),3,FALSE)>1, "" / +"" & VLOOKUP(N31,INDIRECT('Formula Refe"&"rences'!$B76),2,False)+$B31+if($D31 = ""Masterwork"", 1, $D31)-5,) & if(Vlookup(M31,INDIRECT('Formula References'!$B76),3,FALSE)>2, "" / +"" & VLOOKUP(N31,INDIRECT('Formula References'!$B76),2,False)+$B31+if($D31 = ""Masterwork"", 1, $D31)-10,) & if"&"(Vlookup(M31,INDIRECT('Formula References'!$B76),3,FALSE)>3, "" / +"" & VLOOKUP(N31,INDIRECT('Formula References'!$B76),2,False)+$B31+if($D31 = ""Masterwork"", 1, $D31)-15,) ,)& if(M31 = ""Ranged Attack"", if($AJ$74>0, ""+""&VLOOKUP(N31,INDIRECT('Form"&"ula References'!$B76),2,False)+$B31+if($D31 = ""Masterwork"", 1, $D31)& "" / "",) & if($AJ$74>1, ""+""&VLOOKUP(N31,INDIRECT('Formula References'!$B76),2,False)+$B31+if($D31 = ""Masterwork"", 1, $D31)& "" / "",) & if(Vlookup(M31,INDIRECT('Formula Ref"&"erences'!$B76),3,FALSE)>0, ""+""&VLOOKUP(N31,INDIRECT('Formula References'!$B76),2,False)+$B31+if($D31 = ""Masterwork"", 1, $D31),) & if(Vlookup(M31,INDIRECT('Formula References'!$B76),3,FALSE)>1, "" / +"" & VLOOKUP(N31,INDIRECT('Formula References'!$B"&"76),2,False)+$B31+if($D31 = ""Masterwork"", 1, $D31)-5,) & if(Vlookup(M31,INDIRECT('Formula References'!$B76),3,FALSE)>2, "" / +"" & VLOOKUP(N31,INDIRECT('Formula References'!$B76),2,False)+$B31+if($D31 = ""Masterwork"", 1, $D31)-10,) & if(Vlookup(M"&"31,INDIRECT('Formula References'!$B76),3,FALSE)>3, "" / +"" & VLOOKUP(N31,INDIRECT('Formula References'!$B76),2,False)+$B31+if($D31 = ""Masterwork"", 1, $D31)-15,) ,)& if(M31 = ""Off-Hand Melee Attack (must have TWF 1, 2, or 3 active on Buff Table)"", "&" if(Vlookup(M31,INDIRECT('Formula References'!$B76),3,FALSE)>0, ""+""&VLOOKUP(N31,INDIRECT('Formula References'!$B76),2,False)+$B31+if($D31 = ""Masterwork"", 1, $D31),) & if(Vlookup(M31,INDIRECT('Formula References'!$B76),3,FALSE)>1, "" / +"" & VLOOKUP"&"(N31,INDIRECT('Formula References'!$B76),2,False)+$B31+if($D31 = ""Masterwork"", 1, $D31)-5,) & if(Vlookup(M31,INDIRECT('Formula References'!$B76),3,FALSE)>2, "" / +"" & VLOOKUP(N31,INDIRECT('Formula References'!$B76),2,False)+$B31+if($D31 = ""Masterwo"&"rk"", 1, $D31)-10,) & if(Vlookup(M31,INDIRECT('Formula References'!$B76),3,FALSE)>3, "" / +"" & VLOOKUP(N31,INDIRECT('Formula References'!$B76),2,False)+$B31+if($D31 = ""Masterwork"", 1, $D31)-15,) ,)& if(M31 = ""Off-Hand Ranged Attack (must have TWF "&"1, 2, or 3 active on Buff Table)"", if(Vlookup(M31,INDIRECT('Formula References'!$B76),3,FALSE)>0, ""+""&VLOOKUP(N31,INDIRECT('Formula References'!$B76),2,False)+$B31+if($D31 = ""Masterwork"", 1, $D31),) & if(Vlookup(M31,INDIRECT('Formula References"&"'!$B76),3,FALSE)>1, "" / +"" & VLOOKUP(N31,INDIRECT('Formula References'!$B76),2,False)+$B31+if($D31 = ""Masterwork"", 1, $D31)-5,) & if(Vlookup(M31,INDIRECT('Formula References'!$B76),3,FALSE)>2, "" / +"" & VLOOKUP(N31,INDIRECT('Formula References'!$B"&"76),2,False)+$B31+if($D31 = ""Masterwork"", 1, $D31)-10,) & if(Vlookup(M31,INDIRECT('Formula References'!$B76),3,FALSE)>3, "" / +"" & VLOOKUP(N31,INDIRECT('Formula References'!$B76),2,False)+$B31+if($D31 = ""Masterwork"", 1, $D31)-15,) ,)& if(M31 = """&"Combat Maneuver"", if(Vlookup(M31,INDIRECT('Formula References'!$B76),3,FALSE)>0, ""+""&VLOOKUP(N31,INDIRECT('Formula References'!$B76),2,False)+$B31+if($D31 = ""Masterwork"", 1, $D31)+$AC$74,) ,)& if(M31 = ""Magic"", if(Vlookup(M31,INDIRECT('Formu"&"la References'!$B76),3,FALSE)>0, ""+""&VLOOKUP(N31,INDIRECT('Formula References'!$B76),2,False)+$B31+if($D31 = ""Masterwork"", 1, $D31),) ,)& if(M31 = ""Monk Flurry"", if(OR(arrayformula(regexmatch($AE$2:$AE$4,""Monk \(Unchained\)""))), if(Vlookup"&"(M31,INDIRECT('Formula References'!$B76),3,FALSE)>0, ""+"" & VLOOKUP(N31,INDIRECT('Formula References'!$B76),2,False)+$B31+if($D31 = ""Masterwork"", 1, $D31)+$AC$74,)& if(AND($AJ$74>0,regexmatch(N31,""Ranged"")), "" / +"" & VLOOKUP(N31,I"&"NDIRECT('Formula References'!$B76),2,False)+$B31+if($D31 = ""Masterwork"", 1, $D31),)& if(AND($AJ$74>1,regexmatch(N31,""Ranged"")), "" / +"" & VLOOKUP(N31,INDIRECT('Formula References'!$B76),2,False)+$B31+if($D31 = ""Masterwork"", 1, $D3"&"1),)& if(AND($AJ$74>3,regexmatch(N31,""Ranged"")), "" / +"" & VLOOKUP(N31,INDIRECT('Formula References'!$B76),2,False)+$B31+if($D31 = ""Masterwork"", 1, $D31),)& if(AND($AI$74>0,regexmatch(N31,""Melee"")), "" / +"" & VL"&"OOKUP(N31,INDIRECT('Formula References'!$B76),2,False)+$B31+if($D31 = ""Masterwork"", 1, $D31),)& if(Vlookup(""Monk (Unchained)"",$AE$2:$AQ$4,13,false)>0 , "" / +"" & VLOOKUP(N31,INDIRECT('Formula References'!$B76),2,False)+$B31+if($D31 = ""Masterwor"&"k"", 1, $D31),) & if(Vlookup(""Monk (Unchained)"",$AE$2:$AQ$4,13,false)>10, "" / +"" & VLOOKUP(N31,INDIRECT('Formula References'!$B76),2,False)+$B31+if($D31 = ""Masterwork"", 1, $D31),) & if(Vlookup(M31,INDIRECT('Formula References'!$B76),3,FALS"&"E)>1, "" / +"" & VLOOKUP(N31,INDIRECT('Formula References'!$B76),2,False)+$B31+if($D31 = ""Masterwork"", 1, $D31)-5,) & if(Vlookup(M31,INDIRECT('Formula References'!$B76),3,FALSE)>2, "" / +"" & VLOOKUP(N31,INDIRECT('Formula References'!$B76),2,False)"&"+$B31+if($D31 = ""Masterwork"", 1, $D31)-10,) & if(Vlookup(M31,INDIRECT('Formula References'!$B76),3,FALSE)>3, "" / +"" & VLOOKUP(N31,INDIRECT('Formula References'!$B76),2,False)+$B31+if($D31 = ""Masterwork"", 1, $D31)-15,) , if(Vlookup(M31,"&"INDIRECT('Formula References'!$B76),3,FALSE)>0, ""+"" & VLOOKUP(N31,INDIRECT('Formula References'!$B76),2,False)+$B31+if($D31 = ""Masterwork"", 1, $D31)+$AC$74-2,)& if(AND($AJ$74>0,regexmatch(N31,""Ranged"")), "" / +"" & VLOOKUP(N31,INDI"&"RECT('Formula References'!$B76),2,False)+$B31+if($D31 = ""Masterwork"", 1, $D31)-2,)& if(AND($AJ$74>1,regexmatch(N31,""Ranged"")), "" / +"" & VLOOKUP(N31,INDIRECT('Formula References'!$B76),2,False)+$B31+if($D31 = ""Masterwork"", 1, $D31"&")-2,)& if(AND($AJ$74>3,regexmatch(N31,""Ranged"")), "" / +"" & VLOOKUP(N31,INDIRECT('Formula References'!$B76),2,False)+$B31+if($D31 = ""Masterwork"", 1, $D31)-2,)& if(AND($AI$74>0,regexmatch(N31,""Melee"")), "" / +"" &"&" VLOOKUP(N31,INDIRECT('Formula References'!$B76),2,False)+$B31+if($D31 = ""Masterwork"", 1, $D31)-2,)& if(Vlookup(""Monk"",$AE$2:$AQ$4,13,false)>0 , "" / +"" & VLOOKUP(N31,INDIRECT('Formula References'!$B76),2,False)+$B31+if($D31 = ""Masterwork"", 1,"&" $D31)-2,) & if(Vlookup(M31,INDIRECT('Formula References'!$B76),3,FALSE)>1, "" / +"" & VLOOKUP(N31,INDIRECT('Formula References'!$B76),2,False)+$B31+if($D31 = ""Masterwork"", 1, $D31)-7,) & if(Vlookup(""Monk"",$AE$2:$AQ$4,13,false)>5 , "" / +"" "&"& VLOOKUP(N31,INDIRECT('Formula References'!$B76),2,False)+$B31+if($D31 = ""Masterwork"", 1, $D31)-7,) & if(Vlookup(M31,INDIRECT('Formula References'!$B76),3,FALSE)>2, "" / +"" & VLOOKUP(N31,INDIRECT('Formula References'!$B76),2,False)+$B31+if($D31 ="&" ""Masterwork"", 1, $D31)-12,) & if(Vlookup(""Monk"",$AE$2:$AQ$4,13,false)>10 , "" / +"" & VLOOKUP(N31,INDIRECT('Formula References'!$B76),2,False)+$B31+if($D31 = ""Masterwork"", 1, $D31)-12,) & if(Vlookup(""Monk"",$AE$2:$AQ$4,13,false)>15 , "" "&"/ +"" & VLOOKUP(N31,INDIRECT('Formula References'!$B76),2,False)+$B31+if($D31 = ""Masterwork"", 1, $D31)-17,) ),)& if(M31 = ""Single Attack"", if(Vlookup(M31,INDIRECT('Formula References'!$B76),3,FALSE)>0, ""+""&VLOOKUP(N31,INDIRECT('Formula Reference"&"s'!$B76),2,False)+$B31+if($D31 = ""Masterwork"", 1, $D31)+$AC$74,) ,)& if(M31 = ""Natural Attacks (Searches attack name for # of attacks, defaults to 1)"", ""+""&VLOOKUP(N31,INDIRECT('Formula References'!$B76),2,False)"&"+$B31+if($D31 = ""Masterwork"", 1, $D31)+if(REGEXMATCH(N31,""Haste Applies""),$AC$74,)& if(AND(REGEXMATCH(N31,""Haste Applies""),$AI$74>0), "" / +"" & VLOOKUP(N31,INDIRECT('Formula References'!$B76),2,False)+$B31+if($D31 = ""Masterwork"", 1, $D31),)& "&" if(REGEXMATCH(E31,""[2-9]+""), "" / +""&VLOOKUP(N31,INDIRECT('Formula References'!$B76),2,False)+$B31+if($D31 = ""Masterwork"", 1, $D31),)& if(REGEXMATCH(E31,""[3-9]+""), "" / +""&VLOOKUP(N31,INDIRECT('Formula References'!$B76),2,False)+$B31+if($D31 "&"= ""Masterwork"", 1, $D31),)& if(REGEXMATCH(E31,""[4-9]+""), "" / +""&VLOOKUP(N31,INDIRECT('Formula References'!$B76),2,False)+$B31+if($D31 = ""Masterwork"", 1, $D31),)& if(REGEXMATCH(E31,""[5-9]+""), "" / +""&VLOOKUP(N31,INDIRECT('Formula Reference"&"s'!$B76),2,False)+$B31+if($D31 = ""Masterwork"", 1, $D31),)& if(REGEXMATCH(E31,""[6-9]+""), "" / +""&VLOOKUP(N31,INDIRECT('Formula References'!$B76),2,False)+$B31+if($D31 = ""Masterwork"", 1, $D31),) ,)& if( M31 = ""Other"", if( N31=""Alc"&"hemist Bomb (DEX to hit, INT to damage) (No Rapid Bomb Discovery)"", if(1+int(BaseAttack/5)>0, ""+""&VLOOKUP(N31,INDIRECT('Formula References'!$B76),2,False)+$B31+if($D31 = ""Masterwork"", 1, $D31),) ,)& if( N31=""Alchemist Bomb (DEX "&"to hit, INT to damage) (Rapid Bomb)"", if($AJ$74=1, ""+""&VLOOKUP(N31,INDIRECT('Formula References'!$B76),2,False)+$B31+if($D31 = ""Masterwork"", 1, $D31)& "" / "",) & if($AJ$74=2, ""+""&VLOOKUP(N31,INDIRECT('Formula References'!$B76),2,False)"&"+$B31+if($D31 = ""Masterwork"", 1, $D31)& "" / "",) & if(1+int(BaseAttack/5)>0, ""+""&VLOOKUP(N31,INDIRECT('Formula References'!$B76),2,False)+$B31+if($D31 = ""Masterwork"", 1, $D31),) & if(1+int(BaseAttack/5)>1, "" / +"" & VLOOKUP(N31,INDIREC"&"T('Formula References'!$B76),2,False)+$B31+if($D31 = ""Masterwork"", 1, $D31)-5,) & if(1+int(BaseAttack/5)>2, "" / +"" & VLOOKUP(N31,INDIRECT('Formula References'!$B76),2,False)+$B31+if($D31 = ""Masterwork"", 1, $D31)-10,) & if(1+int(BaseAttac"&"k/5)>3, "" / +"" & VLOOKUP(N31,INDIRECT('Formula References'!$B76),2,False)+$B31+if($D31 = ""Masterwork"", 1, $D31)-15,) ,)& if( N31=""Witch Prehensile Hair (INT to hit / INT to damage)"", if(1+int(BaseAttack/5)>0, ""+""&VLOOKUP(N31,I"&"NDIRECT('Formula References'!$B76),2,False)+$B31+if($D31 = ""Masterwork"", 1, $D31)+$AC$74,) ,)& if(REGEXMATCH(N31,""Kineticist""), if(REGEXMATCH(N31,""Ranged""), ""+""&VLOOKUP(N31,INDIRECT('Formula References'!$B76),2,False)+$B31+if($D31 ="&" ""Masterwork"", 1, $D31),)& if(AND(REGEXMATCH(N31,""Melee""),Vlookup(M31,INDIRECT('Formula References'!$B76),3,FALSE)>0), ""+""&VLOOKUP(N31,INDIRECT('Formula References'!$B76),2,False)+$B31+if($D31 = ""Masterwork"", 1, $D31)+$AC$74,)& if(A"&"ND(REGEXMATCH(N31,""Melee""),$AI$74>0), "" / +""&VLOOKUP(N31,INDIRECT('Formula References'!$B76),2,False)+$B31+if($D31 = ""Masterwork"", 1, $D31),)& if(AND(REGEXMATCH(N31,""Melee""),Vlookup(M31,INDIR"&"ECT('Formula References'!$B76),3,FALSE)>1), "" / +""&VLOOKUP(N31,INDIRECT('Formula References'!$B76),2,False)+$B31+if($D31 = ""Masterwork"", 1, $D31)-5,)& if(AND(REGEXMATCH(N31,""Melee""),Vlookup(M31,INDIRECT('Formula References'!$B76),3,FALSE)>2), "&""" / +""&VLOOKUP(N31,INDIRECT('Formula References'!$B76),2,False)+$B31+if($D31 = ""Masterwork"", 1, $D31)-10,)& if(AND(REGEXMATCH(N31,""Melee""),Vlookup(M31,INDIRECT('Formula References'!$B76),3,FALSE)>3), "" / +""&VLOOKUP(N31,INDIRECT('Formula Refe"&"rences'!$B76),2,False)+$B31+if($D31 = ""Masterwork"", 1, $D31)-15,) ,) ,) ,)"),"") | V31: {=iferror(if(istext(N31),U31 & " + " & vlookup(N31,INDIRECT('Formula References'!B76),3,False)+if(isnumber(D31),D31)+C31,),"")} | AD31: =IF(OR( iferror(vlookup($AE$2, 'Class Skills'!$A:$BE,MATCH(AE31,'Class Skills'!$1:$1,0),false),"")="X", iferror(vlookup($AE$3, 'Class Skills'!$A:$BE,MATCH(AE31,'Class Skills'!$1:$1,0),false),"")="X", iferror(vlookup($AE$4, 'Class Skills'!$A:$BE,MATCH(AE31,'Class Skills'!$1:$1,0),false),"")="X", iferror(vlookup(#REF!, 'Class Skills'!$A:$BE,MATCH(AE31,'Class Skills'!$1:$1,0),false),"")="X"),"X",) -> X | AE31: Swim | AI31: =HLOOKUP(AE31,'Class Skills'!$1:$3,3,false) -> Str | AJ31: =if(AND(HLOOKUP(AE31,'Class Skills'!$1:$2,2,false)="Trained Only",AL31<1),,SUM(AL31:AQ31)) -> 6 | AK31: = | AL31: 3 | AM31: =IFERROR(__xludf.DUMMYFUNCTION("offset($E$8,match(AI31,ARRAYFORMULA(Proper(lower(REGEXEXTRACT($E$9:$E$14,""\w\w\w"")))),0),2)"),0.0) -> 0 | AN31: =if(AND(AL31 > 0,AD31 ="X"), 3, ) -> 3 | AP31: =IFERROR(__xludf.DUMMYFUNCTION("if( or(arrayformula(regexmatch($AR$76:$AR$110,AE31))), sum(arrayformula(iferror(value(regexextract(filter( $AR$76:$AR$110, $K$76:$K$110=""ACTIVE"", regexmatch($AR$76:$AR$110,AE31)), ""[-\d]+"")))))+tSkill,tSkill)"),0.0) -> 0 | AQ31: =iferror(if( if(hlookup(AE31,'Class Skills'!$1:$4,4,false)="Armor Penalty",'Formula References'!$Q$156,) +if(AND(isnumber($C$38),AE31="Climb"),8,) +if(AND(isnumber($C$39),AE31="Swim"),8,) +if(AE31="Fly", Vlookup(Size,SizeTable,5,False),) +if(AE31="Fly",if($M$37="Clumsy",-8,if($M$37="Poor",-4,if($M$37="Average",0,if($M$37="Good",4,if($M$37="Perfect",8,0)))))) +if(AE31="Stealth",Vlookup(Size,SizeTable,6,False)) =0,, if(hlookup(AE31,'Class Skills'!$1:$4,4,false)="Armor Penalty",'Formula References'!$Q$156,) +if(AND(isnumber($C$38),AE31="Climb"),8,) +if(AND(isnumber($C$39),AE31="Swim"),8,) +if(AE31="Fly", Vlookup(Size,SizeTable,5,False),) +if(AE31="Fly",if($M$37="Clumsy",-8,if($M$37="Poor",-4,if($M$37="Average",0,if($M$37="Good",4,if($M$37="Perfect",8,0)))))) +if(AE31="Stealth",Vlookup(Size,SizeTable,6,False))),"") | AS31: RESOURCES | BE31: MAGICAL ITEMS
J32: Attack Notes | U32: Combat Effect Quick Toggles - see Row 123 | AD32: =IF(OR( iferror(vlookup($AE$2, 'Class Skills'!$A:$BE,MATCH(AE32,'Class Skills'!$1:$1,0),false),"")="X", iferror(vlookup($AE$3, 'Class Skills'!$A:$BE,MATCH(AE32,'Class Skills'!$1:$1,0),false),"")="X", iferror(vlookup($AE$4, 'Class Skills'!$A:$BE,MATCH(AE32,'Class Skills'!$1:$1,0),false),"")="X", iferror(vlookup(#REF!, 'Class Skills'!$A:$BE,MATCH(AE32,'Class Skills'!$1:$1,0),false),"")="X"),"X",) | AE32: Use Magic Device | AI32: =HLOOKUP(AE32,'Class Skills'!$1:$3,3,false) -> Cha | AJ32: =if(AND(HLOOKUP(AE32,'Class Skills'!$1:$2,2,false)="Trained Only",AL32<1),,SUM(AL32:AQ32)) | AK32: = | AM32: =IFERROR(__xludf.DUMMYFUNCTION("offset($E$8,match(AI32,ARRAYFORMULA(Proper(lower(REGEXEXTRACT($E$9:$E$14,""\w\w\w"")))),0),2)"),0.0) -> 0 | AN32: =if(AND(AL32 > 0,AD32 ="X"), 3, ) | AP32: =IFERROR(__xludf.DUMMYFUNCTION("if( or(arrayformula(regexmatch($AR$76:$AR$110,AE32))), sum(arrayformula(iferror(value(regexextract(filter( $AR$76:$AR$110, $K$76:$K$110=""ACTIVE"", regexmatch($AR$76:$AR$110,AE32)), ""[-\d]+"")))))+tSkill,tSkill)"),0.0) -> 0 | AQ32: =iferror(if( if(hlookup(AE32,'Class Skills'!$1:$4,4,false)="Armor Penalty",'Formula References'!$Q$156,) +if(AND(isnumber($C$38),AE32="Climb"),8,) +if(AND(isnumber($C$39),AE32="Swim"),8,) +if(AE32="Fly", Vlookup(Size,SizeTable,5,False),) +if(AE32="Fly",if($M$37="Clumsy",-8,if($M$37="Poor",-4,if($M$37="Average",0,if($M$37="Good",4,if($M$37="Perfect",8,0)))))) +if(AE32="Stealth",Vlookup(Size,SizeTable,6,False)) =0,, if(hlookup(AE32,'Class Skills'!$1:$4,4,false)="Armor Penalty",'Formula References'!$Q$156,) +if(AND(isnumber($C$38),AE32="Climb"),8,) +if(AND(isnumber($C$39),AE32="Swim"),8,) +if(AE32="Fly", Vlookup(Size,SizeTable,5,False),) +if(AE32="Fly",if($M$37="Clumsy",-8,if($M$37="Poor",-4,if($M$37="Average",0,if($M$37="Good",4,if($M$37="Perfect",8,0)))))) +if(AE32="Stealth",Vlookup(Size,SizeTable,6,False))),"") | AS32: Uses | AT32: / Max | AU32: Resource, Item, or Ability | BE32: Slot | BG32: Item
U33: FALSE | V33: =B101 -> Power Attack | Y33: FALSE | Z33: =B106 -> Rapid Shot | AS33: 11 | AT33: 11 | AU33: Ki Pool | BE33: head
U34: FALSE | V34: =B102 -> Combat Expertise | Z34: =B107 -> (Custom Effect 7) | AD34: B. SKILLS | AH34: =MIN(2*$AQ$6,SUM($AL$35:$AL$45))&" / "&2*$AQ$6 -> 6 / 6 | AJ34: Total | AL34: Ranks | AM34: Ability | AN34: Class | AO34: Misc. | AP34: Temp. | AQ34: Armor | BE34: headband
U35: FALSE | V35: =B103 -> Deadly Aim | Z35: =B108 -> (Custom Effect 8) | AD35: =IF(OR( iferror(vlookup($AE$2, 'Class Skills'!$A:$BE,MATCH(AE35,'Class Skills'!$1:$1,0),false),"")="X", iferror(vlookup($AE$3, 'Class Skills'!$A:$BE,MATCH(AE35,'Class Skills'!$1:$1,0),false),"")="X", iferror(vlookup($AE$4, 'Class Skills'!$A:$BE,MATCH(AE35,'Class Skills'!$1:$1,0),false),"")="X", iferror(vlookup(#REF!, 'Class Skills'!$A:$BE,MATCH(AE35,'Class Skills'!$1:$1,0),false),"")="X"),"X",) -> X | AE35: Appraise | AI35: =HLOOKUP(AE35,'Class Skills'!$1:$3,3,false) -> Int | AJ35: =if(AND(HLOOKUP(AE35,'Class Skills'!$1:$2,2,false)="Trained Only",AL35<1),,SUM(AL35:AQ35)) -> 14 | AK35: = | AL35: 3 | AM35: =IFERROR(__xludf.DUMMYFUNCTION("offset($E$8,match(AI35,ARRAYFORMULA(Proper(lower(REGEXEXTRACT($E$9:$E$14,""\w\w\w"")))),0),2)"),8.0) -> 8 | AN35: =if(AND(AL35 > 0,AD35 ="X"), 3, ) -> 3 | AP35: =IFERROR(__xludf.DUMMYFUNCTION("if( or(arrayformula(regexmatch($AR$76:$AR$110,AE35))), sum(arrayformula(iferror(value(regexextract(filter( $AR$76:$AR$110, $K$76:$K$110=""ACTIVE"", regexmatch($AR$76:$AR$110,AE35)), ""[-\d]+"")))))+tSkill,tSkill)"),0.0) -> 0 | AQ35: =iferror(if( if(hlookup(AE35,'Class Skills'!$1:$4,4,false)="Armor Penalty",'Formula References'!$Q$156,) +if(AND(isnumber($C$38),AE35="Climb"),8,) +if(AND(isnumber($C$39),AE35="Swim"),8,) +if(AE35="Fly", Vlookup(Size,SizeTable,5,False),) +if(AE35="Fly",if($M$37="Clumsy",-8,if($M$37="Poor",-4,if($M$37="Average",0,if($M$37="Good",4,if($M$37="Perfect",8,0)))))) +if(AE35="Stealth",Vlookup(Size,SizeTable,6,False)) =0,, if(hlookup(AE35,'Class Skills'!$1:$4,4,false)="Armor Penalty",'Formula References'!$Q$156,) +if(AND(isnumber($C$38),AE35="Climb"),8,) +if(AND(isnumber($C$39),AE35="Swim"),8,) +if(AE35="Fly", Vlookup(Size,SizeTable,5,False),) +if(AE35="Fly",if($M$37="Clumsy",-8,if($M$37="Poor",-4,if($M$37="Average",0,if($M$37="Good",4,if($M$37="Perfect",8,0)))))) +if(AE35="Stealth",Vlookup(Size,SizeTable,6,False))),"") | BE35: face/eyes
B36: MOVEMENT | E36: Enter base values in the Effects Table | H36: Move | I36: Charge | J36: Run | L36: Ignore Armor? | O36: INITIATIVE | U36: FALSE | V36: =B104 -> Heroism | Y36: FALSE | Z36: =B109 -> (Custom Effect 9) | AD36: =IF(OR( iferror(vlookup($AE$2, 'Class Skills'!$A:$BE,MATCH(AE36,'Class Skills'!$1:$1,0),false),"")="X", iferror(vlookup($AE$3, 'Class Skills'!$A:$BE,MATCH(AE36,'Class Skills'!$1:$1,0),false),"")="X", iferror(vlookup($AE$4, 'Class Skills'!$A:$BE,MATCH(AE36,'Class Skills'!$1:$1,0),false),"")="X", iferror(vlookup(#REF!, 'Class Skills'!$A:$BE,MATCH(AE36,'Class Skills'!$1:$1,0),false),"")="X"),"X",) -> X | AE36: Handle Animal | AI36: =HLOOKUP(AE36,'Class Skills'!$1:$3,3,false) -> Cha | AJ36: =if(AND(HLOOKUP(AE36,'Class Skills'!$1:$2,2,false)="Trained Only",AL36<1),,SUM(AL36:AQ36)) | AK36: = | AM36: =IFERROR(__xludf.DUMMYFUNCTION("offset($E$8,match(AI36,ARRAYFORMULA(Proper(lower(REGEXEXTRACT($E$9:$E$14,""\w\w\w"")))),0),2)"),0.0) -> 0 | AN36: =if(AND(AL36 > 0,AD36 ="X"), 3, ) | AP36: =IFERROR(__xludf.DUMMYFUNCTION("if( or(arrayformula(regexmatch($AR$76:$AR$110,AE36))), sum(arrayformula(iferror(value(regexextract(filter( $AR$76:$AR$110, $K$76:$K$110=""ACTIVE"", regexmatch($AR$76:$AR$110,AE36)), ""[-\d]+"")))))+tSkill,tSkill)"),0.0) -> 0 | AQ36: =iferror(if( if(hlookup(AE36,'Class Skills'!$1:$4,4,false)="Armor Penalty",'Formula References'!$Q$156,) +if(AND(isnumber($C$38),AE36="Climb"),8,) +if(AND(isnumber($C$39),AE36="Swim"),8,) +if(AE36="Fly", Vlookup(Size,SizeTable,5,False),) +if(AE36="Fly",if($M$37="Clumsy",-8,if($M$37="Poor",-4,if($M$37="Average",0,if($M$37="Good",4,if($M$37="Perfect",8,0)))))) +if(AE36="Stealth",Vlookup(Size,SizeTable,6,False)) =0,, if(hlookup(AE36,'Class Skills'!$1:$4,4,false)="Armor Penalty",'Formula References'!$Q$156,) +if(AND(isnumber($C$38),AE36="Climb"),8,) +if(AND(isnumber($C$39),AE36="Swim"),8,) +if(AE36="Fly", Vlookup(Size,SizeTable,5,False),) +if(AE36="Fly",if($M$37="Clumsy",-8,if($M$37="Poor",-4,if($M$37="Average",0,if($M$37="Good",4,if($M$37="Perfect",8,0)))))) +if(AE36="Stealth",Vlookup(Size,SizeTable,6,False))),"") | BE36: throat
C37: Move | D37: Charge | E37: Run | G37: Base | H37: =IFERROR(__xludf.DUMMYFUNCTION("if(OR('Formula References'!$O$154=""Heavy"",'Formula References'!$O$154=""Medium""), if(REGEXMATCH($M$36,'Formula References'!$O$154),AL$74,ROUNDUP(AL$74*2/3/5)*5) ,AL$74)"),30.0) -> 30 | I37: =if(isnumber(H37),(H37+$M$39)*2,) -> 60 | J37: =if(isnumber(H37),IF(ISNUMBER($M$38),$M$38*(H37+$M$39), IF(NOT(OR('Formula References'!$O$154="Medium",'Formula References'!$O$154="Heavy")),4*(H37+$M$39),3*(H37+$M$39))),) -> 120 | L37: Flight Maneuverability | M37: average | O37: Total | Q37: DEX | R37: Misc. | S37: Temp. | V37: =B105 -> Haste | Z37: =B110 -> (Custom Effect 10) | AD37: =IF(OR( iferror(vlookup($AE$2, 'Class Skills'!$A:$BE,MATCH(AE37,'Class Skills'!$1:$1,0),false),"")="X", iferror(vlookup($AE$3, 'Class Skills'!$A:$BE,MATCH(AE37,'Class Skills'!$1:$1,0),false),"")="X", iferror(vlookup($AE$4, 'Class Skills'!$A:$BE,MATCH(AE37,'Class Skills'!$1:$1,0),false),"")="X", iferror(vlookup(#REF!, 'Class Skills'!$A:$BE,MATCH(AE37,'Class Skills'!$1:$1,0),false),"")="X"),"X",) | AE37: Kn. Engineering | AI37: =HLOOKUP(AE37,'Class Skills'!$1:$3,3,false) -> Int | AJ37: =if(AND(HLOOKUP(AE37,'Class Skills'!$1:$2,2,false)="Trained Only",AL37<1),,SUM(AL37:AQ37)) | AK37: = | AM37: =IFERROR(__xludf.DUMMYFUNCTION("offset($E$8,match(AI37,ARRAYFORMULA(Proper(lower(REGEXEXTRACT($E$9:$E$14,""\w\w\w"")))),0),2)"),8.0) -> 8 | AN37: =if(AND(AL37 > 0,AD37 ="X"), 3, ) | AP37: =IFERROR(__xludf.DUMMYFUNCTION("if( or(arrayformula(regexmatch($AR$76:$AR$110,AE37))), sum(arrayformula(iferror(value(regexextract(filter( $AR$76:$AR$110, $K$76:$K$110=""ACTIVE"", regexmatch($AR$76:$AR$110,AE37)), ""[-\d]+"")))))+tSkill,tSkill)"),0.0) -> 0 | AQ37: =iferror(if( if(hlookup(AE37,'Class Skills'!$1:$4,4,false)="Armor Penalty",'Formula References'!$Q$156,) +if(AND(isnumber($C$38),AE37="Climb"),8,) +if(AND(isnumber($C$39),AE37="Swim"),8,) +if(AE37="Fly", Vlookup(Size,SizeTable,5,False),) +if(AE37="Fly",if($M$37="Clumsy",-8,if($M$37="Poor",-4,if($M$37="Average",0,if($M$37="Good",4,if($M$37="Perfect",8,0)))))) +if(AE37="Stealth",Vlookup(Size,SizeTable,6,False)) =0,, if(hlookup(AE37,'Class Skills'!$1:$4,4,false)="Armor Penalty",'Formula References'!$Q$156,) +if(AND(isnumber($C$38),AE37="Climb"),8,) +if(AND(isnumber($C$39),AE37="Swim"),8,) +if(AE37="Fly", Vlookup(Size,SizeTable,5,False),) +if(AE37="Fly",if($M$37="Clumsy",-8,if($M$37="Poor",-4,if($M$37="Average",0,if($M$37="Good",4,if($M$37="Perfect",8,0)))))) +if(AE37="Stealth",Vlookup(Size,SizeTable,6,False))),"") | BE37: shoulders
B38: Climb | C38: =IFERROR(__xludf.DUMMYFUNCTION("if(isblank(AP74),,if(OR('Formula References'!$O$154=""Heavy"",'Formula References'!$O$154=""Medium""), if(REGEXMATCH($M$36,'Formula References'!$O$154),AP$74,ROUNDUP(AP$74*2/3/5)*5) ,AP$74))"),"") | D38: =if(isnumber(C38),(C38+$M$39)*2,) | E38: =if(isnumber(C38),IF(ISNUMBER($M$38),$M$38*(C38+$M$39), IF(NOT(OR('Formula References'!$O$154="Medium",'Formula References'!$O$154="Heavy")),4*(C38+$M$39),3*(C38+$M$39))),) | G38: Fly | H38: =IFERROR(__xludf.DUMMYFUNCTION("if(isblank(AM74),,if(OR('Formula References'!$O$154=""Heavy"",'Formula References'!$O$154=""Medium""), if(REGEXMATCH($M$36,'Formula References'!$O$154),AM$74,ROUNDUP(AM$74*2/3/5)*5) ,AM$74))"),"") | I38: =if(isnumber(H38),(H38+$M$39)*2,) | J38: =if(isnumber(H38),IF(ISNUMBER($M$38),$M$38*(H38+$M$39), IF(NOT(OR('Formula References'!$O$154="Medium",'Formula References'!$O$154="Heavy")),4*(H38+$M$39),3*(H38+$M$39))),) | L38: Run Multiplier | O38: =SUM(Q38:S38) -> 3 | P38: = | Q38: =Dexterity -> 3 | S38: =IFERROR(__xludf.DUMMYFUNCTION("if( or(arrayformula(regexmatch($AR$76:$AR$110,""Initiative""))), sum(arrayformula(iferror(value(regexextract(filter( $AR$76:$AR$110, $K$76:$K$110=""ACTIVE"", regexmatch($AR$76:$AR$110,""Initiative"")), ""[-\d]+""))))),)"),0.0) -> 0 | U38: FALSE | V38: Entangled | Z38: Dazzled | AD38: =IF(OR( iferror(vlookup($AE$2, 'Class Skills'!$A:$BE,MATCH(AE38,'Class Skills'!$1:$1,0),false),"")="X", iferror(vlookup($AE$3, 'Class Skills'!$A:$BE,MATCH(AE38,'Class Skills'!$1:$1,0),false),"")="X", iferror(vlookup($AE$4, 'Class Skills'!$A:$BE,MATCH(AE38,'Class Skills'!$1:$1,0),false),"")="X", iferror(vlookup(#REF!, 'Class Skills'!$A:$BE,MATCH(AE38,'Class Skills'!$1:$1,0),false),"")="X"),"X",) | AE38: Kn. Geography | AI38: =HLOOKUP(AE38,'Class Skills'!$1:$3,3,false) -> Int | AJ38: =if(AND(HLOOKUP(AE38,'Class Skills'!$1:$2,2,false)="Trained Only",AL38<1),,SUM(AL38:AQ38)) | AK38: = | AM38: =IFERROR(__xludf.DUMMYFUNCTION("offset($E$8,match(AI38,ARRAYFORMULA(Proper(lower(REGEXEXTRACT($E$9:$E$14,""\w\w\w"")))),0),2)"),8.0) -> 8 | AN38: =if(AND(AL38 > 0,AD38 ="X"), 3, ) | AP38: =IFERROR(__xludf.DUMMYFUNCTION("if( or(arrayformula(regexmatch($AR$76:$AR$110,AE38))), sum(arrayformula(iferror(value(regexextract(filter( $AR$76:$AR$110, $K$76:$K$110=""ACTIVE"", regexmatch($AR$76:$AR$110,AE38)), ""[-\d]+"")))))+tSkill,tSkill)"),0.0) -> 0 | AQ38: =iferror(if( if(hlookup(AE38,'Class Skills'!$1:$4,4,false)="Armor Penalty",'Formula References'!$Q$156,) +if(AND(isnumber($C$38),AE38="Climb"),8,) +if(AND(isnumber($C$39),AE38="Swim"),8,) +if(AE38="Fly", Vlookup(Size,SizeTable,5,False),) +if(AE38="Fly",if($M$37="Clumsy",-8,if($M$37="Poor",-4,if($M$37="Average",0,if($M$37="Good",4,if($M$37="Perfect",8,0)))))) +if(AE38="Stealth",Vlookup(Size,SizeTable,6,False)) =0,, if(hlookup(AE38,'Class Skills'!$1:$4,4,false)="Armor Penalty",'Formula References'!$Q$156,) +if(AND(isnumber($C$38),AE38="Climb"),8,) +if(AND(isnumber($C$39),AE38="Swim"),8,) +if(AE38="Fly", Vlookup(Size,SizeTable,5,False),) +if(AE38="Fly",if($M$37="Clumsy",-8,if($M$37="Poor",-4,if($M$37="Average",0,if($M$37="Good",4,if($M$37="Perfect",8,0)))))) +if(AE38="Stealth",Vlookup(Size,SizeTable,6,False))),"") | BE38: body
B39: Swim | C39: =IFERROR(__xludf.DUMMYFUNCTION("if(isblank(AN74),,if(OR('Formula References'!$O$154=""Heavy"",'Formula References'!$O$154=""Medium""), if(REGEXMATCH($M$36,'Formula References'!$O$154),AN$74,ROUNDUP(AN$74*2/3/5)*5) ,AN$74))"),"") | D39: =if(isnumber(C39),(C39+$M$39)*2,) | E39: =if(isnumber(C39),IF(ISNUMBER($M$38),$M$38*(C39+$M$39), IF(NOT(OR('Formula References'!$O$154="Medium",'Formula References'!$O$154="Heavy")),4*(C39+$M$39),3*(C39+$M$39))),) | G39: Burrow | H39: =IFERROR(__xludf.DUMMYFUNCTION("if(isblank(AO74),,if(OR('Formula References'!$O$154=""Heavy"",'Formula References'!$O$154=""Medium""), if(REGEXMATCH($M$36,'Formula References'!$O$154),AO$74,ROUNDUP(AO$74*2/3/5)*5) ,AO$74))"),"") | I39: =if(isnumber(H39),(H39+$M$39)*2,) | J39: =if(isnumber(H39),IF(ISNUMBER($M$38),$M$38*(H39+$M$39), IF(NOT(OR('Formula References'!$O$154="Medium",'Formula References'!$O$154="Heavy")),4*(H39+$M$39),3*(H39+$M$39))),) | L39: Charge Bonus Distance | V39: Blinded | Z39: Negative Levels | AD39: =IF(OR( iferror(vlookup($AE$2, 'Class Skills'!$A:$BE,MATCH(AE39,'Class Skills'!$1:$1,0),false),"")="X", iferror(vlookup($AE$3, 'Class Skills'!$A:$BE,MATCH(AE39,'Class Skills'!$1:$1,0),false),"")="X", iferror(vlookup($AE$4, 'Class Skills'!$A:$BE,MATCH(AE39,'Class Skills'!$1:$1,0),false),"")="X", iferror(vlookup(#REF!, 'Class Skills'!$A:$BE,MATCH(AE39,'Class Skills'!$1:$1,0),false),"")="X"),"X",) | AE39: Kn. History | AI39: =HLOOKUP(AE39,'Class Skills'!$1:$3,3,false) -> Int | AJ39: =if(AND(HLOOKUP(AE39,'Class Skills'!$1:$2,2,false)="Trained Only",AL39<1),,SUM(AL39:AQ39)) | AK39: = | AM39: =IFERROR(__xludf.DUMMYFUNCTION("offset($E$8,match(AI39,ARRAYFORMULA(Proper(lower(REGEXEXTRACT($E$9:$E$14,""\w\w\w"")))),0),2)"),8.0) -> 8 | AN39: =if(AND(AL39 > 0,AD39 ="X"), 3, ) | AP39: =IFERROR(__xludf.DUMMYFUNCTION("if( or(arrayformula(regexmatch($AR$76:$AR$110,AE39))), sum(arrayformula(iferror(value(regexextract(filter( $AR$76:$AR$110, $K$76:$K$110=""ACTIVE"", regexmatch($AR$76:$AR$110,AE39)), ""[-\d]+"")))))+tSkill,tSkill)"),0.0) -> 0 | AQ39: =iferror(if( if(hlookup(AE39,'Class Skills'!$1:$4,4,false)="Armor Penalty",'Formula References'!$Q$156,) +if(AND(isnumber($C$38),AE39="Climb"),8,) +if(AND(isnumber($C$39),AE39="Swim"),8,) +if(AE39="Fly", Vlookup(Size,SizeTable,5,False),) +if(AE39="Fly",if($M$37="Clumsy",-8,if($M$37="Poor",-4,if($M$37="Average",0,if($M$37="Good",4,if($M$37="Perfect",8,0)))))) +if(AE39="Stealth",Vlookup(Size,SizeTable,6,False)) =0,, if(hlookup(AE39,'Class Skills'!$1:$4,4,false)="Armor Penalty",'Formula References'!$Q$156,) +if(AND(isnumber($C$38),AE39="Climb"),8,) +if(AND(isnumber($C$39),AE39="Swim"),8,) +if(AE39="Fly", Vlookup(Size,SizeTable,5,False),) +if(AE39="Fly",if($M$37="Clumsy",-8,if($M$37="Poor",-4,if($M$37="Average",0,if($M$37="Good",4,if($M$37="Perfect",8,0)))))) +if(AE39="Stealth",Vlookup(Size,SizeTable,6,False))),"") | BE39: torso
AD40: =IF(OR( iferror(vlookup($AE$2, 'Class Skills'!$A:$BE,MATCH(AE40,'Class Skills'!$1:$1,0),false),"")="X", iferror(vlookup($AE$3, 'Class Skills'!$A:$BE,MATCH(AE40,'Class Skills'!$1:$1,0),false),"")="X", iferror(vlookup($AE$4, 'Class Skills'!$A:$BE,MATCH(AE40,'Class Skills'!$1:$1,0),false),"")="X", iferror(vlookup(#REF!, 'Class Skills'!$A:$BE,MATCH(AE40,'Class Skills'!$1:$1,0),false),"")="X"),"X",) | AE40: Kn. Nobility | AI40: =HLOOKUP(AE40,'Class Skills'!$1:$3,3,false) -> Int | AJ40: =if(AND(HLOOKUP(AE40,'Class Skills'!$1:$2,2,false)="Trained Only",AL40<1),,SUM(AL40:AQ40)) | AK40: = | AM40: =IFERROR(__xludf.DUMMYFUNCTION("offset($E$8,match(AI40,ARRAYFORMULA(Proper(lower(REGEXEXTRACT($E$9:$E$14,""\w\w\w"")))),0),2)"),8.0) -> 8 | AN40: =if(AND(AL40 > 0,AD40 ="X"), 3, ) | AP40: =IFERROR(__xludf.DUMMYFUNCTION("if( or(arrayformula(regexmatch($AR$76:$AR$110,AE40))), sum(arrayformula(iferror(value(regexextract(filter( $AR$76:$AR$110, $K$76:$K$110=""ACTIVE"", regexmatch($AR$76:$AR$110,AE40)), ""[-\d]+"")))))+tSkill,tSkill)"),0.0) -> 0 | AQ40: =iferror(if( if(hlookup(AE40,'Class Skills'!$1:$4,4,false)="Armor Penalty",'Formula References'!$Q$156,) +if(AND(isnumber($C$38),AE40="Climb"),8,) +if(AND(isnumber($C$39),AE40="Swim"),8,) +if(AE40="Fly", Vlookup(Size,SizeTable,5,False),) +if(AE40="Fly",if($M$37="Clumsy",-8,if($M$37="Poor",-4,if($M$37="Average",0,if($M$37="Good",4,if($M$37="Perfect",8,0)))))) +if(AE40="Stealth",Vlookup(Size,SizeTable,6,False)) =0,, if(hlookup(AE40,'Class Skills'!$1:$4,4,false)="Armor Penalty",'Formula References'!$Q$156,) +if(AND(isnumber($C$38),AE40="Climb"),8,) +if(AND(isnumber($C$39),AE40="Swim"),8,) +if(AE40="Fly", Vlookup(Size,SizeTable,5,False),) +if(AE40="Fly",if($M$37="Clumsy",-8,if($M$37="Poor",-4,if($M$37="Average",0,if($M$37="Good",4,if($M$37="Perfect",8,0)))))) +if(AE40="Stealth",Vlookup(Size,SizeTable,6,False))),"") | BE40: arms
B41: mSkill | C41: mDex | D41: Enh. | E41: ARMOR AND PROTECTIVES | M41: Item | N41: Material | O41: AC | P41: Skills | Q41: MaxDex | R41: Spells | S41: =iferror(IF(OR((HLOOKUP(#REF!,'Class Skills'!$3:$4,2,false)="Trained Only"),#REF!="T (Trained Only)"),"*",),"") | T41: Magical Item or Feature | X41: Target | Z41: Type | AB41: Value | AD41: =IF(OR( iferror(vlookup($AE$2, 'Class Skills'!$A:$BE,MATCH(AE41,'Class Skills'!$1:$1,0),false),"")="X", iferror(vlookup($AE$3, 'Class Skills'!$A:$BE,MATCH(AE41,'Class Skills'!$1:$1,0),false),"")="X", iferror(vlookup($AE$4, 'Class Skills'!$A:$BE,MATCH(AE41,'Class Skills'!$1:$1,0),false),"")="X", iferror(vlookup(#REF!, 'Class Skills'!$A:$BE,MATCH(AE41,'Class Skills'!$1:$1,0),false),"")="X"),"X",) -> X | AE41: Linguistics | AI41: =HLOOKUP(AE41,'Class Skills'!$1:$3,3,false) -> Int | AJ41: =if(AND(HLOOKUP(AE41,'Class Skills'!$1:$2,2,false)="Trained Only",AL41<1),,SUM(AL41:AQ41)) -> 22 | AK41: = | AL41: 3 | AM41: =IFERROR(__xludf.DUMMYFUNCTION("offset($E$8,match(AI41,ARRAYFORMULA(Proper(lower(REGEXEXTRACT($E$9:$E$14,""\w\w\w"")))),0),2)"),8.0) -> 8 | AN41: =if(AND(AL41 > 0,AD41 ="X"), 3, ) -> 3 | AO41: 8 | AP41: =IFERROR(__xludf.DUMMYFUNCTION("if( or(arrayformula(regexmatch($AR$76:$AR$110,AE41))), sum(arrayformula(iferror(value(regexextract(filter( $AR$76:$AR$110, $K$76:$K$110=""ACTIVE"", regexmatch($AR$76:$AR$110,AE41)), ""[-\d]+"")))))+tSkill,tSkill)"),0.0) -> 0 | AQ41: =iferror(if( if(hlookup(AE41,'Class Skills'!$1:$4,4,false)="Armor Penalty",'Formula References'!$Q$156,) +if(AND(isnumber($C$38),AE41="Climb"),8,) +if(AND(isnumber($C$39),AE41="Swim"),8,) +if(AE41="Fly", Vlookup(Size,SizeTable,5,False),) +if(AE41="Fly",if($M$37="Clumsy",-8,if($M$37="Poor",-4,if($M$37="Average",0,if($M$37="Good",4,if($M$37="Perfect",8,0)))))) +if(AE41="Stealth",Vlookup(Size,SizeTable,6,False)) =0,, if(hlookup(AE41,'Class Skills'!$1:$4,4,false)="Armor Penalty",'Formula References'!$Q$156,) +if(AND(isnumber($C$38),AE41="Climb"),8,) +if(AND(isnumber($C$39),AE41="Swim"),8,) +if(AE41="Fly", Vlookup(Size,SizeTable,5,False),) +if(AE41="Fly",if($M$37="Clumsy",-8,if($M$37="Poor",-4,if($M$37="Average",0,if($M$37="Good",4,if($M$37="Perfect",8,0)))))) +if(AE41="Stealth",Vlookup(Size,SizeTable,6,False))),"") | BE41: hands
O42: =if(isnumber($D$42),$D$42,)+iferror(VLOOKUP($M$42,'Formula References'!$A$150:$H$206,2,false),"")+IFERROR(VLOOKUP($N$42,'Formula References'!$A$209:$H$232,2,false),"") -> 0 | P42: =MIN(0,-1*iferror(VLOOKUP($M$42,'Formula References'!$A$150:$H$206,4,false),"")+IFERROR(VLOOKUP($N$42,'Formula References'!$A$209:$H$232,4,false),"")+B42+if(OR(D42>0,D42="Mwk"),1,)) -> 0 | Q42: =if( iferror(OR(isblank($M$42),isblank(VLOOKUP($M$42,'Formula References'!$A$150:$H$206,3,false))),""),, iferror(VLOOKUP($M$42,'Formula References'!$A$150:$H$206,3,false),"")+IFERROR(VLOOKUP($N$42,'Formula References'!$A$209:$H$232,3,false),"")+C42) | R42: =MAX(0,iferror(VLOOKUP($M$42,'Formula References'!$A$150:$H$206,5,false),"")+IFERROR(VLOOKUP($N$42,'Formula References'!$A$209:$H$232,5,false),"")) -> 0 | S42: =iferror(IF(OR((HLOOKUP(T42,'Class Skills'!$3:$4,2,false)="Trained Only"),#REF!="T (Trained Only)"),"*",),"") | AD42: =IF(OR( iferror(vlookup($AE$2, 'Class Skills'!$A:$BE,MATCH(AE42,'Class Skills'!$1:$1,0),false),"")="X", iferror(vlookup($AE$3, 'Class Skills'!$A:$BE,MATCH(AE42,'Class Skills'!$1:$1,0),false),"")="X", iferror(vlookup($AE$4, 'Class Skills'!$A:$BE,MATCH(AE42,'Class Skills'!$1:$1,0),false),"")="X", iferror(vlookup(#REF!, 'Class Skills'!$A:$BE,MATCH(AE42,'Class Skills'!$1:$1,0),false),"")="X"),"X",) | AE42: Sleight of Hand | AI42: =HLOOKUP(AE42,'Class Skills'!$1:$3,3,false) -> Dex | AJ42: =if(AND(HLOOKUP(AE42,'Class Skills'!$1:$2,2,false)="Trained Only",AL42<1),,SUM(AL42:AQ42)) | AK42: = | AM42: =IFERROR(__xludf.DUMMYFUNCTION("offset($E$8,match(AI42,ARRAYFORMULA(Proper(lower(REGEXEXTRACT($E$9:$E$14,""\w\w\w"")))),0),2)"),3.0) -> 3 | AN42: =if(AND(AL42 > 0,AD42 ="X"), 3, ) | AP42: =IFERROR(__xludf.DUMMYFUNCTION("if( or(arrayformula(regexmatch($AR$76:$AR$110,AE42))), sum(arrayformula(iferror(value(regexextract(filter( $AR$76:$AR$110, $K$76:$K$110=""ACTIVE"", regexmatch($AR$76:$AR$110,AE42)), ""[-\d]+"")))))+tSkill,tSkill)"),0.0) -> 0 | AQ42: =iferror(if( if(hlookup(AE42,'Class Skills'!$1:$4,4,false)="Armor Penalty",'Formula References'!$Q$156,) +if(AND(isnumber($C$38),AE42="Climb"),8,) +if(AND(isnumber($C$39),AE42="Swim"),8,) +if(AE42="Fly", Vlookup(Size,SizeTable,5,False),) +if(AE42="Fly",if($M$37="Clumsy",-8,if($M$37="Poor",-4,if($M$37="Average",0,if($M$37="Good",4,if($M$37="Perfect",8,0)))))) +if(AE42="Stealth",Vlookup(Size,SizeTable,6,False)) =0,, if(hlookup(AE42,'Class Skills'!$1:$4,4,false)="Armor Penalty",'Formula References'!$Q$156,) +if(AND(isnumber($C$38),AE42="Climb"),8,) +if(AND(isnumber($C$39),AE42="Swim"),8,) +if(AE42="Fly", Vlookup(Size,SizeTable,5,False),) +if(AE42="Fly",if($M$37="Clumsy",-8,if($M$37="Poor",-4,if($M$37="Average",0,if($M$37="Good",4,if($M$37="Perfect",8,0)))))) +if(AE42="Stealth",Vlookup(Size,SizeTable,6,False))),"") | BE42: waist
O43: =if(isnumber($D$43),$D$43,)+iferror(VLOOKUP($M$43,'Formula References'!$A$150:$H$206,2,false),"")+IFERROR(VLOOKUP($N$43,'Formula References'!$A$209:$H$232,2,false),"") -> 0 | P43: =MIN(0,-1*iferror(VLOOKUP($M$43,'Formula References'!$A$150:$H$206,4,false),"")+IFERROR(VLOOKUP($N$43,'Formula References'!$A$209:$H$232,4,false),"")+B43+if(OR(D43>0,D43="Mwk"),1,)) -> 0 | Q43: =if( iferror(OR(isblank($M$43),isblank(VLOOKUP($M$43,'Formula References'!$A$150:$H$206,3,false))),""),, iferror(VLOOKUP($M$43,'Formula References'!$A$150:$H$206,3,false),"")+IFERROR(VLOOKUP($N$43,'Formula References'!$A$209:$H$232,3,false),"")+C43) | R43: =MAX(0,iferror(VLOOKUP($M$43,'Formula References'!$A$150:$H$206,5,false),"")+IFERROR(VLOOKUP($N$43,'Formula References'!$A$209:$H$232,5,false),"")) -> 0 | S43: =iferror(IF(OR((HLOOKUP(T43,'Class Skills'!$3:$4,2,false)="Trained Only"),#REF!="T (Trained Only)"),"*",),"") | AD43: =IF(OR( iferror(vlookup($AE$2, 'Class Skills'!$A:$BE,MATCH(AE43,'Class Skills'!$1:$1,0),false),"")="X", iferror(vlookup($AE$3, 'Class Skills'!$A:$BE,MATCH(AE43,'Class Skills'!$1:$1,0),false),"")="X", iferror(vlookup($AE$4, 'Class Skills'!$A:$BE,MATCH(AE43,'Class Skills'!$1:$1,0),false),"")="X", iferror(vlookup(#REF!, 'Class Skills'!$A:$BE,MATCH(AE43,'Class Skills'!$1:$1,0),false),"")="X"),"X",) -> X | AE43: Perform: | AI43: =HLOOKUP(AE43,'Class Skills'!$1:$3,3,false) -> Cha | AJ43: =if(AND(HLOOKUP(AE43,'Class Skills'!$1:$2,2,false)="Trained Only",AL43<1),,SUM(AL43:AQ43)) -> 0 | AK43: = | AM43: =IFERROR(__xludf.DUMMYFUNCTION("offset($E$8,match(AI43,ARRAYFORMULA(Proper(lower(REGEXEXTRACT($E$9:$E$14,""\w\w\w"")))),0),2)"),0.0) -> 0 | AN43: =if(AND(AL43 > 0,AD43 ="X"), 3, ) | AP43: =IFERROR(__xludf.DUMMYFUNCTION("if( or(arrayformula(regexmatch($AR$76:$AR$110,AE43))), sum(arrayformula(iferror(value(regexextract(filter( $AR$76:$AR$110, $K$76:$K$110=""ACTIVE"", regexmatch($AR$76:$AR$110,AE43)), ""[-\d]+"")))))+tSkill,tSkill)"),0.0) -> 0 | AQ43: =iferror(if( if(hlookup(AE43,'Class Skills'!$1:$4,4,false)="Armor Penalty",'Formula References'!$Q$156,) +if(AND(isnumber($C$38),AE43="Climb"),8,) +if(AND(isnumber($C$39),AE43="Swim"),8,) +if(AE43="Fly", Vlookup(Size,SizeTable,5,False),) +if(AE43="Fly",if($M$37="Clumsy",-8,if($M$37="Poor",-4,if($M$37="Average",0,if($M$37="Good",4,if($M$37="Perfect",8,0)))))) +if(AE43="Stealth",Vlookup(Size,SizeTable,6,False)) =0,, if(hlookup(AE43,'Class Skills'!$1:$4,4,false)="Armor Penalty",'Formula References'!$Q$156,) +if(AND(isnumber($C$38),AE43="Climb"),8,) +if(AND(isnumber($C$39),AE43="Swim"),8,) +if(AE43="Fly", Vlookup(Size,SizeTable,5,False),) +if(AE43="Fly",if($M$37="Clumsy",-8,if($M$37="Poor",-4,if($M$37="Average",0,if($M$37="Good",4,if($M$37="Perfect",8,0)))))) +if(AE43="Stealth",Vlookup(Size,SizeTable,6,False))),"") | BE43: feet
H44: Armor Notes | AD44: =IF(OR( iferror(vlookup($AE$2, 'Class Skills'!$A:$BE,MATCH(AE44,'Class Skills'!$1:$1,0),false),"")="X", iferror(vlookup($AE$3, 'Class Skills'!$A:$BE,MATCH(AE44,'Class Skills'!$1:$1,0),false),"")="X", iferror(vlookup($AE$4, 'Class Skills'!$A:$BE,MATCH(AE44,'Class Skills'!$1:$1,0),false),"")="X", iferror(vlookup(#REF!, 'Class Skills'!$A:$BE,MATCH(AE44,'Class Skills'!$1:$1,0),false),"")="X"),"X",) -> X | AE44: Perform: | AI44: =HLOOKUP(AE44,'Class Skills'!$1:$3,3,false) -> Cha | AJ44: =if(AND(HLOOKUP(AE44,'Class Skills'!$1:$2,2,false)="Trained Only",AL44<1),,SUM(AL44:AQ44)) -> 0 | AK44: = | AM44: =IFERROR(__xludf.DUMMYFUNCTION("offset($E$8,match(AI44,ARRAYFORMULA(Proper(lower(REGEXEXTRACT($E$9:$E$14,""\w\w\w"")))),0),2)"),0.0) -> 0 | AN44: =if(AND(AL44 > 0,AD44 ="X"), 3, ) | AP44: =IFERROR(__xludf.DUMMYFUNCTION("if( or(arrayformula(regexmatch($AR$76:$AR$110,AE44))), sum(arrayformula(iferror(value(regexextract(filter( $AR$76:$AR$110, $K$76:$K$110=""ACTIVE"", regexmatch($AR$76:$AR$110,AE44)), ""[-\d]+"")))))+tSkill,tSkill)"),0.0) -> 0 | AQ44: =iferror(if( if(hlookup(AE44,'Class Skills'!$1:$4,4,false)="Armor Penalty",'Formula References'!$Q$156,) +if(AND(isnumber($C$38),AE44="Climb"),8,) +if(AND(isnumber($C$39),AE44="Swim"),8,) +if(AE44="Fly", Vlookup(Size,SizeTable,5,False),) +if(AE44="Fly",if($M$37="Clumsy",-8,if($M$37="Poor",-4,if($M$37="Average",0,if($M$37="Good",4,if($M$37="Perfect",8,0)))))) +if(AE44="Stealth",Vlookup(Size,SizeTable,6,False)) =0,, if(hlookup(AE44,'Class Skills'!$1:$4,4,false)="Armor Penalty",'Formula References'!$Q$156,) +if(AND(isnumber($C$38),AE44="Climb"),8,) +if(AND(isnumber($C$39),AE44="Swim"),8,) +if(AE44="Fly", Vlookup(Size,SizeTable,5,False),) +if(AE44="Fly",if($M$37="Clumsy",-8,if($M$37="Poor",-4,if($M$37="Average",0,if($M$37="Good",4,if($M$37="Perfect",8,0)))))) +if(AE44="Stealth",Vlookup(Size,SizeTable,6,False))),"") | BE44: ring
AD45: =IF(OR( iferror(vlookup($AE$2, 'Class Skills'!$A:$BE,MATCH(AE45,'Class Skills'!$1:$1,0),false),"")="X", iferror(vlookup($AE$3, 'Class Skills'!$A:$BE,MATCH(AE45,'Class Skills'!$1:$1,0),false),"")="X", iferror(vlookup($AE$4, 'Class Skills'!$A:$BE,MATCH(AE45,'Class Skills'!$1:$1,0),false),"")="X", iferror(vlookup(#REF!, 'Class Skills'!$A:$BE,MATCH(AE45,'Class Skills'!$1:$1,0),false),"")="X"),"X",) -> X | AE45: Perform: | AI45: =HLOOKUP(AE45,'Class Skills'!$1:$3,3,false) -> Cha | AJ45: =if(AND(HLOOKUP(AE45,'Class Skills'!$1:$2,2,false)="Trained Only",AL45<1),,SUM(AL45:AQ45)) -> 0 | AK45: = | AM45: =IFERROR(__xludf.DUMMYFUNCTION("offset($E$8,match(AI45,ARRAYFORMULA(Proper(lower(REGEXEXTRACT($E$9:$E$14,""\w\w\w"")))),0),2)"),0.0) -> 0 | AN45: =if(AND(AL45 > 0,AD45 ="X"), 3, ) | AP45: =IFERROR(__xludf.DUMMYFUNCTION("if( or(arrayformula(regexmatch($AR$76:$AR$110,AE45))), sum(arrayformula(iferror(value(regexextract(filter( $AR$76:$AR$110, $K$76:$K$110=""ACTIVE"", regexmatch($AR$76:$AR$110,AE45)), ""[-\d]+"")))))+tSkill,tSkill)"),0.0) -> 0 | AQ45: =iferror(if( if(hlookup(AE45,'Class Skills'!$1:$4,4,false)="Armor Penalty",'Formula References'!$Q$156,) +if(AND(isnumber($C$38),AE45="Climb"),8,) +if(AND(isnumber($C$39),AE45="Swim"),8,) +if(AE45="Fly", Vlookup(Size,SizeTable,5,False),) +if(AE45="Fly",if($M$37="Clumsy",-8,if($M$37="Poor",-4,if($M$37="Average",0,if($M$37="Good",4,if($M$37="Perfect",8,0)))))) +if(AE45="Stealth",Vlookup(Size,SizeTable,6,False)) =0,, if(hlookup(AE45,'Class Skills'!$1:$4,4,false)="Armor Penalty",'Formula References'!$Q$156,) +if(AND(isnumber($C$38),AE45="Climb"),8,) +if(AND(isnumber($C$39),AE45="Swim"),8,) +if(AE45="Fly", Vlookup(Size,SizeTable,5,False),) +if(AE45="Fly",if($M$37="Clumsy",-8,if($M$37="Poor",-4,if($M$37="Average",0,if($M$37="Good",4,if($M$37="Perfect",8,0)))))) +if(AE45="Stealth",Vlookup(Size,SizeTable,6,False))),"") | BE45: ring
AC46: =iferror(IF(OR((HLOOKUP(#REF!,'Class Skills'!$3:$4,2,false)="Trained Only"),#REF!="T (Trained Only)"),"*",),"") | AD46: Languages:
B48: TRAITS AND DRAWBACK | N48: CLASS FEATURES | Z48: FEATS | AL48: STORY & MISC. NOTES
B49: Trait | C49: Bruising Intellect | O49: Stalker Art (Rogue Talent: Prescient Dodger) | Z49: 1st | AA49: Extra Origin Feat (Uncanny Aptitude - Nodachi) | AL49: Daayan Rajah
B50: Trait | C50: Unorthodox Method (Broken Blade -> Black Seraph) | O50: Stalker Art (Rogue Talent: Shape Veil (Izanami's Nodachi)) | Z50: Hum. | AA50: Focused Veil (Dimensional Bridge) | AL50: Soul Hunter Stakler
B51: DB | O51: Soul Claiming (Su) | Z51: 2nd | AA51: Hidden Brandweaver
B52: Trait | O52: Soulburning (Su) +1d6 | Z52: 3rd | AA52: Extra Readied Maneuver
B54: RACIAL FEATURES | O54: Daayan Veilweaving (Su)
C55: Domain Rune: Trickery | O55: Path of the Vazputrika
C56: Runic Complexity (Su) | O56: Ruler's Domain (Su) ACF
C57: Runic Dominance | O57: Actions of a Ruler (Su) ACF
O58: Strings of the Sun King (Su)
O59: Branded Vassal (Su)
O60: Empowered Brands (Su)
O61: Oppressing Presence (Su)
O62: Tyrant's Grasp (Su)
B70: EFFECT TABLE | BB70: BACKGROUND / PERSONALITY
BC71: How were you raised? Do you have any close family? | BQ71: =if(BM71=True, "Slashing","")
B72: Buff or Effect | G72: Type | K72: Active? | N72: Armor Class | P72: Saving Throws | S72: Ability Scores | Y72: Melee | AD72: Ranged | AG72: Magic | AH72: Extra Attack | AK72: Relative Size Change | AL72: Speed | AQ72: Skill Checks
N73: AC | O73: Nat | P73: Fort | Q73: Ref | R73: Will | S73: Str | T73: Dex | U73: Con | V73: Int | W73: Wis | X73: Cha | Y73: Attack | Z73: Dmg | AA73: OHD | AB73: 2HD | AC73: 1stA | AD73: Attack | AE73: Dmg | AF73: 1stA | AG73: CL | AH73: TWF | AI73: Melee | AJ73: Range | AL73: Base | AM73: Fly | AN73: Swim | AO73: Burrow | AP73: Climb | AQ73: All | AR73: Specified Skills & Initiative
